[
{"f":2637,"p":[{"hits":[],"hurts":[{"rx":-7.47,"ry":1.45,"rw":0.45,"rh":0.35,"t":3},{"rx":-7.82,"ry":0.6,"rw":0.8,"rh":0.95,"t":3},{"rx":-7.82,"ry":0.0,"rw":0.8,"rh":0.6,"t":3}],"grabs":[{"rx":-7.72,"ry":0.0,"rw":0.6,"rh":1.4,"t":4}],"clips":[{"rx":-7.72,"ry":0.0,"rw":0.6,"rh":1.4,"t":0}],"s":"0 STAND 343","x1":-7.5,"x2":-7.5,"x3":-7.5,"hit":0,"fl":0,"st":0,"c":null},{"hits":[],"hurts":[{"rx":-6.7145505,"ry":1.3,"rw":0.7,"rh":0.4,"t":3},{"rx":-6.7145505,"ry":0.0,"rw":0.7,"rh":0.55,"t":3},{"rx":-6.7145505,"ry":0.55,"rw":0.7,"rh":0.75,"t":3}],"grabs":[{"rx":-6.61455059,"ry":0.0,"rw":0.5,"rh":1.35,"t":4}],"clips":[{"rx":-6.61455059,"ry":0.0,"rw":0.5,"rh":1.35,"t":0}],"s":"604 5MK 1","x1":-6.36243057,"x2":-6.36455059,"x3":-6.364553,"hit":0,"fl":0,"st":32,"c":null}],"p1":[],"p2":[],"i1":2560,"i2":0},
{"f":2638,"p":[{"hits":[],"hurts":[{"rx":-8.2,"ry":1.55,"rw":1.3,"rh":0.35,"t":3},{"rx":-8.2,"ry":0.6,"rw":1.3,"rh":0.95,"t":3},{"rx":-8.2,"ry":0.0,"rw":1.3,"rh":0.6,"t":3}],"grabs":[{"rx":-7.95,"ry":0.0,"rw":0.9,"rh":1.4,"t":4}],"clips":[{"rx":-7.95,"ry":0.0,"rw":0.900000036,"rh":1.4,"t":0}],"s":"758 VT_LARIAT_CHARGE 1","x1":-7.5,"x2":-7.5,"x3":-7.5,"hit":0,"fl":0,"st":32,"c":null},{"hits":[],"hurts":[{"rx":-6.944566,"ry":1.3,"rw":0.7,"rh":0.4,"t":3},{"rx":-6.944566,"ry":0.0,"rw":0.7,"rh":0.55,"t":3},{"rx":-6.944566,"ry":0.55,"rw":0.7,"rh":0.75,"t":3}],"grabs":[{"rx":-6.844566,"ry":0.0,"rw":0.5,"rh":1.35,"t":4}],"clips":[{"rx":-6.694566,"ry":0.0,"rw":0.5,"rh":1.35,"t":0}],"s":"604 5MK 2","x1":-6.36243057,"x2":-6.444566,"x3":-6.447469,"hit":0,"fl":26,"st":32,"c":null}],"p1":[],"p2":[],"i1":0,"i2":0},
{"f":2639,"p":[{"hits":[],"hurts":[{"rx":-8.2,"ry":1.55,"rw":1.3,"rh":0.35,"t":3},{"rx":-8.2,"ry":0.6,"rw":1.3,"rh":0.95,"t":3},{"rx":-8.2,"ry":0.0,"rw":1.3,"rh":0.6,"t":3},{"rx":-8.2,"ry":1.55,"rw":1.3,"rh":0.35,"t":3},{"rx":-8.2,"ry":0.4,"rw":1.3,"rh":1.15,"t":3},{"rx":-8.2,"ry":0.0,"rw":1.3,"rh":0.4,"t":3}],"grabs":[{"rx":-7.95,"ry":0.0,"rw":0.9,"rh":1.4,"t":4}],"clips":[{"rx":-7.95,"ry":0.0,"rw":0.900000036,"rh":1.4,"t":0}],"s":"758 VT_LARIAT_CHARGE 2","x1":-7.5,"x2":-7.5,"x3":-7.5,"hit":0,"fl":115,"st":32,"c":null},{"hits":[],"hurts":[{"rx":-7.02760553,"ry":1.3,"rw":0.7,"rh":0.4,"t":3},{"rx":-7.02760553,"ry":0.0,"rw":0.7,"rh":0.55,"t":3},{"rx":-7.02760553,"ry":0.55,"rw":0.7,"rh":0.75,"t":3}],"grabs":[{"rx":-6.92760563,"ry":0.0,"rw":0.5,"rh":1.35,"t":4}],"clips":[{"rx":-6.77760553,"ry":0.0,"rw":0.5,"rh":1.35,"t":0}],"s":"604 5MK 3","x1":-6.36243057,"x2":-6.52760553,"x3":-6.52760553,"hit":0,"fl":25,"st":32,"c":null}],"p1":[],"p2":[],"i1":0,"i2":0},
{"f":2640,"p":[{"hits":[],"hurts":[{"rx":-8.2,"ry":1.55,"rw":1.3,"rh":0.35,"t":3},{"rx":-8.2,"ry":0.6,"rw":1.3,"rh":0.95,"t":3},{"rx":-8.2,"ry":0.0,"rw":1.3,"rh":0.6,"t":3},{"rx":-8.2,"ry":1.55,"rw":1.3,"rh":0.35,"t":3},{"rx":-8.2,"ry":0.4,"rw":1.3,"rh":1.15,"t":3},{"rx":-8.2,"ry":0.0,"rw":1.3,"rh":0.4,"t":3}],"grabs":[{"rx":-7.95,"ry":0.0,"rw":0.9,"rh":1.4,"t":4}],"clips":[{"rx":-7.95,"ry":0.0,"rw":0.900000036,"rh":1.4,"t":0}],"s":"758 VT_LARIAT_CHARGE 3","x1":-7.5,"x2":-7.5,"x3":-7.5,"hit":0,"fl":114,"st":32,"c":null},{"hits":[],"hurts":[{"rx":-7.138839,"ry":1.3,"rw":0.7,"rh":0.4,"t":3},{"rx":-7.138839,"ry":0.0,"rw":0.7,"rh":0.55,"t":3},{"rx":-7.138839,"ry":0.55,"rw":0.7,"rh":0.75,"t":3}],"grabs":[{"rx":-7.038839,"ry":0.0,"rw":0.5,"rh":1.35,"t":4}],"clips":[{"rx":-6.888839,"ry":0.0,"rw":0.5,"rh":1.35,"t":0}],"s":"604 5MK 4","x1":-6.36243057,"x2":-6.638839,"x3":-6.63883829,"hit":0,"fl":24,"st":32,"c":null}],"p1":[],"p2":[],"i1":0,"i2":0},
{"f":2641,"p":[{"hits":[],"hurts":[{"rx":-8.2,"ry":1.55,"rw":1.3,"rh":0.35,"t":3},{"rx":-8.2,"ry":0.6,"rw":1.3,"rh":0.95,"t":3},{"rx":-8.2,"ry":0.0,"rw":1.3,"rh":0.6,"t":3},{"rx":-8.2,"ry":1.55,"rw":1.3,"rh":0.35,"t":3},{"rx":-8.2,"ry":0.4,"rw":1.3,"rh":1.15,"t":3},{"rx":-8.2,"ry":0.0,"rw":1.3,"rh":0.4,"t":3}],"grabs":[{"rx":-7.95,"ry":0.0,"rw":0.9,"rh":1.4,"t":4}],"clips":[{"rx":-7.95,"ry":0.0,"rw":0.900000036,"rh":1.4,"t":0}],"s":"758 VT_LARIAT_CHARGE 4","x1":-7.5,"x2":-7.5,"x3":-7.5,"hit":0,"fl":113,"st":32,"c":null},{"hits":[],"hurts":[{"rx":-7.24509144,"ry":1.3,"rw":0.7,"rh":0.4,"t":3},{"rx":-7.24509144,"ry":0.0,"rw":0.7,"rh":0.55,"t":3},{"rx":-7.24509144,"ry":0.55,"rw":0.7,"rh":0.75,"t":3}],"grabs":[{"rx":-7.14509153,"ry":0.0,"rw":0.5,"rh":1.35,"t":4}],"clips":[{"rx":-6.99509144,"ry":0.0,"rw":0.5,"rh":1.35,"t":0}],"s":"604 5MK 5","x1":-6.36243057,"x2":-6.74509144,"x3":-6.7511816,"hit":0,"fl":23,"st":32,"c":null}],"p1":[],"p2":[],"i1":0,"i2":0},
{"f":2642,"p":[{"hits":[],"hurts":[{"rx":-8.2,"ry":1.55,"rw":1.3,"rh":0.35,"t":3},{"rx":-8.2,"ry":0.6,"rw":1.3,"rh":0.95,"t":3},{"rx":-8.2,"ry":0.0,"rw":1.3,"rh":0.6,"t":3},{"rx":-8.2,"ry":1.55,"rw":1.3,"rh":0.35,"t":3},{"rx":-8.2,"ry":0.4,"rw":1.3,"rh":1.15,"t":3},{"rx":-8.2,"ry":0.0,"rw":1.3,"rh":0.4,"t":3}],"grabs":[{"rx":-7.95,"ry":0.0,"rw":0.9,"rh":1.4,"t":4}],"clips":[{"rx":-7.95,"ry":0.0,"rw":0.900000036,"rh":1.4,"t":0}],"s":"758 VT_LARIAT_CHARGE 5","x1":-7.5,"x2":-7.5,"x3":-7.5,"hit":0,"fl":112,"st":32,"c":null},{"hits":[],"hurts":[{"rx":-7.29999971,"ry":1.3,"rw":0.7,"rh":0.4,"t":3},{"rx":-7.29999971,"ry":0.0,"rw":0.7,"rh":0.55,"t":3},{"rx":-7.29999971,"ry":0.55,"rw":0.7,"rh":0.75,"t":3}],"grabs":[{"rx":-7.2,"ry":0.0,"rw":0.5,"rh":1.35,"t":4}],"clips":[{"rx":-7.04999971,"ry":0.0,"rw":0.5,"rh":1.35,"t":0}],"s":"604 5MK 6","x1":-6.356434,"x2":-6.79999971,"x3":-6.84784365,"hit":0,"fl":22,"st":32,"c":null}],"p1":[],"p2":[],"i1":0,"i2":0},
{"f":2643,"p":[{"hits":[],"hurts":[{"rx":-8.2,"ry":1.55,"rw":1.3,"rh":0.35,"t":3},{"rx":-8.2,"ry":0.6,"rw":1.3,"rh":0.95,"t":3},{"rx":-8.2,"ry":0.0,"rw":1.3,"rh":0.6,"t":3},{"rx":-8.2,"ry":1.55,"rw":1.3,"rh":0.35,"t":3},{"rx":-8.2,"ry":0.4,"rw":1.3,"rh":1.15,"t":3},{"rx":-8.2,"ry":0.0,"rw":1.3,"rh":0.4,"t":3}],"grabs":[{"rx":-7.95,"ry":0.0,"rw":0.9,"rh":1.4,"t":4}],"clips":[{"rx":-7.95,"ry":0.0,"rw":0.900000036,"rh":1.4,"t":0}],"s":"758 VT_LARIAT_CHARGE 6","x1":-7.5,"x2":-7.5,"x3":-7.5,"hit":0,"fl":111,"st":32,"c":null},{"hits":[],"hurts":[{"rx":-7.299999,"ry":1.3,"rw":0.7,"rh":0.4,"t":3},{"rx":-7.299999,"ry":0.0,"rw":0.7,"rh":0.55,"t":3},{"rx":-7.299999,"ry":0.55,"rw":0.7,"rh":0.75,"t":3}],"grabs":[{"rx":-7.19999933,"ry":0.0,"rw":0.5,"rh":1.35,"t":4}],"clips":[{"rx":-7.049999,"ry":0.0,"rw":0.5,"rh":1.35,"t":0}],"s":"604 5MK 7","x1":-6.335924,"x2":-6.799999,"x3":-6.915804,"hit":0,"fl":21,"st":32,"c":null}],"p1":[],"p2":[],"i1":0,"i2":0},
{"f":2644,"p":[{"hits":[],"hurts":[{"rx":-8.2,"ry":1.55,"rw":1.3,"rh":0.35,"t":3},{"rx":-8.2,"ry":0.6,"rw":1.3,"rh":0.95,"t":3},{"rx":-8.2,"ry":0.0,"rw":1.3,"rh":0.6,"t":3},{"rx":-8.2,"ry":1.55,"rw":1.3,"rh":0.35,"t":3},{"rx":-8.2,"ry":0.4,"rw":1.3,"rh":1.15,"t":3},{"rx":-8.2,"ry":0.0,"rw":1.3,"rh":0.4,"t":3}],"grabs":[{"rx":-7.95,"ry":0.0,"rw":0.9,"rh":1.4,"t":4}],"clips":[{"rx":-7.95,"ry":0.0,"rw":0.900000036,"rh":1.4,"t":0}],"s":"758 VT_LARIAT_CHARGE 7","x1":-7.5,"x2":-7.5,"x3":-7.5,"hit":0,"fl":110,"st":32,"c":null},{"hits":[{"rx":-7.84999943,"ry":1.5,"rw":0.75,"rh":0.3,"t":0,"l":0,"c":1,"e":5,"s":40,"i":8},{"rx":-7.579999,"ry":1.2,"rw":0.48,"rh":0.3,"t":0,"l":0,"c":1,"e":5,"s":40,"i":8}],"hurts":[{"rx":-7.299999,"ry":1.3,"rw":0.7,"rh":0.4,"t":3},{"rx":-7.299999,"ry":0.0,"rw":0.7,"rh":0.55,"t":3},{"rx":-7.299999,"ry":0.55,"rw":0.7,"rh":0.75,"t":3},{"rx":-7.84999943,"ry":0.9,"rw":0.55,"rh":0.7,"t":3}],"grabs":[{"rx":-7.19999933,"ry":0.0,"rw":0.5,"rh":1.35,"t":4}],"clips":[{"rx":-7.049999,"ry":0.0,"rw":0.5,"rh":1.35,"t":0}],"s":"604 5MK 8","x1":-6.239828,"x2":-6.799999,"x3":-6.852607,"hit":0,"fl":20,"st":0,"c":null}],"p1":[],"p2":[],"i1":0,"i2":0},
{"f":2645,"p":[{"hits":[],"hurts":[],"grabs":[],"clips":[{"rx":-7.65,"ry":0.0,"rw":0.6,"rh":1.4,"t":0}],"s":"744 VT_broking_HIGH_1 1","x1":-7.5,"x2":-7.5,"x3":-7.5,"hit":0,"fl":109,"st":0,"c":null},{"hits":[],"hurts":[{"rx":-7.299999,"ry":1.3,"rw":0.7,"rh":0.4,"t":3},{"rx":-7.299999,"ry":0.0,"rw":0.7,"rh":0.55,"t":3},{"rx":-7.299999,"ry":0.55,"rw":0.7,"rh":0.75,"t":3},{"rx":-7.84999943,"ry":0.9,"rw":0.55,"rh":0.7,"t":3}],"grabs":[{"rx":-7.19999933,"ry":0.0,"rw":0.5,"rh":1.35,"t":4}],"clips":[{"rx":-7.049999,"ry":0.0,"rw":0.5,"rh":1.35,"t":0}],"s":"604 5MK 8","x1":-6.239828,"x2":-6.799999,"x3":-6.82760668,"hit":0,"fl":37,"st":0,"c":null}],"p1":[],"p2":[],"i1":0,"i2":0},
{"f":2646,"p":[{"hits":[],"hurts":[{"rx":-7.8,"ry":0.6,"rw":0.9,"rh":0.95,"t":1},{"rx":-7.8,"ry":0.0,"rw":0.9,"rh":0.6,"t":1}],"grabs":[{"rx":-7.65,"ry":0.0,"rw":0.6,"rh":1.4,"t":4}],"clips":[{"rx":-7.65,"ry":0.0,"rw":0.6,"rh":1.4,"t":0}],"s":"744 VT_broking_HIGH_1 2","x1":-7.5,"x2":-7.5,"x3":-7.5,"hit":0,"fl":22,"st":0,"c":null},{"hits":[],"hurts":[{"rx":-7.299999,"ry":1.3,"rw":0.7,"rh":0.4,"t":3},{"rx":-7.299999,"ry":0.0,"rw":0.7,"rh":0.55,"t":3},{"rx":-7.299999,"ry":0.55,"rw":0.7,"rh":0.75,"t":3},{"rx":-7.84999943,"ry":0.9,"rw":0.55,"rh":0.7,"t":3}],"grabs":[{"rx":-7.19999933,"ry":0.0,"rw":0.5,"rh":1.35,"t":4}],"clips":[{"rx":-7.049999,"ry":0.0,"rw":0.5,"rh":1.35,"t":0}],"s":"604 5MK 8","x1":-6.239828,"x2":-6.799999,"x3":-6.87739229,"hit":0,"fl":36,"st":0,"c":null}],"p1":[],"p2":[],"i1":0,"i2":0},
{"f":2647,"p":[{"hits":[],"hurts":[{"rx":-7.8,"ry":0.6,"rw":0.9,"rh":0.95,"t":1},{"rx":-7.8,"ry":0.0,"rw":0.9,"rh":0.6,"t":1}],"grabs":[{"rx":-7.65,"ry":0.0,"rw":0.6,"rh":1.4,"t":4}],"clips":[{"rx":-7.65,"ry":0.0,"rw":0.6,"rh":1.4,"t":0}],"s":"744 VT_broking_HIGH_1 3","x1":-7.5,"x2":-7.5,"x3":-7.5,"hit":0,"fl":21,"st":0,"c":null},{"hits":[],"hurts":[{"rx":-7.299999,"ry":1.3,"rw":0.7,"rh":0.4,"t":3},{"rx":-7.299999,"ry":0.0,"rw":0.7,"rh":0.55,"t":3},{"rx":-7.299999,"ry":0.55,"rw":0.7,"rh":0.75,"t":3},{"rx":-7.84999943,"ry":0.9,"rw":0.55,"rh":0.7,"t":3}],"grabs":[{"rx":-7.19999933,"ry":0.0,"rw":0.5,"rh":1.35,"t":4}],"clips":[{"rx":-7.049999,"ry":0.0,"rw":0.5,"rh":1.35,"t":0}],"s":"604 5MK 8","x1":-6.239828,"x2":-6.799999,"x3":-6.82845831,"hit":0,"fl":35,"st":0,"c":null}],"p1":[],"p2":[],"i1":0,"i2":0},
{"f":2648,"p":[{"hits":[],"hurts":[{"rx":-7.8,"ry":0.6,"rw":0.9,"rh":0.95,"t":1},{"rx":-7.8,"ry":0.0,"rw":0.9,"rh":0.6,"t":1}],"grabs":[{"rx":-7.65,"ry":0.0,"rw":0.6,"rh":1.4,"t":4}],"clips":[{"rx":-7.65,"ry":0.0,"rw":0.6,"rh":1.4,"t":0}],"s":"744 VT_broking_HIGH_1 4","x1":-7.5,"x2":-7.5,"x3":-7.5,"hit":0,"fl":20,"st":0,"c":null},{"hits":[],"hurts":[{"rx":-7.299999,"ry":1.3,"rw":0.7,"rh":0.4,"t":3},{"rx":-7.299999,"ry":0.0,"rw":0.7,"rh":0.55,"t":3},{"rx":-7.299999,"ry":0.55,"rw":0.7,"rh":0.75,"t":3},{"rx":-7.84999943,"ry":0.9,"rw":0.55,"rh":0.7,"t":3}],"grabs":[{"rx":-7.19999933,"ry":0.0,"rw":0.5,"rh":1.35,"t":4}],"clips":[{"rx":-7.049999,"ry":0.0,"rw":0.5,"rh":1.35,"t":0}],"s":"604 5MK 8","x1":-6.239828,"x2":-6.799999,"x3":-6.875704,"hit":0,"fl":34,"st":0,"c":null}],"p1":[],"p2":[],"i1":0,"i2":0},
{"f":2649,"p":[{"hits":[],"hurts":[{"rx":-7.8,"ry":0.6,"rw":0.9,"rh":0.95,"t":1},{"rx":-7.8,"ry":0.0,"rw":0.9,"rh":0.6,"t":1}],"grabs":[{"rx":-7.65,"ry":0.0,"rw":0.6,"rh":1.4,"t":4}],"clips":[{"rx":-7.65,"ry":0.0,"rw":0.6,"rh":1.4,"t":0}],"s":"744 VT_broking_HIGH_1 5","x1":-7.5,"x2":-7.5,"x3":-7.5,"hit":0,"fl":19,"st":0,"c":null},{"hits":[],"hurts":[{"rx":-7.299999,"ry":1.3,"rw":0.7,"rh":0.4,"t":3},{"rx":-7.299999,"ry":0.0,"rw":0.7,"rh":0.55,"t":3},{"rx":-7.299999,"ry":0.55,"rw":0.7,"rh":0.75,"t":3},{"rx":-7.84999943,"ry":0.9,"rw":0.55,"rh":0.7,"t":3}],"grabs":[{"rx":-7.19999933,"ry":0.0,"rw":0.5,"rh":1.35,"t":4}],"clips":[{"rx":-7.049999,"ry":0.0,"rw":0.5,"rh":1.35,"t":0}],"s":"604 5MK 8","x1":-6.239828,"x2":-6.799999,"x3":-6.83095551,"hit":0,"fl":33,"st":0,"c":null}],"p1":[],"p2":[],"i1":0,"i2":0},
{"f":2650,"p":[{"hits":[],"hurts":[{"rx":-7.8,"ry":0.6,"rw":0.9,"rh":0.95,"t":1},{"rx":-7.8,"ry":0.0,"rw":0.9,"rh":0.6,"t":1}],"grabs":[{"rx":-7.65,"ry":0.0,"rw":0.6,"rh":1.4,"t":4}],"clips":[{"rx":-7.65,"ry":0.0,"rw":0.6,"rh":1.4,"t":0}],"s":"744 VT_broking_HIGH_1 6","x1":-7.5,"x2":-7.5,"x3":-7.5,"hit":0,"fl":18,"st":0,"c":null},{"hits":[],"hurts":[{"rx":-7.299999,"ry":1.3,"rw":0.7,"rh":0.4,"t":3},{"rx":-7.299999,"ry":0.0,"rw":0.7,"rh":0.55,"t":3},{"rx":-7.299999,"ry":0.55,"rw":0.7,"rh":0.75,"t":3},{"rx":-7.84999943,"ry":0.9,"rw":0.55,"rh":0.7,"t":3}],"grabs":[{"rx":-7.19999933,"ry":0.0,"rw":0.5,"rh":1.35,"t":4}],"clips":[{"rx":-7.049999,"ry":0.0,"rw":0.5,"rh":1.35,"t":0}],"s":"604 5MK 8","x1":-6.239828,"x2":-6.799999,"x3":-6.872441,"hit":0,"fl":32,"st":0,"c":null}],"p1":[],"p2":[],"i1":0,"i2":0},
{"f":2651,"p":[{"hits":[],"hurts":[{"rx":-7.8,"ry":0.6,"rw":0.9,"rh":0.95,"t":1},{"rx":-7.8,"ry":0.0,"rw":0.9,"rh":0.6,"t":1}],"grabs":[{"rx":-7.65,"ry":0.0,"rw":0.6,"rh":1.4,"t":4}],"clips":[{"rx":-7.65,"ry":0.0,"rw":0.6,"rh":1.4,"t":0}],"s":"744 VT_broking_HIGH_1 7","x1":-7.5,"x2":-7.5,"x3":-7.5,"hit":0,"fl":17,"st":0,"c":null},{"hits":[],"hurts":[{"rx":-7.299999,"ry":1.3,"rw":0.7,"rh":0.4,"t":3},{"rx":-7.299999,"ry":0.0,"rw":0.7,"rh":0.55,"t":3},{"rx":-7.299999,"ry":0.55,"rw":0.7,"rh":0.75,"t":3},{"rx":-7.84999943,"ry":0.9,"rw":0.55,"rh":0.7,"t":3}],"grabs":[{"rx":-7.19999933,"ry":0.0,"rw":0.5,"rh":1.35,"t":4}],"clips":[{"rx":-7.049999,"ry":0.0,"rw":0.5,"rh":1.35,"t":0}],"s":"604 5MK 8","x1":-6.239828,"x2":-6.799999,"x3":-6.83492851,"hit":0,"fl":31,"st":0,"c":null}],"p1":[],"p2":[],"i1":0,"i2":0},
{"f":2652,"p":[{"hits":[],"hurts":[{"rx":-7.8,"ry":0.6,"rw":0.9,"rh":0.95,"t":1},{"rx":-7.8,"ry":0.0,"rw":0.9,"rh":0.6,"t":1}],"grabs":[{"rx":-7.65,"ry":0.0,"rw":0.6,"rh":1.4,"t":4}],"clips":[{"rx":-7.65,"ry":0.0,"rw":0.6,"rh":1.4,"t":0}],"s":"744 VT_broking_HIGH_1 8","x1":-7.5,"x2":-7.5,"x3":-7.5,"hit":0,"fl":16,"st":0,"c":null},{"hits":[],"hurts":[{"rx":-7.299999,"ry":1.3,"rw":0.7,"rh":0.4,"t":3},{"rx":-7.299999,"ry":0.0,"rw":0.7,"rh":0.55,"t":3},{"rx":-7.299999,"ry":0.55,"rw":0.7,"rh":0.75,"t":3},{"rx":-7.84999943,"ry":0.9,"rw":0.55,"rh":0.7,"t":3}],"grabs":[{"rx":-7.19999933,"ry":0.0,"rw":0.5,"rh":1.35,"t":4}],"clips":[{"rx":-7.049999,"ry":0.0,"rw":0.5,"rh":1.35,"t":0}],"s":"604 5MK 8","x1":-6.239828,"x2":-6.799999,"x3":-6.867826,"hit":0,"fl":30,"st":0,"c":null}],"p1":[],"p2":[],"i1":0,"i2":0},
{"f":2653,"p":[{"hits":[],"hurts":[{"rx":-7.8,"ry":0.6,"rw":0.9,"rh":0.95,"t":1},{"rx":-7.8,"ry":0.0,"rw":0.9,"rh":0.6,"t":1}],"grabs":[{"rx":-7.65,"ry":0.0,"rw":0.6,"rh":1.4,"t":4}],"clips":[{"rx":-7.65,"ry":0.0,"rw":0.6,"rh":1.4,"t":0}],"s":"744 VT_broking_HIGH_1 9","x1":-7.5,"x2":-7.5,"x3":-7.5,"hit":0,"fl":15,"st":0,"c":null},{"hits":[],"hurts":[{"rx":-7.299999,"ry":1.3,"rw":0.7,"rh":0.4,"t":3},{"rx":-7.299999,"ry":0.0,"rw":0.7,"rh":0.55,"t":3},{"rx":-7.299999,"ry":0.55,"rw":0.7,"rh":0.75,"t":3},{"rx":-7.84999943,"ry":0.9,"rw":0.55,"rh":0.7,"t":3}],"grabs":[{"rx":-7.19999933,"ry":0.0,"rw":0.5,"rh":1.35,"t":4}],"clips":[{"rx":-7.049999,"ry":0.0,"rw":0.5,"rh":1.35,"t":0}],"s":"604 5MK 8","x1":-6.239828,"x2":-6.799999,"x3":-6.840106,"hit":0,"fl":29,"st":0,"c":null}],"p1":[],"p2":[],"i1":0,"i2":0},
{"f":2654,"p":[{"hits":[],"hurts":[{"rx":-7.8,"ry":0.6,"rw":0.9,"rh":0.95,"t":1},{"rx":-7.8,"ry":0.0,"rw":0.9,"rh":0.6,"t":1}],"grabs":[{"rx":-7.65,"ry":0.0,"rw":0.6,"rh":1.4,"t":4}],"clips":[{"rx":-7.65,"ry":0.0,"rw":0.6,"rh":1.4,"t":0}],"s":"744 VT_broking_HIGH_1 10","x1":-7.5,"x2":-7.5,"x3":-7.5,"hit":0,"fl":14,"st":0,"c":null},{"hits":[],"hurts":[{"rx":-7.299999,"ry":1.3,"rw":0.7,"rh":0.4,"t":3},{"rx":-7.299999,"ry":0.0,"rw":0.7,"rh":0.55,"t":3},{"rx":-7.299999,"ry":0.55,"rw":0.7,"rh":0.75,"t":3},{"rx":-7.84999943,"ry":0.9,"rw":0.55,"rh":0.7,"t":3}],"grabs":[{"rx":-7.19999933,"ry":0.0,"rw":0.5,"rh":1.35,"t":4}],"clips":[{"rx":-7.049999,"ry":0.0,"rw":0.5,"rh":1.35,"t":0}],"s":"604 5MK 8","x1":-6.239828,"x2":-6.799999,"x3":-6.862174,"hit":0,"fl":28,"st":0,"c":null}],"p1":[],"p2":[],"i1":0,"i2":0},
{"f":2655,"p":[{"hits":[],"hurts":[{"rx":-7.8,"ry":0.6,"rw":0.9,"rh":0.95,"t":1},{"rx":-7.8,"ry":0.0,"rw":0.9,"rh":0.6,"t":1}],"grabs":[{"rx":-7.65,"ry":0.0,"rw":0.6,"rh":1.4,"t":4}],"clips":[{"rx":-7.65,"ry":0.0,"rw":0.6,"rh":1.4,"t":0}],"s":"744 VT_broking_HIGH_1 11","x1":-7.5,"x2":-7.5,"x3":-7.5,"hit":0,"fl":13,"st":0,"c":null},{"hits":[],"hurts":[{"rx":-7.299999,"ry":1.3,"rw":0.7,"rh":0.4,"t":3},{"rx":-7.299999,"ry":0.0,"rw":0.7,"rh":0.55,"t":3},{"rx":-7.299999,"ry":0.55,"rw":0.7,"rh":0.75,"t":3},{"rx":-7.84999943,"ry":0.9,"rw":0.55,"rh":0.7,"t":3}],"grabs":[{"rx":-7.19999933,"ry":0.0,"rw":0.5,"rh":1.35,"t":4}],"clips":[{"rx":-7.049999,"ry":0.0,"rw":0.5,"rh":1.35,"t":0}],"s":"604 5MK 8","x1":-6.239828,"x2":-6.799999,"x3":-6.84613562,"hit":0,"fl":27,"st":0,"c":null}],"p1":[],"p2":[],"i1":0,"i2":0},
{"f":2656,"p":[{"hits":[],"hurts":[{"rx":-7.8,"ry":0.6,"rw":0.9,"rh":0.95,"t":1},{"rx":-7.8,"ry":0.0,"rw":0.9,"rh":0.6,"t":1}],"grabs":[{"rx":-7.65,"ry":0.0,"rw":0.6,"rh":1.4,"t":4}],"clips":[{"rx":-7.65,"ry":0.0,"rw":0.6,"rh":1.4,"t":0}],"s":"744 VT_broking_HIGH_1 12","x1":-7.5,"x2":-7.5,"x3":-7.5,"hit":0,"fl":12,"st":0,"c":null},{"hits":[],"hurts":[{"rx":-7.299999,"ry":1.3,"rw":0.7,"rh":0.4,"t":3},{"rx":-7.299999,"ry":0.0,"rw":0.7,"rh":0.55,"t":3},{"rx":-7.299999,"ry":0.55,"rw":0.7,"rh":0.75,"t":3},{"rx":-7.84999943,"ry":0.9,"rw":0.55,"rh":0.7,"t":3}],"grabs":[{"rx":-7.19999933,"ry":0.0,"rw":0.5,"rh":1.35,"t":4}],"clips":[{"rx":-7.049999,"ry":0.0,"rw":0.5,"rh":1.35,"t":0}],"s":"604 5MK 8","x1":-6.239828,"x2":-6.799999,"x3":-6.85587025,"hit":0,"fl":26,"st":0,"c":null}],"p1":[],"p2":[],"i1":0,"i2":0},
{"f":2657,"p":[{"hits":[],"hurts":[{"rx":-7.8,"ry":0.6,"rw":0.9,"rh":0.95,"t":1},{"rx":-7.8,"ry":0.0,"rw":0.9,"rh":0.6,"t":1}],"grabs":[{"rx":-7.65,"ry":0.0,"rw":0.6,"rh":1.4,"t":4}],"clips":[{"rx":-7.65,"ry":0.0,"rw":0.6,"rh":1.4,"t":0}],"s":"744 VT_broking_HIGH_1 13","x1":-7.5,"x2":-7.5,"x3":-7.5,"hit":0,"fl":11,"st":0,"c":null},{"hits":[],"hurts":[{"rx":-7.299999,"ry":1.3,"rw":0.7,"rh":0.4,"t":3},{"rx":-7.299999,"ry":0.0,"rw":0.7,"rh":0.55,"t":3},{"rx":-7.299999,"ry":0.55,"rw":0.7,"rh":0.75,"t":3},{"rx":-7.84999943,"ry":0.9,"rw":0.55,"rh":0.7,"t":3}],"grabs":[{"rx":-7.19999933,"ry":0.0,"rw":0.5,"rh":1.35,"t":4}],"clips":[{"rx":-7.049999,"ry":0.0,"rw":0.5,"rh":1.35,"t":0}],"s":"604 5MK 8","x1":-6.239828,"x2":-6.799999,"x3":-6.852607,"hit":0,"fl":25,"st":0,"c":null}],"p1":[],"p2":[],"i1":0,"i2":0},
{"f":2658,"p":[{"hits":[],"hurts":[{"rx":-7.8,"ry":0.6,"rw":0.9,"rh":0.95,"t":1},{"rx":-7.8,"ry":0.0,"rw":0.9,"rh":0.6,"t":1}],"grabs":[{"rx":-7.65,"ry":0.0,"rw":0.6,"rh":1.4,"t":4}],"clips":[{"rx":-7.65,"ry":0.0,"rw":0.6,"rh":1.4,"t":0}],"s":"744 VT_broking_HIGH_1 14","x1":-7.5,"x2":-7.5,"x3":-7.5,"hit":0,"fl":10,"st":0,"c":null},{"hits":[],"hurts":[{"rx":-7.299999,"ry":1.3,"rw":0.7,"rh":0.4,"t":3},{"rx":-7.299999,"ry":0.0,"rw":0.7,"rh":0.55,"t":3},{"rx":-7.299999,"ry":0.55,"rw":0.7,"rh":0.75,"t":3},{"rx":-7.84999943,"ry":0.9,"rw":0.55,"rh":0.7,"t":3}],"grabs":[{"rx":-7.19999933,"ry":0.0,"rw":0.5,"rh":1.35,"t":4}],"clips":[{"rx":-7.049999,"ry":0.0,"rw":0.5,"rh":1.35,"t":0}],"s":"604 5MK 8","x1":-6.239828,"x2":-6.799999,"x3":-6.852607,"hit":0,"fl":24,"st":0,"c":null}],"p1":[],"p2":[],"i1":0,"i2":0},
{"f":2659,"p":[{"hits":[],"hurts":[{"rx":-7.8,"ry":0.6,"rw":0.9,"rh":0.95,"t":1},{"rx":-7.8,"ry":0.0,"rw":0.9,"rh":0.6,"t":1}],"grabs":[{"rx":-7.65,"ry":0.0,"rw":0.6,"rh":1.4,"t":4}],"clips":[{"rx":-7.65,"ry":0.0,"rw":0.6,"rh":1.4,"t":0}],"s":"744 VT_broking_HIGH_1 15","x1":-7.5,"x2":-7.5,"x3":-7.5,"hit":0,"fl":9,"st":0,"c":null},{"hits":[],"hurts":[{"rx":-7.299999,"ry":1.3,"rw":0.7,"rh":0.4,"t":3},{"rx":-7.299999,"ry":0.0,"rw":0.7,"rh":0.55,"t":3},{"rx":-7.299999,"ry":0.55,"rw":0.7,"rh":0.75,"t":3},{"rx":-7.84999943,"ry":0.9,"rw":0.55,"rh":0.7,"t":3}],"grabs":[{"rx":-7.19999933,"ry":0.0,"rw":0.5,"rh":1.35,"t":4}],"clips":[{"rx":-7.049999,"ry":0.0,"rw":0.5,"rh":1.35,"t":0}],"s":"604 5MK 8","x1":-6.239828,"x2":-6.799999,"x3":-6.852607,"hit":0,"fl":23,"st":0,"c":null}],"p1":[],"p2":[],"i1":0,"i2":0},
{"f":2660,"p":[{"hits":[],"hurts":[{"rx":-7.8,"ry":0.6,"rw":0.9,"rh":0.95,"t":1},{"rx":-7.8,"ry":0.0,"rw":0.9,"rh":0.6,"t":1}],"grabs":[{"rx":-7.65,"ry":0.0,"rw":0.6,"rh":1.4,"t":4}],"clips":[{"rx":-7.65,"ry":0.0,"rw":0.6,"rh":1.4,"t":0}],"s":"744 VT_broking_HIGH_1 16","x1":-7.5,"x2":-7.5,"x3":-7.5,"hit":0,"fl":8,"st":0,"c":null},{"hits":[],"hurts":[{"rx":-7.299999,"ry":1.3,"rw":0.7,"rh":0.4,"t":3},{"rx":-7.299999,"ry":0.0,"rw":0.7,"rh":0.55,"t":3},{"rx":-7.299999,"ry":0.55,"rw":0.7,"rh":0.75,"t":3},{"rx":-7.84999943,"ry":0.9,"rw":0.55,"rh":0.7,"t":3}],"grabs":[{"rx":-7.19999933,"ry":0.0,"rw":0.5,"rh":1.35,"t":4}],"clips":[{"rx":-7.049999,"ry":0.0,"rw":0.5,"rh":1.35,"t":0}],"s":"604 5MK 8","x1":-6.239828,"x2":-6.799999,"x3":-6.852607,"hit":0,"fl":22,"st":0,"c":null}],"p1":[],"p2":[],"i1":0,"i2":0},
{"f":2661,"p":[{"hits":[],"hurts":[{"rx":-7.8,"ry":1.45,"rw":0.9,"rh":0.4,"t":3},{"rx":-7.8,"ry":0.7,"rw":0.9,"rh":0.75,"t":3},{"rx":-7.8,"ry":0.0,"rw":0.9,"rh":0.7,"t":3}],"grabs":[{"rx":-7.65,"ry":0.0,"rw":0.6,"rh":1.4,"t":4}],"clips":[{"rx":-7.65,"ry":0.0,"rw":0.6,"rh":1.4,"t":0}],"s":"744 VT_broking_HIGH_1 17","x1":-7.5,"x2":-7.5,"x3":-7.5,"hit":0,"fl":7,"st":0,"c":null},{"hits":[],"hurts":[{"rx":-7.299999,"ry":1.3,"rw":0.7,"rh":0.4,"t":3},{"rx":-7.299999,"ry":0.0,"rw":0.7,"rh":0.55,"t":3},{"rx":-7.299999,"ry":0.55,"rw":0.7,"rh":0.75,"t":3},{"rx":-7.84999943,"ry":0.9,"rw":0.55,"rh":0.7,"t":3}],"grabs":[{"rx":-7.19999933,"ry":0.0,"rw":0.5,"rh":1.35,"t":4}],"clips":[{"rx":-7.049999,"ry":0.0,"rw":0.5,"rh":1.35,"t":0}],"s":"604 5MK 8","x1":-6.239828,"x2":-6.799999,"x3":-6.852607,"hit":0,"fl":21,"st":0,"c":null}],"p1":[],"p2":[],"i1":0,"i2":0},
{"f":2662,"p":[{"hits":[],"hurts":[{"rx":-7.8,"ry":1.45,"rw":0.9,"rh":0.4,"t":3},{"rx":-7.8,"ry":0.7,"rw":0.9,"rh":0.75,"t":3},{"rx":-7.8,"ry":0.0,"rw":0.9,"rh":0.7,"t":3}],"grabs":[{"rx":-7.65,"ry":0.0,"rw":0.6,"rh":1.4,"t":4}],"clips":[{"rx":-7.65,"ry":0.0,"rw":0.6,"rh":1.4,"t":0}],"s":"744 VT_broking_HIGH_1 18","x1":-7.5,"x2":-7.5,"x3":-7.5,"hit":0,"fl":6,"st":0,"c":null},{"hits":[],"hurts":[{"rx":-7.299999,"ry":1.3,"rw":0.7,"rh":0.4,"t":3},{"rx":-7.299999,"ry":0.0,"rw":0.7,"rh":0.55,"t":3},{"rx":-7.299999,"ry":0.55,"rw":0.7,"rh":0.75,"t":3},{"rx":-7.84999943,"ry":0.9,"rw":0.55,"rh":0.7,"t":3}],"grabs":[{"rx":-7.19999933,"ry":0.0,"rw":0.5,"rh":1.35,"t":4}],"clips":[{"rx":-7.049999,"ry":0.0,"rw":0.5,"rh":1.35,"t":0}],"s":"604 5MK 8","x1":-6.239828,"x2":-6.799999,"x3":-6.852607,"hit":0,"fl":20,"st":0,"c":null}],"p1":[],"p2":[],"i1":0,"i2":0},
{"f":2663,"p":[{"hits":[],"hurts":[{"rx":-7.8,"ry":1.45,"rw":0.9,"rh":0.4,"t":3},{"rx":-7.8,"ry":0.7,"rw":0.9,"rh":0.75,"t":3},{"rx":-7.8,"ry":0.0,"rw":0.9,"rh":0.7,"t":3}],"grabs":[{"rx":-7.65,"ry":0.0,"rw":0.6,"rh":1.4,"t":4}],"clips":[{"rx":-7.65,"ry":0.0,"rw":0.6,"rh":1.4,"t":0}],"s":"744 VT_broking_HIGH_1 19","x1":-7.5,"x2":-7.5,"x3":-7.5,"hit":0,"fl":5,"st":0,"c":null},{"hits":[],"hurts":[{"rx":-7.3,"ry":1.3,"rw":0.7,"rh":0.4,"t":3},{"rx":-7.3,"ry":0.0,"rw":0.7,"rh":0.55,"t":3},{"rx":-7.3,"ry":0.55,"rw":0.7,"rh":0.75,"t":3},{"rx":-7.8,"ry":0.9,"rw":0.5,"rh":0.7,"t":3}],"grabs":[{"rx":-7.20000029,"ry":0.0,"rw":0.5,"rh":1.35,"t":4}],"clips":[{"rx":-7.05,"ry":0.0,"rw":0.5,"rh":1.35,"t":0}],"s":"604 5MK 9","x1":-6.2087183,"x2":-6.8,"x3":-6.821274,"hit":0,"fl":19,"st":0,"c":null}],"p1":[],"p2":[],"i1":0,"i2":0},
{"f":2664,"p":[{"hits":[],"hurts":[{"rx":-7.8,"ry":1.45,"rw":0.9,"rh":0.4,"t":3},{"rx":-7.8,"ry":0.7,"rw":0.9,"rh":0.75,"t":3},{"rx":-7.8,"ry":0.0,"rw":0.9,"rh":0.7,"t":3}],"grabs":[{"rx":-7.65,"ry":0.0,"rw":0.6,"rh":1.4,"t":4}],"clips":[{"rx":-7.65,"ry":0.0,"rw":0.6,"rh":1.4,"t":0}],"s":"744 VT_broking_HIGH_1 20","x1":-7.5,"x2":-7.5,"x3":-7.5,"hit":0,"fl":4,"st":0,"c":null},{"hits":[],"hurts":[{"rx":-7.3,"ry":1.3,"rw":0.7,"rh":0.4,"t":3},{"rx":-7.3,"ry":0.0,"rw":0.7,"rh":0.55,"t":3},{"rx":-7.3,"ry":0.55,"rw":0.7,"rh":0.75,"t":3},{"rx":-7.70000029,"ry":0.9,"rw":0.4,"rh":0.7,"t":3}],"grabs":[{"rx":-7.20000029,"ry":0.0,"rw":0.5,"rh":1.35,"t":4}],"clips":[{"rx":-7.05,"ry":0.0,"rw":0.5,"rh":1.35,"t":0}],"s":"604 5MK 10","x1":-6.18493557,"x2":-6.8,"x3":-6.797407,"hit":0,"fl":18,"st":0,"c":null}],"p1":[],"p2":[],"i1":0,"i2":0},
{"f":2665,"p":[{"hits":[],"hurts":[{"rx":-7.8,"ry":1.45,"rw":0.9,"rh":0.4,"t":3},{"rx":-7.8,"ry":0.7,"rw":0.9,"rh":0.75,"t":3},{"rx":-7.8,"ry":0.0,"rw":0.9,"rh":0.7,"t":3}],"grabs":[{"rx":-7.65,"ry":0.0,"rw":0.6,"rh":1.4,"t":4}],"clips":[{"rx":-7.65,"ry":0.0,"rw":0.6,"rh":1.4,"t":0}],"s":"744 VT_broking_HIGH_1 21","x1":-7.5,"x2":-7.5,"x3":-7.5,"hit":0,"fl":3,"st":0,"c":null},{"hits":[],"hurts":[{"rx":-7.3,"ry":1.3,"rw":0.7,"rh":0.4,"t":3},{"rx":-7.3,"ry":0.0,"rw":0.7,"rh":0.55,"t":3},{"rx":-7.3,"ry":0.55,"rw":0.7,"rh":0.75,"t":3}],"grabs":[{"rx":-7.20000029,"ry":0.0,"rw":0.5,"rh":1.35,"t":4}],"clips":[{"rx":-7.05,"ry":0.0,"rw":0.5,"rh":1.35,"t":0}],"s":"604 5MK 11","x1":-6.163768,"x2":-6.8,"x3":-6.77634335,"hit":0,"fl":17,"st":0,"c":null}],"p1":[],"p2":[],"i1":0,"i2":0},
{"f":2666,"p":[{"hits":[],"hurts":[{"rx":-7.8,"ry":1.45,"rw":0.9,"rh":0.4,"t":3},{"rx":-7.8,"ry":0.7,"rw":0.9,"rh":0.75,"t":3},{"rx":-7.8,"ry":0.0,"rw":0.9,"rh":0.7,"t":3}],"grabs":[{"rx":-7.65,"ry":0.0,"rw":0.6,"rh":1.4,"t":4}],"clips":[{"rx":-7.65,"ry":0.0,"rw":0.6,"rh":1.4,"t":0}],"s":"744 VT_broking_HIGH_1 22","x1":-7.5,"x2":-7.5,"x3":-7.5,"hit":0,"fl":2,"st":0,"c":null},{"hits":[],"hurts":[{"rx":-7.3,"ry":1.3,"rw":0.7,"rh":0.4,"t":3},{"rx":-7.3,"ry":0.0,"rw":0.7,"rh":0.55,"t":3},{"rx":-7.3,"ry":0.55,"rw":0.7,"rh":0.75,"t":3}],"grabs":[{"rx":-7.20000029,"ry":0.0,"rw":0.5,"rh":1.35,"t":4}],"clips":[{"rx":-7.05,"ry":0.0,"rw":0.5,"rh":1.35,"t":0}],"s":"604 5MK 12","x1":-6.13898373,"x2":-6.8,"x3":-6.75178,"hit":0,"fl":16,"st":0,"c":null}],"p1":[],"p2":[],"i1":0,"i2":0},
{"f":2667,"p":[{"hits":[],"hurts":[{"rx":-7.8,"ry":1.45,"rw":0.9,"rh":0.4,"t":3},{"rx":-7.8,"ry":0.7,"rw":0.9,"rh":0.75,"t":3},{"rx":-7.8,"ry":0.0,"rw":0.9,"rh":0.7,"t":3}],"grabs":[{"rx":-7.65,"ry":0.0,"rw":0.6,"rh":1.4,"t":4}],"clips":[{"rx":-7.65,"ry":0.0,"rw":0.6,"rh":1.4,"t":0}],"s":"744 VT_broking_HIGH_1 23 IASA","x1":-7.5,"x2":-7.5,"x3":-7.5,"hit":0,"fl":1,"st":0,"c":null},{"hits":[],"hurts":[{"rx":-7.3,"ry":1.3,"rw":0.7,"rh":0.4,"t":3},{"rx":-7.3,"ry":0.0,"rw":0.7,"rh":0.55,"t":3},{"rx":-7.3,"ry":0.55,"rw":0.7,"rh":0.75,"t":3}],"grabs":[{"rx":-7.20000029,"ry":0.0,"rw":0.5,"rh":1.35,"t":4}],"clips":[{"rx":-7.05,"ry":0.0,"rw":0.5,"rh":1.35,"t":0}],"s":"604 5MK 13","x1":-6.1071825,"x2":-6.8,"x3":-6.719915,"hit":0,"fl":15,"st":0,"c":null}],"p1":[],"p2":[],"i1":0,"i2":0},
{"f":2668,"p":[{"hits":[],"hurts":[{"rx":-7.8,"ry":1.45,"rw":0.9,"rh":0.4,"t":3},{"rx":-7.8,"ry":0.7,"rw":0.9,"rh":0.75,"t":3},{"rx":-7.8,"ry":0.0,"rw":0.9,"rh":0.7,"t":3}],"grabs":[{"rx":-7.65,"ry":0.0,"rw":0.6,"rh":1.4,"t":4}],"clips":[{"rx":-7.65,"ry":0.0,"rw":0.6,"rh":1.4,"t":0}],"s":"744 VT_broking_HIGH_1 24 +","x1":-7.5,"x2":-7.5,"x3":-7.5,"hit":0,"fl":0,"st":0,"c":null},{"hits":[],"hurts":[{"rx":-7.3,"ry":1.3,"rw":0.7,"rh":0.4,"t":3},{"rx":-7.3,"ry":0.0,"rw":0.7,"rh":0.55,"t":3},{"rx":-7.3,"ry":0.55,"rw":0.7,"rh":0.75,"t":3}],"grabs":[{"rx":-7.20000029,"ry":0.0,"rw":0.5,"rh":1.35,"t":4}],"clips":[{"rx":-7.05,"ry":0.0,"rw":0.5,"rh":1.35,"t":0}],"s":"604 5MK 14","x1":-6.077758,"x2":-6.8,"x3":-6.69022751,"hit":0,"fl":14,"st":0,"c":null}],"p1":[],"p2":[],"i1":0,"i2":0},
{"f":2669,"p":[{"hits":[],"hurts":[{"rx":-7.8,"ry":1.45,"rw":0.9,"rh":0.4,"t":3},{"rx":-7.8,"ry":0.7,"rw":0.9,"rh":0.75,"t":3},{"rx":-7.8,"ry":0.0,"rw":0.9,"rh":0.7,"t":3}],"grabs":[{"rx":-7.65,"ry":0.0,"rw":0.6,"rh":1.4,"t":4}],"clips":[{"rx":-7.65,"ry":0.0,"rw":0.6,"rh":1.4,"t":0}],"s":"744 VT_broking_HIGH_1 25 +","x1":-7.5,"x2":-7.5,"x3":-7.5,"hit":0,"fl":0,"st":0,"c":null},{"hits":[],"hurts":[{"rx":-7.3,"ry":1.3,"rw":0.7,"rh":0.4,"t":3},{"rx":-7.3,"ry":0.0,"rw":0.7,"rh":0.55,"t":3},{"rx":-7.3,"ry":0.55,"rw":0.7,"rh":0.75,"t":3}],"grabs":[{"rx":-7.20000029,"ry":0.0,"rw":0.5,"rh":1.35,"t":4}],"clips":[{"rx":-7.05,"ry":0.0,"rw":0.5,"rh":1.35,"t":0}],"s":"604 5MK 15","x1":-6.05707264,"x2":-6.8,"x3":-6.669188,"hit":0,"fl":13,"st":0,"c":null}],"p1":[],"p2":[],"i1":0,"i2":0},
{"f":2670,"p":[{"hits":[],"hurts":[{"rx":-7.8,"ry":1.45,"rw":0.9,"rh":0.4,"t":3},{"rx":-7.8,"ry":0.7,"rw":0.9,"rh":0.75,"t":3},{"rx":-7.8,"ry":0.0,"rw":0.9,"rh":0.7,"t":3}],"grabs":[{"rx":-7.65,"ry":0.0,"rw":0.6,"rh":1.4,"t":4}],"clips":[{"rx":-7.65,"ry":0.0,"rw":0.6,"rh":1.4,"t":0}],"s":"744 VT_broking_HIGH_1 26 +","x1":-7.5,"x2":-7.5,"x3":-7.5,"hit":0,"fl":0,"st":0,"c":null},{"hits":[],"hurts":[{"rx":-7.3,"ry":1.3,"rw":0.7,"rh":0.4,"t":3},{"rx":-7.3,"ry":0.0,"rw":0.7,"rh":0.55,"t":3},{"rx":-7.3,"ry":0.55,"rw":0.7,"rh":0.75,"t":3}],"grabs":[{"rx":-7.20000029,"ry":0.0,"rw":0.5,"rh":1.35,"t":4}],"clips":[{"rx":-7.05,"ry":0.0,"rw":0.5,"rh":1.35,"t":0}],"s":"604 5MK 16","x1":-6.04832172,"x2":-6.8,"x3":-6.659978,"hit":0,"fl":12,"st":0,"c":null}],"p1":[],"p2":[],"i1":0,"i2":0},
{"f":2671,"p":[{"hits":[],"hurts":[{"rx":-7.8,"ry":1.45,"rw":0.9,"rh":0.4,"t":3},{"rx":-7.8,"ry":0.7,"rw":0.9,"rh":0.75,"t":3},{"rx":-7.8,"ry":0.0,"rw":0.9,"rh":0.7,"t":3}],"grabs":[{"rx":-7.65,"ry":0.0,"rw":0.6,"rh":1.4,"t":4}],"clips":[{"rx":-7.65,"ry":0.0,"rw":0.6,"rh":1.4,"t":0}],"s":"744 VT_broking_HIGH_1 27 +","x1":-7.5,"x2":-7.5,"x3":-7.5,"hit":0,"fl":0,"st":0,"c":null},{"hits":[],"hurts":[{"rx":-7.14341259,"ry":1.3,"rw":0.7,"rh":0.4,"t":3},{"rx":-7.14341259,"ry":0.0,"rw":0.7,"rh":0.55,"t":3},{"rx":-7.14341259,"ry":0.55,"rw":0.7,"rh":0.75,"t":3}],"grabs":[{"rx":-7.04341269,"ry":0.0,"rw":0.5,"rh":1.35,"t":4}],"clips":[{"rx":-7.04341269,"ry":0.0,"rw":0.5,"rh":1.35,"t":0}],"s":"604 5MK 17","x1":-6.04832172,"x2":-6.79341269,"x3":-6.65950775,"hit":0,"fl":11,"st":0,"c":null}],"p1":[],"p2":[],"i1":0,"i2":0},
{"f":2672,"p":[{"hits":[],"hurts":[{"rx":-7.8,"ry":1.45,"rw":0.9,"rh":0.4,"t":3},{"rx":-7.8,"ry":0.7,"rw":0.9,"rh":0.75,"t":3},{"rx":-7.8,"ry":0.0,"rw":0.9,"rh":0.7,"t":3}],"grabs":[{"rx":-7.65,"ry":0.0,"rw":0.6,"rh":1.4,"t":4}],"clips":[{"rx":-7.65,"ry":0.0,"rw":0.6,"rh":1.4,"t":0}],"s":"744 VT_broking_HIGH_1 28 +","x1":-7.5,"x2":-7.5,"x3":-7.5,"hit":0,"fl":0,"st":0,"c":null},{"hits":[],"hurts":[{"rx":-7.12172747,"ry":1.3,"rw":0.7,"rh":0.4,"t":3},{"rx":-7.12172747,"ry":0.0,"rw":0.7,"rh":0.55,"t":3},{"rx":-7.12172747,"ry":0.55,"rw":0.7,"rh":0.75,"t":3}],"grabs":[{"rx":-7.02172756,"ry":0.0,"rw":0.5,"rh":1.35,"t":4}],"clips":[{"rx":-7.02172756,"ry":0.0,"rw":0.5,"rh":1.35,"t":0}],"s":"604 5MK 18","x1":-6.04832172,"x2":-6.77172756,"x3":-6.659556,"hit":0,"fl":10,"st":0,"c":null}],"p1":[],"p2":[],"i1":0,"i2":0},
{"f":2673,"p":[{"hits":[],"hurts":[{"rx":-7.8,"ry":1.45,"rw":0.9,"rh":0.4,"t":3},{"rx":-7.8,"ry":0.7,"rw":0.9,"rh":0.75,"t":3},{"rx":-7.8,"ry":0.0,"rw":0.9,"rh":0.7,"t":3}],"grabs":[{"rx":-7.65,"ry":0.0,"rw":0.6,"rh":1.4,"t":4}],"clips":[{"rx":-7.65,"ry":0.0,"rw":0.6,"rh":1.4,"t":0}],"s":"744 VT_broking_HIGH_1 29 +","x1":-7.5,"x2":-7.5,"x3":-7.5,"hit":0,"fl":0,"st":0,"c":null},{"hits":[],"hurts":[{"rx":-7.10164165,"ry":1.3,"rw":0.7,"rh":0.4,"t":3},{"rx":-7.10164165,"ry":0.0,"rw":0.7,"rh":0.55,"t":3},{"rx":-7.10164165,"ry":0.55,"rw":0.7,"rh":0.75,"t":3}],"grabs":[{"rx":-7.00164175,"ry":0.0,"rw":0.5,"rh":1.35,"t":4}],"clips":[{"rx":-7.00164175,"ry":0.0,"rw":0.5,"rh":1.35,"t":0}],"s":"604 5MK 19","x1":-6.04832172,"x2":-6.75164175,"x3":-6.65955544,"hit":0,"fl":9,"st":0,"c":null}],"p1":[],"p2":[],"i1":0,"i2":0},
{"f":2674,"p":[{"hits":[],"hurts":[{"rx":-7.8,"ry":1.45,"rw":0.9,"rh":0.4,"t":3},{"rx":-7.8,"ry":0.7,"rw":0.9,"rh":0.75,"t":3},{"rx":-7.8,"ry":0.0,"rw":0.9,"rh":0.7,"t":3}],"grabs":[{"rx":-7.65,"ry":0.0,"rw":0.6,"rh":1.4,"t":4}],"clips":[{"rx":-7.65,"ry":0.0,"rw":0.6,"rh":1.4,"t":0}],"s":"744 VT_broking_HIGH_1 30 +","x1":-7.5,"x2":-7.5,"x3":-7.5,"hit":0,"fl":0,"st":0,"c":null},{"hits":[],"hurts":[{"rx":-7.08170557,"ry":1.3,"rw":0.7,"rh":0.4,"t":3},{"rx":-7.08170557,"ry":0.0,"rw":0.7,"rh":0.55,"t":3},{"rx":-7.08170557,"ry":0.55,"rw":0.7,"rh":0.75,"t":3}],"grabs":[{"rx":-6.98170567,"ry":0.0,"rw":0.5,"rh":1.35,"t":4}],"clips":[{"rx":-6.98170567,"ry":0.0,"rw":0.5,"rh":1.35,"t":0}],"s":"604 5MK 20","x1":-6.04832172,"x2":-6.73170567,"x3":-6.659708,"hit":0,"fl":8,"st":0,"c":null}],"p1":[],"p2":[],"i1":0,"i2":0},
{"f":2675,"p":[{"hits":[],"hurts":[{"rx":-7.8,"ry":1.45,"rw":0.9,"rh":0.4,"t":3},{"rx":-7.8,"ry":0.7,"rw":0.9,"rh":0.75,"t":3},{"rx":-7.8,"ry":0.0,"rw":0.9,"rh":0.7,"t":3}],"grabs":[{"rx":-7.65,"ry":0.0,"rw":0.6,"rh":1.4,"t":4}],"clips":[{"rx":-7.65,"ry":0.0,"rw":0.6,"rh":1.4,"t":0}],"s":"744 VT_broking_HIGH_1 31 +","x1":-7.5,"x2":-7.5,"x3":-7.5,"hit":0,"fl":0,"st":0,"c":null},{"hits":[],"hurts":[{"rx":-7.06673145,"ry":1.3,"rw":0.7,"rh":0.4,"t":3},{"rx":-7.06673145,"ry":0.0,"rw":0.7,"rh":0.55,"t":3},{"rx":-7.06673145,"ry":0.55,"rw":0.7,"rh":0.75,"t":3}],"grabs":[{"rx":-6.96673155,"ry":0.0,"rw":0.5,"rh":1.35,"t":4}],"clips":[{"rx":-6.96673155,"ry":0.0,"rw":0.5,"rh":1.35,"t":0}],"s":"604 5MK 21","x1":-6.04832172,"x2":-6.71673155,"x3":-6.65982246,"hit":0,"fl":7,"st":0,"c":null}],"p1":[],"p2":[],"i1":0,"i2":0},
{"f":2676,"p":[{"hits":[],"hurts":[{"rx":-7.8,"ry":1.45,"rw":0.9,"rh":0.4,"t":3},{"rx":-7.8,"ry":0.7,"rw":0.9,"rh":0.75,"t":3},{"rx":-7.8,"ry":0.0,"rw":0.9,"rh":0.7,"t":3}],"grabs":[{"rx":-7.65,"ry":0.0,"rw":0.6,"rh":1.4,"t":4}],"clips":[{"rx":-7.65,"ry":0.0,"rw":0.6,"rh":1.4,"t":0}],"s":"744 VT_broking_HIGH_1 32 +","x1":-7.5,"x2":-7.5,"x3":-7.5,"hit":0,"fl":0,"st":0,"c":null},{"hits":[],"hurts":[{"rx":-7.05552149,"ry":1.3,"rw":0.7,"rh":0.4,"t":3},{"rx":-7.05552149,"ry":0.0,"rw":0.7,"rh":0.55,"t":3},{"rx":-7.05552149,"ry":0.55,"rw":0.7,"rh":0.75,"t":3}],"grabs":[{"rx":-6.95552158,"ry":0.0,"rw":0.5,"rh":1.35,"t":4}],"clips":[{"rx":-6.95552158,"ry":0.0,"rw":0.5,"rh":1.35,"t":0}],"s":"604 5MK 22","x1":-6.04832172,"x2":-6.70552158,"x3":-6.65986633,"hit":0,"fl":6,"st":0,"c":null}],"p1":[],"p2":[],"i1":0,"i2":0},
{"f":2677,"p":[{"hits":[],"hurts":[{"rx":-7.8,"ry":1.45,"rw":0.9,"rh":0.4,"t":3},{"rx":-7.8,"ry":0.7,"rw":0.9,"rh":0.75,"t":3},{"rx":-7.8,"ry":0.0,"rw":0.9,"rh":0.7,"t":3}],"grabs":[{"rx":-7.65,"ry":0.0,"rw":0.6,"rh":1.4,"t":4}],"clips":[{"rx":-7.65,"ry":0.0,"rw":0.6,"rh":1.4,"t":0}],"s":"744 VT_broking_HIGH_1 33 +","x1":-7.5,"x2":-7.5,"x3":-7.5,"hit":0,"fl":0,"st":0,"c":null},{"hits":[],"hurts":[{"rx":-7.04574966,"ry":1.3,"rw":0.7,"rh":0.4,"t":3},{"rx":-7.04574966,"ry":0.0,"rw":0.7,"rh":0.55,"t":3},{"rx":-7.04574966,"ry":0.55,"rw":0.7,"rh":0.75,"t":3}],"grabs":[{"rx":-6.94574976,"ry":0.0,"rw":0.5,"rh":1.35,"t":4}],"clips":[{"rx":-6.94574976,"ry":0.0,"rw":0.5,"rh":1.35,"t":0}],"s":"604 5MK 23","x1":-6.04832172,"x2":-6.69574976,"x3":-6.65986729,"hit":0,"fl":5,"st":0,"c":null}],"p1":[],"p2":[],"i1":0,"i2":0},
{"f":2678,"p":[{"hits":[],"hurts":[{"rx":-7.8,"ry":1.45,"rw":0.9,"rh":0.4,"t":3},{"rx":-7.8,"ry":0.7,"rw":0.9,"rh":0.75,"t":3},{"rx":-7.8,"ry":0.0,"rw":0.9,"rh":0.7,"t":3}],"grabs":[{"rx":-7.65,"ry":0.0,"rw":0.6,"rh":1.4,"t":4}],"clips":[{"rx":-7.65,"ry":0.0,"rw":0.6,"rh":1.4,"t":0}],"s":"744 VT_broking_HIGH_1 34 +","x1":-7.5,"x2":-7.5,"x3":-7.5,"hit":0,"fl":0,"st":0,"c":null},{"hits":[],"hurts":[{"rx":-7.035969,"ry":1.3,"rw":0.7,"rh":0.4,"t":3},{"rx":-7.035969,"ry":0.0,"rw":0.7,"rh":0.55,"t":3},{"rx":-7.035969,"ry":0.55,"rw":0.7,"rh":0.75,"t":3}],"grabs":[{"rx":-6.935969,"ry":0.0,"rw":0.5,"rh":1.35,"t":4}],"clips":[{"rx":-6.935969,"ry":0.0,"rw":0.5,"rh":1.35,"t":0}],"s":"604 5MK 24","x1":-6.04832172,"x2":-6.685969,"x3":-6.659858,"hit":0,"fl":4,"st":0,"c":null}],"p1":[],"p2":[],"i1":0,"i2":0},
{"f":2679,"p":[{"hits":[],"hurts":[{"rx":-7.8,"ry":1.45,"rw":0.9,"rh":0.4,"t":3},{"rx":-7.8,"ry":0.7,"rw":0.9,"rh":0.75,"t":3},{"rx":-7.8,"ry":0.0,"rw":0.9,"rh":0.7,"t":3}],"grabs":[{"rx":-7.65,"ry":0.0,"rw":0.6,"rh":1.4,"t":4}],"clips":[{"rx":-7.65,"ry":0.0,"rw":0.6,"rh":1.4,"t":0}],"s":"744 VT_broking_HIGH_1 35 +","x1":-7.5,"x2":-7.5,"x3":-7.5,"hit":0,"fl":0,"st":0,"c":null},{"hits":[],"hurts":[{"rx":-7.02589941,"ry":1.3,"rw":0.7,"rh":0.4,"t":3},{"rx":-7.02589941,"ry":0.0,"rw":0.7,"rh":0.55,"t":3},{"rx":-7.02589941,"ry":0.55,"rw":0.7,"rh":0.75,"t":3}],"grabs":[{"rx":-6.92589951,"ry":0.0,"rw":0.5,"rh":1.35,"t":4}],"clips":[{"rx":-6.92589951,"ry":0.0,"rw":0.5,"rh":1.35,"t":0}],"s":"604 5MK 25","x1":-6.04832172,"x2":-6.67589951,"x3":-6.65985441,"hit":0,"fl":3,"st":0,"c":null}],"p1":[],"p2":[],"i1":0,"i2":0},
{"f":2680,"p":[{"hits":[],"hurts":[{"rx":-7.8,"ry":1.45,"rw":0.9,"rh":0.4,"t":3},{"rx":-7.8,"ry":0.7,"rw":0.9,"rh":0.75,"t":3},{"rx":-7.8,"ry":0.0,"rw":0.9,"rh":0.7,"t":3}],"grabs":[{"rx":-7.65,"ry":0.0,"rw":0.6,"rh":1.4,"t":4}],"clips":[{"rx":-7.65,"ry":0.0,"rw":0.6,"rh":1.4,"t":0}],"s":"744 VT_broking_HIGH_1 36 +","x1":-7.5,"x2":-7.5,"x3":-7.5,"hit":0,"fl":0,"st":0,"c":null},{"hits":[],"hurts":[{"rx":-7.01578045,"ry":1.3,"rw":0.7,"rh":0.4,"t":3},{"rx":-7.01578045,"ry":0.0,"rw":0.7,"rh":0.55,"t":3},{"rx":-7.01578045,"ry":0.55,"rw":0.7,"rh":0.75,"t":3}],"grabs":[{"rx":-6.91578054,"ry":0.0,"rw":0.5,"rh":1.35,"t":4}],"clips":[{"rx":-6.91578054,"ry":0.0,"rw":0.5,"rh":1.35,"t":0}],"s":"604 5MK 26","x1":-6.04832172,"x2":-6.66578054,"x3":-6.659908,"hit":0,"fl":2,"st":0,"c":null}],"p1":[],"p2":[],"i1":0,"i2":0},
{"f":2681,"p":[{"hits":[],"hurts":[{"rx":-7.8,"ry":1.45,"rw":0.9,"rh":0.4,"t":3},{"rx":-7.8,"ry":0.7,"rw":0.9,"rh":0.75,"t":3},{"rx":-7.8,"ry":0.0,"rw":0.9,"rh":0.7,"t":3}],"grabs":[{"rx":-7.65,"ry":0.0,"rw":0.6,"rh":1.4,"t":4}],"clips":[{"rx":-7.65,"ry":0.0,"rw":0.6,"rh":1.4,"t":0}],"s":"744 VT_broking_HIGH_1 37 +","x1":-7.5,"x2":-7.5,"x3":-7.5,"hit":0,"fl":0,"st":0,"c":null},{"hits":[],"hurts":[{"rx":-7.00749159,"ry":1.3,"rw":0.7,"rh":0.4,"t":3},{"rx":-7.00749159,"ry":0.0,"rw":0.7,"rh":0.55,"t":3},{"rx":-7.00749159,"ry":0.55,"rw":0.7,"rh":0.75,"t":3}],"grabs":[{"rx":-6.90749168,"ry":0.0,"rw":0.5,"rh":1.35,"t":4}],"clips":[{"rx":-6.90749168,"ry":0.0,"rw":0.5,"rh":1.35,"t":0}],"s":"604 5MK 27 IASA","x1":-6.04832172,"x2":-6.65749168,"x3":-6.66002226,"hit":0,"fl":1,"st":0,"c":null}],"p1":[],"p2":[],"i1":0,"i2":0},
{"f":2682,"p":[{"hits":[],"hurts":[{"rx":-7.8,"ry":1.45,"rw":0.9,"rh":0.4,"t":3},{"rx":-7.8,"ry":0.7,"rw":0.9,"rh":0.75,"t":3},{"rx":-7.8,"ry":0.0,"rw":0.9,"rh":0.7,"t":3}],"grabs":[{"rx":-7.65,"ry":0.0,"rw":0.6,"rh":1.4,"t":4}],"clips":[{"rx":-7.65,"ry":0.0,"rw":0.6,"rh":1.4,"t":0}],"s":"744 VT_broking_HIGH_1 38 +","x1":-7.5,"x2":-7.5,"x3":-7.5,"hit":0,"fl":0,"st":0,"c":null},{"hits":[],"hurts":[{"rx":-7.00302458,"ry":1.3,"rw":0.7,"rh":0.4,"t":3},{"rx":-7.00302458,"ry":0.0,"rw":0.7,"rh":0.55,"t":3},{"rx":-7.00302458,"ry":0.55,"rw":0.7,"rh":0.75,"t":3}],"grabs":[{"rx":-6.90302467,"ry":0.0,"rw":0.5,"rh":1.35,"t":4}],"clips":[{"rx":-6.90302467,"ry":0.0,"rw":0.5,"rh":1.35,"t":0}],"s":"604 5MK 28 +","x1":-6.04832172,"x2":-6.65302467,"x3":-6.660124,"hit":0,"fl":0,"st":0,"c":null}],"p1":[],"p2":[],"i1":0,"i2":0},
{"f":2683,"p":[{"hits":[],"hurts":[{"rx":-7.8,"ry":1.45,"rw":0.9,"rh":0.4,"t":3},{"rx":-7.8,"ry":0.7,"rw":0.9,"rh":0.75,"t":3},{"rx":-7.8,"ry":0.0,"rw":0.9,"rh":0.7,"t":3}],"grabs":[{"rx":-7.65,"ry":0.0,"rw":0.6,"rh":1.4,"t":4}],"clips":[{"rx":-7.65,"ry":0.0,"rw":0.6,"rh":1.4,"t":0}],"s":"744 VT_broking_HIGH_1 39 +","x1":-7.5,"x2":-7.5,"x3":-7.5,"hit":0,"fl":0,"st":0,"c":null},{"hits":[],"hurts":[{"rx":-7.00195837,"ry":1.3,"rw":0.7,"rh":0.4,"t":3},{"rx":-7.00195837,"ry":0.0,"rw":0.7,"rh":0.55,"t":3},{"rx":-7.00195837,"ry":0.55,"rw":0.7,"rh":0.75,"t":3}],"grabs":[{"rx":-6.90195847,"ry":0.0,"rw":0.5,"rh":1.35,"t":4}],"clips":[{"rx":-6.90195847,"ry":0.0,"rw":0.5,"rh":1.35,"t":0}],"s":"604 5MK 29 +","x1":-6.04832172,"x2":-6.65195847,"x3":-6.660286,"hit":0,"fl":0,"st":0,"c":null}],"p1":[],"p2":[],"i1":0,"i2":0},
{"f":2684,"p":[{"hits":[],"hurts":[{"rx":-7.8,"ry":1.45,"rw":0.9,"rh":0.4,"t":3},{"rx":-7.8,"ry":0.7,"rw":0.9,"rh":0.75,"t":3},{"rx":-7.8,"ry":0.0,"rw":0.9,"rh":0.7,"t":3}],"grabs":[{"rx":-7.65,"ry":0.0,"rw":0.6,"rh":1.4,"t":4}],"clips":[{"rx":-7.65,"ry":0.0,"rw":0.6,"rh":1.4,"t":0}],"s":"744 VT_broking_HIGH_1 40 +","x1":-7.5,"x2":-7.5,"x3":-7.5,"hit":0,"fl":0,"st":0,"c":null},{"hits":[],"hurts":[{"rx":-7.00616,"ry":1.3,"rw":0.7,"rh":0.4,"t":3},{"rx":-7.00616,"ry":0.0,"rw":0.7,"rh":0.55,"t":3},{"rx":-7.00616,"ry":0.55,"rw":0.7,"rh":0.75,"t":3}],"grabs":[{"rx":-6.90616,"ry":0.0,"rw":0.5,"rh":1.35,"t":4}],"clips":[{"rx":-6.90616,"ry":0.0,"rw":0.5,"rh":1.35,"t":0}],"s":"604 5MK 30 +","x1":-6.04832172,"x2":-6.65616,"x3":-6.660275,"hit":0,"fl":0,"st":0,"c":null}],"p1":[],"p2":[],"i1":0,"i2":0},
{"f":2685,"p":[{"hits":[],"hurts":[{"rx":-7.8,"ry":1.45,"rw":0.9,"rh":0.4,"t":3},{"rx":-7.8,"ry":0.7,"rw":0.9,"rh":0.75,"t":3},{"rx":-7.8,"ry":0.0,"rw":0.9,"rh":0.7,"t":3}],"grabs":[{"rx":-7.65,"ry":0.0,"rw":0.6,"rh":1.4,"t":4}],"clips":[{"rx":-7.65,"ry":0.0,"rw":0.6,"rh":1.4,"t":0}],"s":"744 VT_broking_HIGH_1 41 +","x1":-7.5,"x2":-7.5,"x3":-7.5,"hit":0,"fl":0,"st":0,"c":null},{"hits":[],"hurts":[{"rx":-7.009855,"ry":1.3,"rw":0.7,"rh":0.4,"t":3},{"rx":-7.009855,"ry":0.0,"rw":0.7,"rh":0.55,"t":3},{"rx":-7.009855,"ry":0.55,"rw":0.7,"rh":0.75,"t":3}],"grabs":[{"rx":-6.909855,"ry":0.0,"rw":0.5,"rh":1.35,"t":4}],"clips":[{"rx":-6.909855,"ry":0.0,"rw":0.5,"rh":1.35,"t":0}],"s":"604 5MK 31 +","x1":-6.04832172,"x2":-6.659855,"x3":-6.66017056,"hit":0,"fl":0,"st":0,"c":null}],"p1":[],"p2":[],"i1":0,"i2":0},
{"f":2686,"p":[{"hits":[],"hurts":[{"rx":-7.8,"ry":1.45,"rw":0.9,"rh":0.4,"t":3},{"rx":-7.8,"ry":0.7,"rw":0.9,"rh":0.75,"t":3},{"rx":-7.8,"ry":0.0,"rw":0.9,"rh":0.7,"t":3}],"grabs":[{"rx":-7.65,"ry":0.0,"rw":0.6,"rh":1.4,"t":4}],"clips":[{"rx":-7.65,"ry":0.0,"rw":0.6,"rh":1.4,"t":0}],"s":"744 VT_broking_HIGH_1 42 +","x1":-7.5,"x2":-7.5,"x3":-7.5,"hit":0,"fl":0,"st":0,"c":null},{"hits":[],"hurts":[{"rx":-7.010257,"ry":1.3,"rw":0.7,"rh":0.4,"t":3},{"rx":-7.010257,"ry":0.0,"rw":0.7,"rh":0.55,"t":3},{"rx":-7.010257,"ry":0.55,"rw":0.7,"rh":0.75,"t":3}],"grabs":[{"rx":-6.910257,"ry":0.0,"rw":0.5,"rh":1.35,"t":4}],"clips":[{"rx":-6.910257,"ry":0.0,"rw":0.5,"rh":1.35,"t":0}],"s":"604 5MK 32 +","x1":-6.04832172,"x2":-6.660257,"x3":-6.660257,"hit":0,"fl":0,"st":0,"c":null}],"p1":[],"p2":[],"i1":0,"i2":0},
{"f":2687,"p":[{"hits":[],"hurts":[{"rx":-7.8,"ry":1.45,"rw":0.9,"rh":0.4,"t":3},{"rx":-7.8,"ry":0.7,"rw":0.9,"rh":0.75,"t":3},{"rx":-7.8,"ry":0.0,"rw":0.9,"rh":0.7,"t":3}],"grabs":[{"rx":-7.65,"ry":0.0,"rw":0.6,"rh":1.4,"t":4}],"clips":[{"rx":-7.65,"ry":0.0,"rw":0.6,"rh":1.4,"t":0}],"s":"744 VT_broking_HIGH_1 43 +","x1":-7.5,"x2":-7.5,"x3":-7.5,"hit":0,"fl":0,"st":0,"c":null},{"hits":[],"hurts":[{"rx":-7.01352549,"ry":1.3,"rw":0.7,"rh":0.4,"t":3},{"rx":-7.01352549,"ry":0.0,"rw":0.7,"rh":0.55,"t":3},{"rx":-7.01352549,"ry":0.55,"rw":0.7,"rh":0.75,"t":3}],"grabs":[{"rx":-6.91352558,"ry":0.0,"rw":0.5,"rh":1.35,"t":4}],"clips":[{"rx":-6.91352558,"ry":0.0,"rw":0.5,"rh":1.35,"t":0}],"s":"604 5MK 33 +","x1":-6.04832172,"x2":-6.66352558,"x3":-6.663525,"hit":0,"fl":0,"st":0,"c":null}],"p1":[],"p2":[],"i1":0,"i2":0},
{"f":2688,"p":[{"hits":[],"hurts":[{"rx":-7.8,"ry":1.45,"rw":0.9,"rh":0.4,"t":3},{"rx":-7.8,"ry":0.7,"rw":0.9,"rh":0.75,"t":3},{"rx":-7.8,"ry":0.0,"rw":0.9,"rh":0.7,"t":3}],"grabs":[{"rx":-7.65,"ry":0.0,"rw":0.6,"rh":1.4,"t":4}],"clips":[{"rx":-7.65,"ry":0.0,"rw":0.6,"rh":1.4,"t":0}],"s":"744 VT_broking_HIGH_1 44 +","x1":-7.5,"x2":-7.5,"x3":-7.5,"hit":0,"fl":0,"st":0,"c":null},{"hits":[],"hurts":[{"rx":-7.01533747,"ry":1.3,"rw":0.7,"rh":0.4,"t":3},{"rx":-7.01533747,"ry":0.0,"rw":0.7,"rh":0.55,"t":3},{"rx":-7.01533747,"ry":0.55,"rw":0.7,"rh":0.75,"t":3}],"grabs":[{"rx":-6.91533756,"ry":0.0,"rw":0.5,"rh":1.35,"t":4}],"clips":[{"rx":-6.91533756,"ry":0.0,"rw":0.5,"rh":1.35,"t":0}],"s":"604 5MK 34 +","x1":-6.04832172,"x2":-6.66533756,"x3":-6.66533756,"hit":0,"fl":0,"st":0,"c":null}],"p1":[],"p2":[],"i1":0,"i2":0},
{"f":2689,"p":[{"hits":[],"hurts":[{"rx":-7.8,"ry":1.45,"rw":0.9,"rh":0.4,"t":3},{"rx":-7.8,"ry":0.7,"rw":0.9,"rh":0.75,"t":3},{"rx":-7.8,"ry":0.0,"rw":0.9,"rh":0.7,"t":3}],"grabs":[{"rx":-7.65,"ry":0.0,"rw":0.6,"rh":1.4,"t":4}],"clips":[{"rx":-7.65,"ry":0.0,"rw":0.6,"rh":1.4,"t":0}],"s":"744 VT_broking_HIGH_1 45 +","x1":-7.5,"x2":-7.5,"x3":-7.5,"hit":0,"fl":0,"st":0,"c":null},{"hits":[],"hurts":[{"rx":-7.01828671,"ry":1.3,"rw":0.7,"rh":0.4,"t":3},{"rx":-7.01828671,"ry":0.0,"rw":0.7,"rh":0.55,"t":3},{"rx":-7.01828671,"ry":0.55,"rw":0.7,"rh":0.75,"t":3}],"grabs":[{"rx":-6.918287,"ry":0.0,"rw":0.5,"rh":1.35,"t":4}],"clips":[{"rx":-6.918287,"ry":0.0,"rw":0.5,"rh":1.35,"t":0}],"s":"604 5MK 35 +","x1":-6.04832172,"x2":-6.668287,"x3":-6.668287,"hit":0,"fl":0,"st":0,"c":null}],"p1":[],"p2":[],"i1":0,"i2":0},
{"f":2690,"p":[{"hits":[],"hurts":[{"rx":-7.8,"ry":1.45,"rw":0.9,"rh":0.4,"t":3},{"rx":-7.8,"ry":0.7,"rw":0.9,"rh":0.75,"t":3},{"rx":-7.8,"ry":0.0,"rw":0.9,"rh":0.7,"t":3}],"grabs":[{"rx":-7.65,"ry":0.0,"rw":0.6,"rh":1.4,"t":4}],"clips":[{"rx":-7.65,"ry":0.0,"rw":0.6,"rh":1.4,"t":0}],"s":"744 VT_broking_HIGH_1 46 +","x1":-7.5,"x2":-7.5,"x3":-7.5,"hit":0,"fl":0,"st":0,"c":null},{"hits":[],"hurts":[{"rx":-7.02139854,"ry":1.3,"rw":0.7,"rh":0.4,"t":3},{"rx":-7.02139854,"ry":0.0,"rw":0.7,"rh":0.55,"t":3},{"rx":-7.02139854,"ry":0.55,"rw":0.7,"rh":0.75,"t":3}],"grabs":[{"rx":-6.92139864,"ry":0.0,"rw":0.5,"rh":1.35,"t":4}],"clips":[{"rx":-6.92139864,"ry":0.0,"rw":0.5,"rh":1.35,"t":0}],"s":"604 5MK 36 +","x1":-6.04832172,"x2":-6.67139864,"x3":-6.67139864,"hit":0,"fl":0,"st":0,"c":null}],"p1":[],"p2":[],"i1":0,"i2":0},
{"f":2691,"p":[{"hits":[],"hurts":[{"rx":-7.8,"ry":1.45,"rw":0.9,"rh":0.4,"t":3},{"rx":-7.8,"ry":0.7,"rw":0.9,"rh":0.75,"t":3},{"rx":-7.8,"ry":0.0,"rw":0.9,"rh":0.7,"t":3}],"grabs":[{"rx":-7.65,"ry":0.0,"rw":0.6,"rh":1.4,"t":4}],"clips":[{"rx":-7.65,"ry":0.0,"rw":0.6,"rh":1.4,"t":0}],"s":"744 VT_broking_HIGH_1 47 +","x1":-7.5,"x2":-7.5,"x3":-7.5,"hit":0,"fl":0,"st":0,"c":null},{"hits":[],"hurts":[{"rx":-7.02234268,"ry":1.3,"rw":0.7,"rh":0.4,"t":3},{"rx":-7.02234268,"ry":0.0,"rw":0.7,"rh":0.55,"t":3},{"rx":-7.02234268,"ry":0.55,"rw":0.7,"rh":0.75,"t":3}],"grabs":[{"rx":-6.922343,"ry":0.0,"rw":0.5,"rh":1.35,"t":4}],"clips":[{"rx":-6.922343,"ry":0.0,"rw":0.5,"rh":1.35,"t":0}],"s":"604 5MK 37 +","x1":-6.04832172,"x2":-6.672343,"x3":-6.6723423,"hit":0,"fl":0,"st":0,"c":null}],"p1":[],"p2":[],"i1":0,"i2":0},
{"f":2692,"p":[{"hits":[],"hurts":[{"rx":-7.8,"ry":1.45,"rw":0.9,"rh":0.4,"t":3},{"rx":-7.8,"ry":0.7,"rw":0.9,"rh":0.75,"t":3},{"rx":-7.8,"ry":0.0,"rw":0.9,"rh":0.7,"t":3}],"grabs":[{"rx":-7.65,"ry":0.0,"rw":0.6,"rh":1.4,"t":4}],"clips":[{"rx":-7.65,"ry":0.0,"rw":0.6,"rh":1.4,"t":0}],"s":"744 VT_broking_HIGH_1 48 +","x1":-7.5,"x2":-7.5,"x3":-7.5,"hit":0,"fl":0,"st":0,"c":null},{"hits":[],"hurts":[{"rx":-7.022917,"ry":1.3,"rw":0.7,"rh":0.4,"t":3},{"rx":-7.022917,"ry":0.0,"rw":0.7,"rh":0.55,"t":3},{"rx":-7.022917,"ry":0.55,"rw":0.7,"rh":0.75,"t":3}],"grabs":[{"rx":-6.922917,"ry":0.0,"rw":0.5,"rh":1.35,"t":4}],"clips":[{"rx":-6.922917,"ry":0.0,"rw":0.5,"rh":1.35,"t":0}],"s":"604 5MK 38 +","x1":-6.04832172,"x2":-6.672917,"x3":-6.672078,"hit":0,"fl":0,"st":0,"c":null}],"p1":[],"p2":[],"i1":0,"i2":0},
{"f":2693,"p":[{"hits":[],"hurts":[{"rx":-7.8,"ry":1.45,"rw":0.9,"rh":0.4,"t":3},{"rx":-7.8,"ry":0.7,"rw":0.9,"rh":0.75,"t":3},{"rx":-7.8,"ry":0.0,"rw":0.9,"rh":0.7,"t":3}],"grabs":[{"rx":-7.65,"ry":0.0,"rw":0.6,"rh":1.4,"t":4}],"clips":[{"rx":-7.65,"ry":0.0,"rw":0.6,"rh":1.4,"t":0}],"s":"744 VT_broking_HIGH_1 49 +","x1":-7.5,"x2":-7.5,"x3":-7.5,"hit":0,"fl":0,"st":0,"c":null},{"hits":[],"hurts":[{"rx":-7.02424955,"ry":1.3,"rw":0.7,"rh":0.4,"t":3},{"rx":-7.02424955,"ry":0.0,"rw":0.7,"rh":0.55,"t":3},{"rx":-7.02424955,"ry":0.55,"rw":0.7,"rh":0.75,"t":3}],"grabs":[{"rx":-6.92424965,"ry":0.0,"rw":0.5,"rh":1.35,"t":4}],"clips":[{"rx":-6.92424965,"ry":0.0,"rw":0.5,"rh":1.35,"t":0}],"s":"604 5MK 39 +","x1":-6.04832172,"x2":-6.67424965,"x3":-6.671309,"hit":0,"fl":0,"st":0,"c":null}],"p1":[],"p2":[],"i1":0,"i2":0},
{"f":2694,"p":[{"hits":[],"hurts":[{"rx":-7.8,"ry":1.45,"rw":0.9,"rh":0.4,"t":3},{"rx":-7.8,"ry":0.7,"rw":0.9,"rh":0.75,"t":3},{"rx":-7.8,"ry":0.0,"rw":0.9,"rh":0.7,"t":3}],"grabs":[{"rx":-7.65,"ry":0.0,"rw":0.6,"rh":1.4,"t":4}],"clips":[{"rx":-7.65,"ry":0.0,"rw":0.6,"rh":1.4,"t":0}],"s":"744 VT_broking_HIGH_1 50 +","x1":-7.5,"x2":-7.5,"x3":-7.5,"hit":0,"fl":0,"st":0,"c":null},{"hits":[],"hurts":[{"rx":-7.02661467,"ry":1.3,"rw":0.7,"rh":0.4,"t":3},{"rx":-7.02661467,"ry":0.0,"rw":0.7,"rh":0.55,"t":3},{"rx":-7.02661467,"ry":0.55,"rw":0.7,"rh":0.75,"t":3}],"grabs":[{"rx":-6.92661476,"ry":0.0,"rw":0.5,"rh":1.35,"t":4}],"clips":[{"rx":-6.92661476,"ry":0.0,"rw":0.5,"rh":1.35,"t":0}],"s":"604 5MK 40 +","x1":-6.04832172,"x2":-6.67661476,"x3":-6.670108,"hit":0,"fl":0,"st":0,"c":null}],"p1":[],"p2":[],"i1":0,"i2":0},
{"f":2695,"p":[{"hits":[],"hurts":[{"rx":-7.8,"ry":1.45,"rw":0.9,"rh":0.4,"t":3},{"rx":-7.8,"ry":0.7,"rw":0.9,"rh":0.75,"t":3},{"rx":-7.8,"ry":0.0,"rw":0.9,"rh":0.7,"t":3}],"grabs":[{"rx":-7.65,"ry":0.0,"rw":0.6,"rh":1.4,"t":4}],"clips":[{"rx":-7.65,"ry":0.0,"rw":0.6,"rh":1.4,"t":0}],"s":"744 VT_broking_HIGH_1 51 +","x1":-7.5,"x2":-7.5,"x3":-7.5,"hit":0,"fl":0,"st":0,"c":null},{"hits":[],"hurts":[{"rx":-7.02970743,"ry":1.3,"rw":0.7,"rh":0.4,"t":3},{"rx":-7.02970743,"ry":0.0,"rw":0.7,"rh":0.55,"t":3},{"rx":-7.02970743,"ry":0.55,"rw":0.7,"rh":0.75,"t":3}],"grabs":[{"rx":-6.92970753,"ry":0.0,"rw":0.5,"rh":1.35,"t":4}],"clips":[{"rx":-6.92970753,"ry":0.0,"rw":0.5,"rh":1.35,"t":0}],"s":"604 5MK 41 +","x1":-6.04832172,"x2":-6.67970753,"x3":-6.668542,"hit":0,"fl":0,"st":0,"c":null}],"p1":[],"p2":[],"i1":0,"i2":0},
{"f":2696,"p":[{"hits":[],"hurts":[{"rx":-7.8,"ry":1.45,"rw":0.9,"rh":0.4,"t":3},{"rx":-7.8,"ry":0.7,"rw":0.9,"rh":0.75,"t":3},{"rx":-7.8,"ry":0.0,"rw":0.9,"rh":0.7,"t":3}],"grabs":[{"rx":-7.65,"ry":0.0,"rw":0.6,"rh":1.4,"t":4}],"clips":[{"rx":-7.65,"ry":0.0,"rw":0.6,"rh":1.4,"t":0}],"s":"744 VT_broking_HIGH_1 52 +","x1":-7.5,"x2":-7.5,"x3":-7.5,"hit":0,"fl":0,"st":0,"c":null},{"hits":[],"hurts":[{"rx":-7.03252268,"ry":1.3,"rw":0.7,"rh":0.4,"t":3},{"rx":-7.03252268,"ry":0.0,"rw":0.7,"rh":0.55,"t":3},{"rx":-7.03252268,"ry":0.55,"rw":0.7,"rh":0.75,"t":3}],"grabs":[{"rx":-6.932523,"ry":0.0,"rw":0.5,"rh":1.35,"t":4}],"clips":[{"rx":-6.932523,"ry":0.0,"rw":0.5,"rh":1.35,"t":0}],"s":"604 5MK 42 +","x1":-6.04832172,"x2":-6.682523,"x3":-6.66680956,"hit":0,"fl":0,"st":0,"c":null}],"p1":[],"p2":[],"i1":0,"i2":0},
{"f":2697,"p":[{"hits":[],"hurts":[{"rx":-7.8,"ry":1.45,"rw":0.9,"rh":0.4,"t":3},{"rx":-7.8,"ry":0.7,"rw":0.9,"rh":0.75,"t":3},{"rx":-7.8,"ry":0.0,"rw":0.9,"rh":0.7,"t":3}],"grabs":[{"rx":-7.65,"ry":0.0,"rw":0.6,"rh":1.4,"t":4}],"clips":[{"rx":-7.65,"ry":0.0,"rw":0.6,"rh":1.4,"t":0}],"s":"744 VT_broking_HIGH_1 53 +","x1":-7.5,"x2":-7.5,"x3":-7.5,"hit":0,"fl":0,"st":0,"c":null},{"hits":[],"hurts":[{"rx":-7.03740644,"ry":1.3,"rw":0.7,"rh":0.4,"t":3},{"rx":-7.03740644,"ry":0.0,"rw":0.7,"rh":0.55,"t":3},{"rx":-7.03740644,"ry":0.55,"rw":0.7,"rh":0.75,"t":3}],"grabs":[{"rx":-6.93740654,"ry":0.0,"rw":0.5,"rh":1.35,"t":4}],"clips":[{"rx":-6.93740654,"ry":0.0,"rw":0.5,"rh":1.35,"t":0}],"s":"604 5MK 43 +","x1":-6.04832172,"x2":-6.68740654,"x3":-6.66484356,"hit":0,"fl":0,"st":0,"c":null}],"p1":[],"p2":[],"i1":0,"i2":0},
{"f":2698,"p":[{"hits":[],"hurts":[{"rx":-7.8,"ry":1.45,"rw":0.9,"rh":0.4,"t":3},{"rx":-7.8,"ry":0.7,"rw":0.9,"rh":0.75,"t":3},{"rx":-7.8,"ry":0.0,"rw":0.9,"rh":0.7,"t":3}],"grabs":[{"rx":-7.65,"ry":0.0,"rw":0.6,"rh":1.4,"t":4}],"clips":[{"rx":-7.65,"ry":0.0,"rw":0.6,"rh":1.4,"t":0}],"s":"744 VT_broking_HIGH_1 54 +","x1":-7.5,"x2":-7.5,"x3":-7.5,"hit":0,"fl":0,"st":0,"c":null},{"hits":[],"hurts":[{"rx":-7.041671,"ry":1.3,"rw":0.7,"rh":0.4,"t":3},{"rx":-7.041671,"ry":0.0,"rw":0.7,"rh":0.55,"t":3},{"rx":-7.041671,"ry":0.55,"rw":0.7,"rh":0.75,"t":3}],"grabs":[{"rx":-6.941671,"ry":0.0,"rw":0.5,"rh":1.35,"t":4}],"clips":[{"rx":-6.941671,"ry":0.0,"rw":0.5,"rh":1.35,"t":0}],"s":"604 5MK 44 +","x1":-6.04832172,"x2":-6.691671,"x3":-6.66281652,"hit":0,"fl":0,"st":0,"c":null}],"p1":[],"p2":[],"i1":0,"i2":0},
{"f":2699,"p":[{"hits":[],"hurts":[{"rx":-7.8,"ry":1.45,"rw":0.9,"rh":0.4,"t":3},{"rx":-7.8,"ry":0.7,"rw":0.9,"rh":0.75,"t":3},{"rx":-7.8,"ry":0.0,"rw":0.9,"rh":0.7,"t":3}],"grabs":[{"rx":-7.65,"ry":0.0,"rw":0.6,"rh":1.4,"t":4}],"clips":[{"rx":-7.65,"ry":0.0,"rw":0.6,"rh":1.4,"t":0}],"s":"744 VT_broking_HIGH_1 55 +","x1":-7.5,"x2":-7.5,"x3":-7.5,"hit":0,"fl":0,"st":0,"c":null},{"hits":[],"hurts":[{"rx":-7.0452714,"ry":1.3,"rw":0.7,"rh":0.4,"t":3},{"rx":-7.0452714,"ry":0.0,"rw":0.7,"rh":0.55,"t":3},{"rx":-7.0452714,"ry":0.55,"rw":0.7,"rh":0.75,"t":3}],"grabs":[{"rx":-6.94527149,"ry":0.0,"rw":0.5,"rh":1.35,"t":4}],"clips":[{"rx":-6.94527149,"ry":0.0,"rw":0.5,"rh":1.35,"t":0}],"s":"604 5MK 45 +","x1":-6.04832172,"x2":-6.69527149,"x3":-6.66052341,"hit":0,"fl":0,"st":0,"c":null}],"p1":[],"p2":[],"i1":0,"i2":0},
{"f":2700,"p":[{"hits":[],"hurts":[{"rx":-7.8,"ry":1.45,"rw":0.9,"rh":0.4,"t":3},{"rx":-7.8,"ry":0.7,"rw":0.9,"rh":0.75,"t":3},{"rx":-7.8,"ry":0.0,"rw":0.9,"rh":0.7,"t":3}],"grabs":[{"rx":-7.65,"ry":0.0,"rw":0.6,"rh":1.4,"t":4}],"clips":[{"rx":-7.65,"ry":0.0,"rw":0.6,"rh":1.4,"t":0}],"s":"744 VT_broking_HIGH_1 56 +","x1":-7.5,"x2":-7.5,"x3":-7.5,"hit":0,"fl":0,"st":0,"c":null},{"hits":[],"hurts":[{"rx":-7.04844046,"ry":1.3,"rw":0.7,"rh":0.4,"t":3},{"rx":-7.04844046,"ry":0.0,"rw":0.7,"rh":0.55,"t":3},{"rx":-7.04844046,"ry":0.55,"rw":0.7,"rh":0.75,"t":3}],"grabs":[{"rx":-6.94844055,"ry":0.0,"rw":0.5,"rh":1.35,"t":4}],"clips":[{"rx":-6.94844055,"ry":0.0,"rw":0.5,"rh":1.35,"t":0}],"s":"604 5MK 46 +","x1":-6.04832172,"x2":-6.69844055,"x3":-6.657799,"hit":0,"fl":0,"st":0,"c":null}],"p1":[],"p2":[],"i1":0,"i2":0},
{"f":2701,"p":[{"hits":[],"hurts":[{"rx":-7.8,"ry":1.45,"rw":0.9,"rh":0.4,"t":3},{"rx":-7.8,"ry":0.7,"rw":0.9,"rh":0.75,"t":3},{"rx":-7.8,"ry":0.0,"rw":0.9,"rh":0.7,"t":3}],"grabs":[{"rx":-7.65,"ry":0.0,"rw":0.6,"rh":1.4,"t":4}],"clips":[{"rx":-7.65,"ry":0.0,"rw":0.6,"rh":1.4,"t":0}],"s":"744 VT_broking_HIGH_1 57 +","x1":-7.5,"x2":-7.5,"x3":-7.5,"hit":0,"fl":0,"st":0,"c":null},{"hits":[],"hurts":[{"rx":-7.05141258,"ry":1.3,"rw":0.7,"rh":0.4,"t":3},{"rx":-7.05141258,"ry":0.0,"rw":0.7,"rh":0.55,"t":3},{"rx":-7.05141258,"ry":0.55,"rw":0.7,"rh":0.75,"t":3}],"grabs":[{"rx":-6.95141268,"ry":0.0,"rw":0.5,"rh":1.35,"t":4}],"clips":[{"rx":-6.95141268,"ry":0.0,"rw":0.5,"rh":1.35,"t":0}],"s":"604 5MK 47 +","x1":-6.04832172,"x2":-6.70141268,"x3":-6.65476847,"hit":0,"fl":0,"st":0,"c":null}],"p1":[],"p2":[],"i1":0,"i2":0},
{"f":2702,"p":[{"hits":[],"hurts":[{"rx":-7.8,"ry":1.45,"rw":0.9,"rh":0.4,"t":3},{"rx":-7.8,"ry":0.7,"rw":0.9,"rh":0.75,"t":3},{"rx":-7.8,"ry":0.0,"rw":0.9,"rh":0.7,"t":3}],"grabs":[{"rx":-7.65,"ry":0.0,"rw":0.6,"rh":1.4,"t":4}],"clips":[{"rx":-7.65,"ry":0.0,"rw":0.6,"rh":1.4,"t":0}],"s":"744 VT_broking_HIGH_1 58 +","x1":-7.5,"x2":-7.5,"x3":-7.5,"hit":0,"fl":0,"st":0,"c":null},{"hits":[],"hurts":[{"rx":-7.054393,"ry":1.3,"rw":0.7,"rh":0.4,"t":3},{"rx":-7.054393,"ry":0.0,"rw":0.7,"rh":0.55,"t":3},{"rx":-7.054393,"ry":0.55,"rw":0.7,"rh":0.75,"t":3}],"grabs":[{"rx":-6.954393,"ry":0.0,"rw":0.5,"rh":1.35,"t":4}],"clips":[{"rx":-6.954393,"ry":0.0,"rw":0.5,"rh":1.35,"t":0}],"s":"604 5MK 48 +","x1":-6.04832172,"x2":-6.704393,"x3":-6.651583,"hit":0,"fl":0,"st":0,"c":null}],"p1":[],"p2":[],"i1":0,"i2":0},
{"f":2703,"p":[{"hits":[],"hurts":[{"rx":-7.8,"ry":1.45,"rw":0.9,"rh":0.4,"t":3},{"rx":-7.8,"ry":0.7,"rw":0.9,"rh":0.75,"t":3},{"rx":-7.8,"ry":0.0,"rw":0.9,"rh":0.7,"t":3}],"grabs":[{"rx":-7.65,"ry":0.0,"rw":0.6,"rh":1.4,"t":4}],"clips":[{"rx":-7.65,"ry":0.0,"rw":0.6,"rh":1.4,"t":0}],"s":"744 VT_broking_HIGH_1 59 +","x1":-7.5,"x2":-7.5,"x3":-7.5,"hit":0,"fl":0,"st":0,"c":null},{"hits":[],"hurts":[{"rx":-7.057635,"ry":1.3,"rw":0.7,"rh":0.4,"t":3},{"rx":-7.057635,"ry":0.0,"rw":0.7,"rh":0.55,"t":3},{"rx":-7.057635,"ry":0.55,"rw":0.7,"rh":0.75,"t":3}],"grabs":[{"rx":-6.957635,"ry":0.0,"rw":0.5,"rh":1.35,"t":4}],"clips":[{"rx":-6.957635,"ry":0.0,"rw":0.5,"rh":1.35,"t":0}],"s":"604 5MK 49 +","x1":-6.04832172,"x2":-6.707635,"x3":-6.64837837,"hit":0,"fl":0,"st":0,"c":null}],"p1":[],"p2":[],"i1":0,"i2":0},
{"f":2704,"p":[{"hits":[],"hurts":[{"rx":-7.8,"ry":1.45,"rw":0.9,"rh":0.4,"t":3},{"rx":-7.8,"ry":0.7,"rw":0.9,"rh":0.75,"t":3},{"rx":-7.8,"ry":0.0,"rw":0.9,"rh":0.7,"t":3}],"grabs":[{"rx":-7.65,"ry":0.0,"rw":0.6,"rh":1.4,"t":4}],"clips":[{"rx":-7.65,"ry":0.0,"rw":0.6,"rh":1.4,"t":0}],"s":"744 VT_broking_HIGH_1 60 +","x1":-7.5,"x2":-7.5,"x3":-7.5,"hit":0,"fl":0,"st":0,"c":null},{"hits":[],"hurts":[{"rx":-7.06135845,"ry":1.3,"rw":0.7,"rh":0.4,"t":3},{"rx":-7.06135845,"ry":0.0,"rw":0.7,"rh":0.55,"t":3},{"rx":-7.06135845,"ry":0.55,"rw":0.7,"rh":0.75,"t":3}],"grabs":[{"rx":-6.96135855,"ry":0.0,"rw":0.5,"rh":1.35,"t":4}],"clips":[{"rx":-6.96135855,"ry":0.0,"rw":0.5,"rh":1.35,"t":0}],"s":"604 5MK 50 +","x1":-6.04832172,"x2":-6.71135855,"x3":-6.64529228,"hit":0,"fl":0,"st":0,"c":null}],"p1":[],"p2":[],"i1":0,"i2":0},
{"f":2705,"p":[{"hits":[],"hurts":[{"rx":-7.47,"ry":1.45,"rw":0.45,"rh":0.35,"t":3},{"rx":-7.82,"ry":0.6,"rw":0.8,"rh":0.95,"t":3},{"rx":-7.82,"ry":0.0,"rw":0.8,"rh":0.6,"t":3}],"grabs":[{"rx":-7.72,"ry":0.0,"rw":0.6,"rh":1.4,"t":4}],"clips":[{"rx":-7.72,"ry":0.0,"rw":0.6,"rh":1.4,"t":0}],"s":"0 STAND 1","x1":-7.5,"x2":-7.5,"x3":-7.5,"hit":0,"fl":0,"st":0,"c":null},{"hits":[],"hurts":[{"rx":-7.0657196,"ry":1.3,"rw":0.7,"rh":0.4,"t":3},{"rx":-7.0657196,"ry":0.0,"rw":0.7,"rh":0.55,"t":3},{"rx":-7.0657196,"ry":0.55,"rw":0.7,"rh":0.75,"t":3}],"grabs":[{"rx":-6.9657197,"ry":0.0,"rw":0.5,"rh":1.35,"t":4}],"clips":[{"rx":-6.9657197,"ry":0.0,"rw":0.5,"rh":1.35,"t":0}],"s":"604 5MK 51 +","x1":-6.04832172,"x2":-6.7157197,"x3":-6.64239168,"hit":0,"fl":0,"st":0,"c":null}],"p1":[],"p2":[],"i1":0,"i2":0},
{"f":2706,"p":[{"hits":[],"hurts":[{"rx":-7.47,"ry":1.45,"rw":0.45,"rh":0.35,"t":3},{"rx":-7.82,"ry":0.6,"rw":0.8,"rh":0.95,"t":3},{"rx":-7.82,"ry":0.0,"rw":0.8,"rh":0.6,"t":3}],"grabs":[{"rx":-7.72,"ry":0.0,"rw":0.6,"rh":1.4,"t":4}],"clips":[{"rx":-7.72,"ry":0.0,"rw":0.6,"rh":1.4,"t":0}],"s":"0 STAND 2","x1":-7.5,"x2":-7.5,"x3":-7.5,"hit":0,"fl":0,"st":0,"c":null},{"hits":[],"hurts":[{"rx":-7.06859159,"ry":1.3,"rw":0.7,"rh":0.4,"t":3},{"rx":-7.06859159,"ry":0.0,"rw":0.7,"rh":0.55,"t":3},{"rx":-7.06859159,"ry":0.55,"rw":0.7,"rh":0.75,"t":3}],"grabs":[{"rx":-6.96859169,"ry":0.0,"rw":0.5,"rh":1.35,"t":4}],"clips":[{"rx":-6.96859169,"ry":0.0,"rw":0.5,"rh":1.35,"t":0}],"s":"604 5MK 52 +","x1":-6.04832172,"x2":-6.71859169,"x3":-6.63993025,"hit":0,"fl":0,"st":0,"c":null}],"p1":[],"p2":[],"i1":0,"i2":0},
{"f":2707,"p":[{"hits":[],"hurts":[{"rx":-7.47,"ry":1.45,"rw":0.45,"rh":0.35,"t":3},{"rx":-7.82,"ry":0.6,"rw":0.8,"rh":0.95,"t":3},{"rx":-7.82,"ry":0.0,"rw":0.8,"rh":0.6,"t":3}],"grabs":[{"rx":-7.72,"ry":0.0,"rw":0.6,"rh":1.4,"t":4}],"clips":[{"rx":-7.72,"ry":0.0,"rw":0.6,"rh":1.4,"t":0}],"s":"0 STAND 3","x1":-7.5,"x2":-7.5,"x3":-7.5,"hit":0,"fl":0,"st":0,"c":null},{"hits":[],"hurts":[{"rx":-7.07142353,"ry":1.3,"rw":0.7,"rh":0.4,"t":3},{"rx":-7.07142353,"ry":0.0,"rw":0.7,"rh":0.55,"t":3},{"rx":-7.07142353,"ry":0.55,"rw":0.7,"rh":0.75,"t":3}],"grabs":[{"rx":-6.97142363,"ry":0.0,"rw":0.5,"rh":1.35,"t":4}],"clips":[{"rx":-6.97142363,"ry":0.0,"rw":0.5,"rh":1.35,"t":0}],"s":"604 5MK 53 +","x1":-6.04832172,"x2":-6.72142363,"x3":-6.63789463,"hit":0,"fl":0,"st":0,"c":null}],"p1":[],"p2":[],"i1":0,"i2":0},
{"f":2708,"p":[{"hits":[],"hurts":[{"rx":-7.47,"ry":1.45,"rw":0.45,"rh":0.35,"t":3},{"rx":-7.82,"ry":0.6,"rw":0.8,"rh":0.95,"t":3},{"rx":-7.82,"ry":0.0,"rw":0.8,"rh":0.6,"t":3}],"grabs":[{"rx":-7.72,"ry":0.0,"rw":0.6,"rh":1.4,"t":4}],"clips":[{"rx":-7.72,"ry":0.0,"rw":0.6,"rh":1.4,"t":0}],"s":"0 STAND 4","x1":-7.5,"x2":-7.5,"x3":-7.5,"hit":0,"fl":0,"st":0,"c":null},{"hits":[],"hurts":[{"rx":-7.07090044,"ry":1.3,"rw":0.7,"rh":0.4,"t":3},{"rx":-7.07090044,"ry":0.0,"rw":0.7,"rh":0.55,"t":3},{"rx":-7.07090044,"ry":0.55,"rw":0.7,"rh":0.75,"t":3}],"grabs":[{"rx":-6.97090054,"ry":0.0,"rw":0.5,"rh":1.35,"t":4}],"clips":[{"rx":-6.97090054,"ry":0.0,"rw":0.5,"rh":1.35,"t":0}],"s":"604 5MK 54 +","x1":-6.04832172,"x2":-6.72090054,"x3":-6.6366,"hit":0,"fl":0,"st":0,"c":null}],"p1":[],"p2":[],"i1":0,"i2":0},
{"f":2709,"p":[{"hits":[],"hurts":[{"rx":-7.47,"ry":1.45,"rw":0.45,"rh":0.35,"t":3},{"rx":-7.82,"ry":0.6,"rw":0.8,"rh":0.95,"t":3},{"rx":-7.82,"ry":0.0,"rw":0.8,"rh":0.6,"t":3}],"grabs":[{"rx":-7.72,"ry":0.0,"rw":0.6,"rh":1.4,"t":4}],"clips":[{"rx":-7.72,"ry":0.0,"rw":0.6,"rh":1.4,"t":0}],"s":"0 STAND 5","x1":-7.5,"x2":-7.5,"x3":-7.5,"hit":0,"fl":0,"st":0,"c":null},{"hits":[],"hurts":[{"rx":-7.06932163,"ry":1.3,"rw":0.7,"rh":0.4,"t":3},{"rx":-7.06932163,"ry":0.0,"rw":0.7,"rh":0.55,"t":3},{"rx":-7.06932163,"ry":0.55,"rw":0.7,"rh":0.75,"t":3}],"grabs":[{"rx":-6.96932173,"ry":0.0,"rw":0.5,"rh":1.35,"t":4}],"clips":[{"rx":-6.96932173,"ry":0.0,"rw":0.5,"rh":1.35,"t":0}],"s":"604 5MK 55 +","x1":-6.04832172,"x2":-6.71932173,"x3":-6.63611937,"hit":0,"fl":0,"st":0,"c":null}],"p1":[],"p2":[],"i1":0,"i2":0},
{"f":2710,"p":[{"hits":[],"hurts":[{"rx":-7.47,"ry":1.45,"rw":0.45,"rh":0.35,"t":3},{"rx":-7.82,"ry":0.6,"rw":0.8,"rh":0.95,"t":3},{"rx":-7.82,"ry":0.0,"rw":0.8,"rh":0.6,"t":3}],"grabs":[{"rx":-7.72,"ry":0.0,"rw":0.6,"rh":1.4,"t":4}],"clips":[{"rx":-7.72,"ry":0.0,"rw":0.6,"rh":1.4,"t":0}],"s":"0 STAND 6","x1":-7.5,"x2":-7.5,"x3":-7.5,"hit":0,"fl":0,"st":0,"c":null},{"hits":[],"hurts":[{"rx":-7.06679869,"ry":1.3,"rw":0.7,"rh":0.4,"t":3},{"rx":-7.06679869,"ry":0.0,"rw":0.7,"rh":0.55,"t":3},{"rx":-7.06679869,"ry":0.55,"rw":0.7,"rh":0.75,"t":3}],"grabs":[{"rx":-6.966799,"ry":0.0,"rw":0.5,"rh":1.35,"t":4}],"clips":[{"rx":-6.966799,"ry":0.0,"rw":0.5,"rh":1.35,"t":0}],"s":"604 5MK 56 +","x1":-6.04832172,"x2":-6.716799,"x3":-6.63608742,"hit":0,"fl":0,"st":0,"c":null}],"p1":[],"p2":[],"i1":0,"i2":0},
{"f":2711,"p":[{"hits":[],"hurts":[{"rx":-7.47,"ry":1.45,"rw":0.45,"rh":0.35,"t":3},{"rx":-7.82,"ry":0.6,"rw":0.8,"rh":0.95,"t":3},{"rx":-7.82,"ry":0.0,"rw":0.8,"rh":0.6,"t":3}],"grabs":[{"rx":-7.72,"ry":0.0,"rw":0.6,"rh":1.4,"t":4}],"clips":[{"rx":-7.72,"ry":0.0,"rw":0.6,"rh":1.4,"t":0}],"s":"0 STAND 7","x1":-7.5,"x2":-7.5,"x3":-7.5,"hit":0,"fl":0,"st":0,"c":null},{"hits":[],"hurts":[{"rx":-7.0632596,"ry":1.3,"rw":0.7,"rh":0.4,"t":3},{"rx":-7.0632596,"ry":0.0,"rw":0.7,"rh":0.55,"t":3},{"rx":-7.0632596,"ry":0.55,"rw":0.7,"rh":0.75,"t":3}],"grabs":[{"rx":-6.9632597,"ry":0.0,"rw":0.5,"rh":1.35,"t":4}],"clips":[{"rx":-6.9632597,"ry":0.0,"rw":0.5,"rh":1.35,"t":0}],"s":"604 5MK 57 +","x1":-6.04832172,"x2":-6.7132597,"x3":-6.63606071,"hit":0,"fl":0,"st":0,"c":null}],"p1":[],"p2":[],"i1":0,"i2":0},
{"f":2712,"p":[{"hits":[],"hurts":[{"rx":-7.47,"ry":1.45,"rw":0.45,"rh":0.35,"t":3},{"rx":-7.82,"ry":0.6,"rw":0.8,"rh":0.95,"t":3},{"rx":-7.82,"ry":0.0,"rw":0.8,"rh":0.6,"t":3}],"grabs":[{"rx":-7.72,"ry":0.0,"rw":0.6,"rh":1.4,"t":4}],"clips":[{"rx":-7.72,"ry":0.0,"rw":0.6,"rh":1.4,"t":0}],"s":"0 STAND 8","x1":-7.5,"x2":-7.5,"x3":-7.5,"hit":0,"fl":0,"st":0,"c":null},{"hits":[],"hurts":[{"rx":-7.058881,"ry":1.3,"rw":0.7,"rh":0.4,"t":3},{"rx":-7.058881,"ry":0.0,"rw":0.7,"rh":0.55,"t":3},{"rx":-7.058881,"ry":0.55,"rw":0.7,"rh":0.75,"t":3}],"grabs":[{"rx":-6.958881,"ry":0.0,"rw":0.5,"rh":1.35,"t":4}],"clips":[{"rx":-6.958881,"ry":0.0,"rw":0.5,"rh":1.35,"t":0}],"s":"604 5MK 58 +","x1":-6.04832172,"x2":-6.708881,"x3":-6.636076,"hit":0,"fl":0,"st":0,"c":null}],"p1":[],"p2":[],"i1":0,"i2":0},
{"f":2713,"p":[{"hits":[],"hurts":[{"rx":-7.47,"ry":1.45,"rw":0.45,"rh":0.35,"t":3},{"rx":-7.82,"ry":0.6,"rw":0.8,"rh":0.95,"t":3},{"rx":-7.82,"ry":0.0,"rw":0.8,"rh":0.6,"t":3}],"grabs":[{"rx":-7.72,"ry":0.0,"rw":0.6,"rh":1.4,"t":4}],"clips":[{"rx":-7.72,"ry":0.0,"rw":0.6,"rh":1.4,"t":0}],"s":"0 STAND 9","x1":-7.5,"x2":-7.5,"x3":-7.5,"hit":0,"fl":0,"st":0,"c":null},{"hits":[],"hurts":[{"rx":-7.05489969,"ry":1.3,"rw":0.7,"rh":0.4,"t":3},{"rx":-7.05489969,"ry":0.0,"rw":0.7,"rh":0.55,"t":3},{"rx":-7.05489969,"ry":0.55,"rw":0.7,"rh":0.75,"t":3}],"grabs":[{"rx":-6.9549,"ry":0.0,"rw":0.5,"rh":1.35,"t":4}],"clips":[{"rx":-6.9549,"ry":0.0,"rw":0.5,"rh":1.35,"t":0}],"s":"604 5MK 59 +","x1":-6.04832172,"x2":-6.7049,"x3":-6.63604069,"hit":0,"fl":0,"st":0,"c":null}],"p1":[],"p2":[],"i1":0,"i2":0},
{"f":2714,"p":[{"hits":[],"hurts":[{"rx":-7.47,"ry":1.45,"rw":0.45,"rh":0.35,"t":3},{"rx":-7.82,"ry":0.6,"rw":0.8,"rh":0.95,"t":3},{"rx":-7.82,"ry":0.0,"rw":0.8,"rh":0.6,"t":3}],"grabs":[{"rx":-7.72,"ry":0.0,"rw":0.6,"rh":1.4,"t":4}],"clips":[{"rx":-7.72,"ry":0.0,"rw":0.6,"rh":1.4,"t":0}],"s":"0 STAND 10","x1":-7.5,"x2":-7.5,"x3":-7.5,"hit":0,"fl":0,"st":0,"c":null},{"hits":[],"hurts":[{"rx":-7.04974651,"ry":1.3,"rw":0.7,"rh":0.4,"t":3},{"rx":-7.04974651,"ry":0.0,"rw":0.7,"rh":0.55,"t":3},{"rx":-7.04974651,"ry":0.55,"rw":0.7,"rh":0.75,"t":3}],"grabs":[{"rx":-6.94974661,"ry":0.0,"rw":0.5,"rh":1.35,"t":4}],"clips":[{"rx":-6.94974661,"ry":0.0,"rw":0.5,"rh":1.35,"t":0}],"s":"604 5MK 60 +","x1":-6.04832172,"x2":-6.69974661,"x3":-6.63602543,"hit":0,"fl":0,"st":0,"c":null}],"p1":[],"p2":[],"i1":0,"i2":0},
{"f":2715,"p":[{"hits":[],"hurts":[{"rx":-7.47,"ry":1.45,"rw":0.45,"rh":0.35,"t":3},{"rx":-7.82,"ry":0.6,"rw":0.8,"rh":0.95,"t":3},{"rx":-7.82,"ry":0.0,"rw":0.8,"rh":0.6,"t":3}],"grabs":[{"rx":-7.72,"ry":0.0,"rw":0.6,"rh":1.4,"t":4}],"clips":[{"rx":-7.72,"ry":0.0,"rw":0.6,"rh":1.4,"t":0}],"s":"0 STAND 11","x1":-7.5,"x2":-7.5,"x3":-7.5,"hit":0,"fl":0,"st":0,"c":null},{"hits":[],"hurts":[{"rx":-7.04407454,"ry":1.3,"rw":0.7,"rh":0.4,"t":3},{"rx":-7.04407454,"ry":0.0,"rw":0.7,"rh":0.55,"t":3},{"rx":-7.04407454,"ry":0.55,"rw":0.7,"rh":0.75,"t":3}],"grabs":[{"rx":-6.94407463,"ry":0.0,"rw":0.5,"rh":1.35,"t":4}],"clips":[{"rx":-6.94407463,"ry":0.0,"rw":0.5,"rh":1.35,"t":0}],"s":"604 5MK 61 +","x1":-6.04832172,"x2":-6.69407463,"x3":-6.635984,"hit":0,"fl":0,"st":0,"c":null}],"p1":[],"p2":[],"i1":0,"i2":0},
{"f":2716,"p":[{"hits":[],"hurts":[{"rx":-7.47,"ry":1.45,"rw":0.45,"rh":0.35,"t":3},{"rx":-7.82,"ry":0.6,"rw":0.8,"rh":0.95,"t":3},{"rx":-7.82,"ry":0.0,"rw":0.8,"rh":0.6,"t":3}],"grabs":[{"rx":-7.72,"ry":0.0,"rw":0.6,"rh":1.4,"t":4}],"clips":[{"rx":-7.72,"ry":0.0,"rw":0.6,"rh":1.4,"t":0}],"s":"0 STAND 12","x1":-7.5,"x2":-7.5,"x3":-7.5,"hit":0,"fl":0,"st":0,"c":null},{"hits":[],"hurts":[{"rx":-7.03707647,"ry":1.3,"rw":0.7,"rh":0.4,"t":3},{"rx":-7.03707647,"ry":0.0,"rw":0.7,"rh":0.55,"t":3},{"rx":-7.03707647,"ry":0.55,"rw":0.7,"rh":0.75,"t":3}],"grabs":[{"rx":-6.93707657,"ry":0.0,"rw":0.5,"rh":1.35,"t":4}],"clips":[{"rx":-6.93707657,"ry":0.0,"rw":0.5,"rh":1.35,"t":0}],"s":"604 5MK 62 +","x1":-6.04832172,"x2":-6.68707657,"x3":-6.63600349,"hit":0,"fl":0,"st":0,"c":null}],"p1":[],"p2":[],"i1":0,"i2":0},
{"f":2717,"p":[{"hits":[],"hurts":[{"rx":-7.47,"ry":1.45,"rw":0.45,"rh":0.35,"t":3},{"rx":-7.82,"ry":0.6,"rw":0.8,"rh":0.95,"t":3},{"rx":-7.82,"ry":0.0,"rw":0.8,"rh":0.6,"t":3}],"grabs":[{"rx":-7.72,"ry":0.0,"rw":0.6,"rh":1.4,"t":4}],"clips":[{"rx":-7.72,"ry":0.0,"rw":0.6,"rh":1.4,"t":0}],"s":"0 STAND 13","x1":-7.5,"x2":-7.5,"x3":-7.5,"hit":0,"fl":0,"st":0,"c":null},{"hits":[],"hurts":[{"rx":-7.03078747,"ry":1.3,"rw":0.7,"rh":0.4,"t":3},{"rx":-7.03078747,"ry":0.0,"rw":0.7,"rh":0.55,"t":3},{"rx":-7.03078747,"ry":0.55,"rw":0.7,"rh":0.75,"t":3}],"grabs":[{"rx":-6.93078756,"ry":0.0,"rw":0.5,"rh":1.35,"t":4}],"clips":[{"rx":-6.93078756,"ry":0.0,"rw":0.5,"rh":1.35,"t":0}],"s":"604 5MK 63 +","x1":-6.04832172,"x2":-6.68078756,"x3":-6.636034,"hit":0,"fl":0,"st":0,"c":null}],"p1":[],"p2":[],"i1":0,"i2":0},
{"f":2718,"p":[{"hits":[],"hurts":[{"rx":-7.47,"ry":1.45,"rw":0.45,"rh":0.35,"t":3},{"rx":-7.82,"ry":0.6,"rw":0.8,"rh":0.95,"t":3},{"rx":-7.82,"ry":0.0,"rw":0.8,"rh":0.6,"t":3}],"grabs":[{"rx":-7.72,"ry":0.0,"rw":0.6,"rh":1.4,"t":4}],"clips":[{"rx":-7.72,"ry":0.0,"rw":0.6,"rh":1.4,"t":0}],"s":"0 STAND 14","x1":-7.5,"x2":-7.5,"x3":-7.5,"hit":0,"fl":0,"st":0,"c":null},{"hits":[],"hurts":[{"rx":-7.02551365,"ry":1.3,"rw":0.7,"rh":0.4,"t":3},{"rx":-7.02551365,"ry":0.0,"rw":0.7,"rh":0.55,"t":3},{"rx":-7.02551365,"ry":0.55,"rw":0.7,"rh":0.75,"t":3}],"grabs":[{"rx":-6.92551374,"ry":0.0,"rw":0.5,"rh":1.35,"t":4}],"clips":[{"rx":-6.92551374,"ry":0.0,"rw":0.5,"rh":1.35,"t":0}],"s":"604 5MK 64 +","x1":-6.04832172,"x2":-6.67551374,"x3":-6.636043,"hit":0,"fl":0,"st":0,"c":null}],"p1":[],"p2":[],"i1":0,"i2":0},
{"f":2719,"p":[{"hits":[],"hurts":[{"rx":-7.47,"ry":1.45,"rw":0.45,"rh":0.35,"t":3},{"rx":-7.82,"ry":0.6,"rw":0.8,"rh":0.95,"t":3},{"rx":-7.82,"ry":0.0,"rw":0.8,"rh":0.6,"t":3}],"grabs":[{"rx":-7.72,"ry":0.0,"rw":0.6,"rh":1.4,"t":4}],"clips":[{"rx":-7.72,"ry":0.0,"rw":0.6,"rh":1.4,"t":0}],"s":"0 STAND 15","x1":-7.5,"x2":-7.5,"x3":-7.5,"hit":0,"fl":0,"st":0,"c":null},{"hits":[],"hurts":[{"rx":-7.02052546,"ry":1.3,"rw":0.7,"rh":0.4,"t":3},{"rx":-7.02052546,"ry":0.0,"rw":0.7,"rh":0.55,"t":3},{"rx":-7.02052546,"ry":0.55,"rw":0.7,"rh":0.75,"t":3}],"grabs":[{"rx":-6.92052555,"ry":0.0,"rw":0.5,"rh":1.35,"t":4}],"clips":[{"rx":-6.92052555,"ry":0.0,"rw":0.5,"rh":1.35,"t":0}],"s":"604 5MK 65 +","x1":-6.04832172,"x2":-6.67052555,"x3":-6.636057,"hit":0,"fl":0,"st":0,"c":null}],"p1":[],"p2":[],"i1":0,"i2":0},
{"f":2720,"p":[{"hits":[],"hurts":[{"rx":-7.47,"ry":1.45,"rw":0.45,"rh":0.35,"t":3},{"rx":-7.82,"ry":0.6,"rw":0.8,"rh":0.95,"t":3},{"rx":-7.82,"ry":0.0,"rw":0.8,"rh":0.6,"t":3}],"grabs":[{"rx":-7.72,"ry":0.0,"rw":0.6,"rh":1.4,"t":4}],"clips":[{"rx":-7.72,"ry":0.0,"rw":0.6,"rh":1.4,"t":0}],"s":"0 STAND 16","x1":-7.5,"x2":-7.5,"x3":-7.5,"hit":0,"fl":0,"st":0,"c":null},{"hits":[],"hurts":[{"rx":-7.01600456,"ry":1.3,"rw":0.7,"rh":0.4,"t":3},{"rx":-7.01600456,"ry":0.0,"rw":0.7,"rh":0.55,"t":3},{"rx":-7.01600456,"ry":0.55,"rw":0.7,"rh":0.75,"t":3}],"grabs":[{"rx":-6.91600466,"ry":0.0,"rw":0.5,"rh":1.35,"t":4}],"clips":[{"rx":-6.91600466,"ry":0.0,"rw":0.5,"rh":1.35,"t":0}],"s":"604 5MK 66 +","x1":-6.04832172,"x2":-6.66600466,"x3":-6.636059,"hit":0,"fl":0,"st":0,"c":null}],"p1":[],"p2":[],"i1":0,"i2":0},
{"f":2721,"p":[{"hits":[],"hurts":[{"rx":-7.47,"ry":1.45,"rw":0.45,"rh":0.35,"t":3},{"rx":-7.82,"ry":0.6,"rw":0.8,"rh":0.95,"t":3},{"rx":-7.82,"ry":0.0,"rw":0.8,"rh":0.6,"t":3}],"grabs":[{"rx":-7.72,"ry":0.0,"rw":0.6,"rh":1.4,"t":4}],"clips":[{"rx":-7.72,"ry":0.0,"rw":0.6,"rh":1.4,"t":0}],"s":"0 STAND 17","x1":-7.5,"x2":-7.5,"x3":-7.5,"hit":0,"fl":0,"st":0,"c":null},{"hits":[],"hurts":[{"rx":-7.011541,"ry":1.3,"rw":0.7,"rh":0.4,"t":3},{"rx":-7.011541,"ry":0.0,"rw":0.7,"rh":0.55,"t":3},{"rx":-7.011541,"ry":0.55,"rw":0.7,"rh":0.75,"t":3}],"grabs":[{"rx":-6.911541,"ry":0.0,"rw":0.5,"rh":1.35,"t":4}],"clips":[{"rx":-6.911541,"ry":0.0,"rw":0.5,"rh":1.35,"t":0}],"s":"604 5MK 67 +","x1":-6.04832172,"x2":-6.661541,"x3":-6.63604927,"hit":0,"fl":0,"st":0,"c":null}],"p1":[],"p2":[],"i1":0,"i2":0},
{"f":2722,"p":[{"hits":[],"hurts":[{"rx":-7.47,"ry":1.45,"rw":0.45,"rh":0.35,"t":3},{"rx":-7.82,"ry":0.6,"rw":0.8,"rh":0.95,"t":3},{"rx":-7.82,"ry":0.0,"rw":0.8,"rh":0.6,"t":3}],"grabs":[{"rx":-7.72,"ry":0.0,"rw":0.6,"rh":1.4,"t":4}],"clips":[{"rx":-7.72,"ry":0.0,"rw":0.6,"rh":1.4,"t":0}],"s":"0 STAND 18","x1":-7.5,"x2":-7.5,"x3":-7.5,"hit":0,"fl":0,"st":0,"c":null},{"hits":[],"hurts":[{"rx":-7.0067687,"ry":1.3,"rw":0.7,"rh":0.4,"t":3},{"rx":-7.0067687,"ry":0.0,"rw":0.7,"rh":0.55,"t":3},{"rx":-7.0067687,"ry":0.55,"rw":0.7,"rh":0.75,"t":3}],"grabs":[{"rx":-6.906769,"ry":0.0,"rw":0.5,"rh":1.35,"t":4}],"clips":[{"rx":-6.906769,"ry":0.0,"rw":0.5,"rh":1.35,"t":0}],"s":"604 5MK 68 +","x1":-6.04832172,"x2":-6.656769,"x3":-6.636053,"hit":0,"fl":0,"st":0,"c":null}],"p1":[],"p2":[],"i1":0,"i2":0},
{"f":2723,"p":[{"hits":[],"hurts":[{"rx":-7.47,"ry":1.45,"rw":0.45,"rh":0.35,"t":3},{"rx":-7.82,"ry":0.6,"rw":0.8,"rh":0.95,"t":3},{"rx":-7.82,"ry":0.0,"rw":0.8,"rh":0.6,"t":3}],"grabs":[{"rx":-7.72,"ry":0.0,"rw":0.6,"rh":1.4,"t":4}],"clips":[{"rx":-7.72,"ry":0.0,"rw":0.6,"rh":1.4,"t":0}],"s":"0 STAND 19","x1":-7.5,"x2":-7.5,"x3":-7.5,"hit":0,"fl":0,"st":0,"c":null},{"hits":[],"hurts":[{"rx":-7.00216246,"ry":1.3,"rw":0.7,"rh":0.4,"t":3},{"rx":-7.00216246,"ry":0.0,"rw":0.7,"rh":0.55,"t":3},{"rx":-7.00216246,"ry":0.55,"rw":0.7,"rh":0.75,"t":3}],"grabs":[{"rx":-6.90216255,"ry":0.0,"rw":0.5,"rh":1.35,"t":4}],"clips":[{"rx":-6.90216255,"ry":0.0,"rw":0.5,"rh":1.35,"t":0}],"s":"604 5MK 69 +","x1":-6.04832172,"x2":-6.65216255,"x3":-6.63606453,"hit":0,"fl":0,"st":0,"c":null}],"p1":[],"p2":[],"i1":0,"i2":0},
{"f":2724,"p":[{"hits":[],"hurts":[{"rx":-7.47,"ry":1.45,"rw":0.45,"rh":0.35,"t":3},{"rx":-7.82,"ry":0.6,"rw":0.8,"rh":0.95,"t":3},{"rx":-7.82,"ry":0.0,"rw":0.8,"rh":0.6,"t":3}],"grabs":[{"rx":-7.72,"ry":0.0,"rw":0.6,"rh":1.4,"t":4}],"clips":[{"rx":-7.72,"ry":0.0,"rw":0.6,"rh":1.4,"t":0}],"s":"0 STAND 20","x1":-7.5,"x2":-7.5,"x3":-7.5,"hit":0,"fl":0,"st":0,"c":null},{"hits":[],"hurts":[{"rx":-6.99783468,"ry":1.3,"rw":0.7,"rh":0.4,"t":3},{"rx":-6.99783468,"ry":0.0,"rw":0.7,"rh":0.55,"t":3},{"rx":-6.99783468,"ry":0.55,"rw":0.7,"rh":0.75,"t":3}],"grabs":[{"rx":-6.897835,"ry":0.0,"rw":0.5,"rh":1.35,"t":4}],"clips":[{"rx":-6.897835,"ry":0.0,"rw":0.5,"rh":1.35,"t":0}],"s":"604 5MK 70 +","x1":-6.04832172,"x2":-6.647835,"x3":-6.63607836,"hit":0,"fl":0,"st":0,"c":null}],"p1":[],"p2":[],"i1":0,"i2":0},
{"f":2725,"p":[{"hits":[],"hurts":[{"rx":-7.47,"ry":1.45,"rw":0.45,"rh":0.35,"t":3},{"rx":-7.82,"ry":0.6,"rw":0.8,"rh":0.95,"t":3},{"rx":-7.82,"ry":0.0,"rw":0.8,"rh":0.6,"t":3}],"grabs":[{"rx":-7.72,"ry":0.0,"rw":0.6,"rh":1.4,"t":4}],"clips":[{"rx":-7.72,"ry":0.0,"rw":0.6,"rh":1.4,"t":0}],"s":"0 STAND 21","x1":-7.5,"x2":-7.5,"x3":-7.5,"hit":0,"fl":0,"st":0,"c":null},{"hits":[],"hurts":[{"rx":-6.993983,"ry":1.3,"rw":0.7,"rh":0.4,"t":3},{"rx":-6.993983,"ry":0.0,"rw":0.7,"rh":0.55,"t":3},{"rx":-6.993983,"ry":0.55,"rw":0.7,"rh":0.75,"t":3}],"grabs":[{"rx":-6.893983,"ry":0.0,"rw":0.5,"rh":1.35,"t":4}],"clips":[{"rx":-6.893983,"ry":0.0,"rw":0.5,"rh":1.35,"t":0}],"s":"604 5MK 71 +","x1":-6.04832172,"x2":-6.643983,"x3":-6.63609362,"hit":0,"fl":0,"st":0,"c":null}],"p1":[],"p2":[],"i1":0,"i2":0},
{"f":2726,"p":[{"hits":[],"hurts":[{"rx":-7.47,"ry":1.45,"rw":0.45,"rh":0.35,"t":3},{"rx":-7.82,"ry":0.6,"rw":0.8,"rh":0.95,"t":3},{"rx":-7.82,"ry":0.0,"rw":0.8,"rh":0.6,"t":3}],"grabs":[{"rx":-7.72,"ry":0.0,"rw":0.6,"rh":1.4,"t":4}],"clips":[{"rx":-7.72,"ry":0.0,"rw":0.6,"rh":1.4,"t":0}],"s":"0 STAND 22","x1":-7.5,"x2":-7.5,"x3":-7.5,"hit":0,"fl":0,"st":0,"c":null},{"hits":[],"hurts":[{"rx":-6.99068069,"ry":1.3,"rw":0.7,"rh":0.4,"t":3},{"rx":-6.99068069,"ry":0.0,"rw":0.7,"rh":0.55,"t":3},{"rx":-6.99068069,"ry":0.55,"rw":0.7,"rh":0.75,"t":3}],"grabs":[{"rx":-6.890681,"ry":0.0,"rw":0.5,"rh":1.35,"t":4}],"clips":[{"rx":-6.890681,"ry":0.0,"rw":0.5,"rh":1.35,"t":0}],"s":"604 5MK 72 +","x1":-6.04832172,"x2":-6.640681,"x3":-6.63613462,"hit":0,"fl":0,"st":0,"c":null}],"p1":[],"p2":[],"i1":0,"i2":0},
{"f":2727,"p":[{"hits":[],"hurts":[{"rx":-7.47,"ry":1.45,"rw":0.45,"rh":0.35,"t":3},{"rx":-7.82,"ry":0.6,"rw":0.8,"rh":0.95,"t":3},{"rx":-7.82,"ry":0.0,"rw":0.8,"rh":0.6,"t":3}],"grabs":[{"rx":-7.72,"ry":0.0,"rw":0.6,"rh":1.4,"t":4}],"clips":[{"rx":-7.72,"ry":0.0,"rw":0.6,"rh":1.4,"t":0}],"s":"0 STAND 23","x1":-7.5,"x2":-7.5,"x3":-7.5,"hit":0,"fl":0,"st":0,"c":null},{"hits":[],"hurts":[{"rx":-6.98872137,"ry":1.3,"rw":0.7,"rh":0.4,"t":3},{"rx":-6.98872137,"ry":0.0,"rw":0.7,"rh":0.55,"t":3},{"rx":-6.98872137,"ry":0.55,"rw":0.7,"rh":0.75,"t":3}],"grabs":[{"rx":-6.88872147,"ry":0.0,"rw":0.5,"rh":1.35,"t":4}],"clips":[{"rx":-6.88872147,"ry":0.0,"rw":0.5,"rh":1.35,"t":0}],"s":"604 5MK 73 +","x1":-6.04832172,"x2":-6.63872147,"x3":-6.636168,"hit":0,"fl":0,"st":0,"c":null}],"p1":[],"p2":[],"i1":0,"i2":0},
{"f":2728,"p":[{"hits":[],"hurts":[{"rx":-7.47,"ry":1.45,"rw":0.45,"rh":0.35,"t":3},{"rx":-7.82,"ry":0.6,"rw":0.8,"rh":0.95,"t":3},{"rx":-7.82,"ry":0.0,"rw":0.8,"rh":0.6,"t":3}],"grabs":[{"rx":-7.72,"ry":0.0,"rw":0.6,"rh":1.4,"t":4}],"clips":[{"rx":-7.72,"ry":0.0,"rw":0.6,"rh":1.4,"t":0}],"s":"0 STAND 24","x1":-7.5,"x2":-7.5,"x3":-7.5,"hit":0,"fl":0,"st":0,"c":null},{"hits":[],"hurts":[{"rx":-6.987847,"ry":1.3,"rw":0.7,"rh":0.4,"t":3},{"rx":-6.987847,"ry":0.0,"rw":0.7,"rh":0.55,"t":3},{"rx":-6.987847,"ry":0.55,"rw":0.7,"rh":0.75,"t":3}],"grabs":[{"rx":-6.887847,"ry":0.0,"rw":0.5,"rh":1.35,"t":4}],"clips":[{"rx":-6.887847,"ry":0.0,"rw":0.5,"rh":1.35,"t":0}],"s":"604 5MK 74 +","x1":-6.04832172,"x2":-6.637847,"x3":-6.63617134,"hit":0,"fl":0,"st":0,"c":null}],"p1":[],"p2":[],"i1":0,"i2":0},
{"f":2729,"p":[{"hits":[],"hurts":[{"rx":-7.47,"ry":1.45,"rw":0.45,"rh":0.35,"t":3},{"rx":-7.82,"ry":0.6,"rw":0.8,"rh":0.95,"t":3},{"rx":-7.82,"ry":0.0,"rw":0.8,"rh":0.6,"t":3}],"grabs":[{"rx":-7.72,"ry":0.0,"rw":0.6,"rh":1.4,"t":4}],"clips":[{"rx":-7.72,"ry":0.0,"rw":0.6,"rh":1.4,"t":0}],"s":"0 STAND 25","x1":-7.5,"x2":-7.5,"x3":-7.5,"hit":0,"fl":0,"st":0,"c":null},{"hits":[],"hurts":[{"rx":-6.98708773,"ry":1.3,"rw":0.7,"rh":0.4,"t":3},{"rx":-6.98708773,"ry":0.0,"rw":0.7,"rh":0.55,"t":3},{"rx":-6.98708773,"ry":0.55,"rw":0.7,"rh":0.75,"t":3}],"grabs":[{"rx":-6.887088,"ry":0.0,"rw":0.5,"rh":1.35,"t":4}],"clips":[{"rx":-6.887088,"ry":0.0,"rw":0.5,"rh":1.35,"t":0}],"s":"604 5MK 75 +","x1":-6.04832172,"x2":-6.637088,"x3":-6.636183,"hit":0,"fl":0,"st":0,"c":null}],"p1":[],"p2":[],"i1":0,"i2":0},
{"f":2730,"p":[{"hits":[],"hurts":[{"rx":-7.47,"ry":1.45,"rw":0.45,"rh":0.35,"t":3},{"rx":-7.82,"ry":0.6,"rw":0.8,"rh":0.95,"t":3},{"rx":-7.82,"ry":0.0,"rw":0.8,"rh":0.6,"t":3}],"grabs":[{"rx":-7.72,"ry":0.0,"rw":0.6,"rh":1.4,"t":4}],"clips":[{"rx":-7.72,"ry":0.0,"rw":0.6,"rh":1.4,"t":0}],"s":"0 STAND 26","x1":-7.5,"x2":-7.5,"x3":-7.5,"hit":0,"fl":0,"st":0,"c":null},{"hits":[],"hurts":[{"rx":-6.98666954,"ry":1.3,"rw":0.7,"rh":0.4,"t":3},{"rx":-6.98666954,"ry":0.0,"rw":0.7,"rh":0.55,"t":3},{"rx":-6.98666954,"ry":0.55,"rw":0.7,"rh":0.75,"t":3}],"grabs":[{"rx":-6.88666964,"ry":0.0,"rw":0.5,"rh":1.35,"t":4}],"clips":[{"rx":-6.88666964,"ry":0.0,"rw":0.5,"rh":1.35,"t":0}],"s":"604 5MK 76 +","x1":-6.04832172,"x2":-6.63666964,"x3":-6.636185,"hit":0,"fl":0,"st":0,"c":null}],"p1":[],"p2":[],"i1":0,"i2":0},
{"f":2731,"p":[{"hits":[],"hurts":[{"rx":-7.47,"ry":1.45,"rw":0.45,"rh":0.35,"t":3},{"rx":-7.82,"ry":0.6,"rw":0.8,"rh":0.95,"t":3},{"rx":-7.82,"ry":0.0,"rw":0.8,"rh":0.6,"t":3}],"grabs":[{"rx":-7.72,"ry":0.0,"rw":0.6,"rh":1.4,"t":4}],"clips":[{"rx":-7.72,"ry":0.0,"rw":0.6,"rh":1.4,"t":0}],"s":"0 STAND 27","x1":-7.5,"x2":-7.5,"x3":-7.5,"hit":0,"fl":0,"st":0,"c":null},{"hits":[],"hurts":[{"rx":-6.98633242,"ry":1.3,"rw":0.7,"rh":0.4,"t":3},{"rx":-6.98633242,"ry":0.0,"rw":0.7,"rh":0.55,"t":3},{"rx":-6.98633242,"ry":0.55,"rw":0.7,"rh":0.75,"t":3}],"grabs":[{"rx":-6.88633251,"ry":0.0,"rw":0.5,"rh":1.35,"t":4}],"clips":[{"rx":-6.88633251,"ry":0.0,"rw":0.5,"rh":1.35,"t":0}],"s":"604 5MK 77 +","x1":-6.04832172,"x2":-6.63633251,"x3":-6.63619,"hit":0,"fl":0,"st":0,"c":null}],"p1":[],"p2":[],"i1":0,"i2":0},
{"f":2732,"p":[{"hits":[],"hurts":[{"rx":-7.47,"ry":1.45,"rw":0.45,"rh":0.35,"t":3},{"rx":-7.82,"ry":0.6,"rw":0.8,"rh":0.95,"t":3},{"rx":-7.82,"ry":0.0,"rw":0.8,"rh":0.6,"t":3}],"grabs":[{"rx":-7.72,"ry":0.0,"rw":0.6,"rh":1.4,"t":4}],"clips":[{"rx":-7.72,"ry":0.0,"rw":0.6,"rh":1.4,"t":0}],"s":"0 STAND 28","x1":-7.5,"x2":-7.5,"x3":-7.5,"hit":0,"fl":0,"st":0,"c":null},{"hits":[],"hurts":[{"rx":-6.98619556,"ry":1.3,"rw":0.7,"rh":0.4,"t":3},{"rx":-6.98619556,"ry":0.0,"rw":0.7,"rh":0.55,"t":3},{"rx":-6.98619556,"ry":0.55,"rw":0.7,"rh":0.75,"t":3}],"grabs":[{"rx":-6.88619566,"ry":0.0,"rw":0.5,"rh":1.35,"t":4}],"clips":[{"rx":-6.88619566,"ry":0.0,"rw":0.5,"rh":1.35,"t":0}],"s":"604 5MK 78 +","x1":-6.04832172,"x2":-6.63619566,"x3":-6.636194,"hit":0,"fl":0,"st":0,"c":null}],"p1":[],"p2":[],"i1":0,"i2":0},
{"f":2733,"p":[{"hits":[],"hurts":[{"rx":-7.47,"ry":1.45,"rw":0.45,"rh":0.35,"t":3},{"rx":-7.82,"ry":0.6,"rw":0.8,"rh":0.95,"t":3},{"rx":-7.82,"ry":0.0,"rw":0.8,"rh":0.6,"t":3}],"grabs":[{"rx":-7.72,"ry":0.0,"rw":0.6,"rh":1.4,"t":4}],"clips":[{"rx":-7.72,"ry":0.0,"rw":0.6,"rh":1.4,"t":0}],"s":"0 STAND 29","x1":-7.5,"x2":-7.5,"x3":-7.5,"hit":0,"fl":0,"st":0,"c":null},{"hits":[],"hurts":[{"rx":-6.936196,"ry":1.3,"rw":0.42,"rh":0.4,"t":3},{"rx":-6.98619556,"ry":0.55,"rw":0.7,"rh":0.98,"t":3},{"rx":-6.98619556,"ry":0.0,"rw":0.7,"rh":0.55,"t":3}],"grabs":[{"rx":-6.88619566,"ry":0.0,"rw":0.5,"rh":1.35,"t":4}],"clips":[{"rx":-6.88619566,"ry":0.0,"rw":0.5,"rh":1.35,"t":0}],"s":"0 STAND 1","x1":-6.63619566,"x2":-6.63619566,"x3":-6.63619566,"hit":0,"fl":0,"st":0,"c":null}],"p1":[],"p2":[],"i1":0,"i2":0},
{"f":2734,"p":[{"hits":[],"hurts":[{"rx":-7.47,"ry":1.45,"rw":0.45,"rh":0.35,"t":3},{"rx":-7.82,"ry":0.6,"rw":0.8,"rh":0.95,"t":3},{"rx":-7.82,"ry":0.0,"rw":0.8,"rh":0.6,"t":3}],"grabs":[{"rx":-7.72,"ry":0.0,"rw":0.6,"rh":1.4,"t":4}],"clips":[{"rx":-7.72,"ry":0.0,"rw":0.6,"rh":1.4,"t":0}],"s":"0 STAND 30","x1":-7.5,"x2":-7.5,"x3":-7.5,"hit":0,"fl":0,"st":0,"c":null},{"hits":[],"hurts":[{"rx":-6.936196,"ry":1.3,"rw":0.42,"rh":0.4,"t":3},{"rx":-6.98619556,"ry":0.55,"rw":0.7,"rh":0.98,"t":3},{"rx":-6.98619556,"ry":0.0,"rw":0.7,"rh":0.55,"t":3}],"grabs":[{"rx":-6.88619566,"ry":0.0,"rw":0.5,"rh":1.35,"t":4}],"clips":[{"rx":-6.88619566,"ry":0.0,"rw":0.5,"rh":1.35,"t":0}],"s":"0 STAND 2","x1":-6.63619566,"x2":-6.63619566,"x3":-6.63619566,"hit":0,"fl":0,"st":0,"c":null}],"p1":[],"p2":[],"i1":0,"i2":0},
{"f":2735,"p":[{"hits":[],"hurts":[{"rx":-7.47,"ry":1.45,"rw":0.45,"rh":0.35,"t":3},{"rx":-7.82,"ry":0.6,"rw":0.8,"rh":0.95,"t":3},{"rx":-7.82,"ry":0.0,"rw":0.8,"rh":0.6,"t":3}],"grabs":[{"rx":-7.72,"ry":0.0,"rw":0.6,"rh":1.4,"t":4}],"clips":[{"rx":-7.72,"ry":0.0,"rw":0.6,"rh":1.4,"t":0}],"s":"0 STAND 31","x1":-7.5,"x2":-7.5,"x3":-7.5,"hit":0,"fl":0,"st":0,"c":null},{"hits":[],"hurts":[{"rx":-6.936196,"ry":1.3,"rw":0.42,"rh":0.4,"t":3},{"rx":-6.98619556,"ry":0.55,"rw":0.7,"rh":0.98,"t":3},{"rx":-6.98619556,"ry":0.0,"rw":0.7,"rh":0.55,"t":3}],"grabs":[{"rx":-6.88619566,"ry":0.0,"rw":0.5,"rh":1.35,"t":4}],"clips":[{"rx":-6.88619566,"ry":0.0,"rw":0.5,"rh":1.35,"t":0}],"s":"0 STAND 3","x1":-6.63619566,"x2":-6.63619566,"x3":-6.63619566,"hit":0,"fl":0,"st":0,"c":null}],"p1":[],"p2":[],"i1":0,"i2":0},
{"f":2736,"p":[{"hits":[],"hurts":[{"rx":-7.47,"ry":1.45,"rw":0.45,"rh":0.35,"t":3},{"rx":-7.82,"ry":0.6,"rw":0.8,"rh":0.95,"t":3},{"rx":-7.82,"ry":0.0,"rw":0.8,"rh":0.6,"t":3}],"grabs":[{"rx":-7.72,"ry":0.0,"rw":0.6,"rh":1.4,"t":4}],"clips":[{"rx":-7.72,"ry":0.0,"rw":0.6,"rh":1.4,"t":0}],"s":"0 STAND 32","x1":-7.5,"x2":-7.5,"x3":-7.5,"hit":0,"fl":0,"st":0,"c":null},{"hits":[],"hurts":[{"rx":-6.936196,"ry":1.3,"rw":0.42,"rh":0.4,"t":3},{"rx":-6.98619556,"ry":0.55,"rw":0.7,"rh":0.98,"t":3},{"rx":-6.98619556,"ry":0.0,"rw":0.7,"rh":0.55,"t":3}],"grabs":[{"rx":-6.88619566,"ry":0.0,"rw":0.5,"rh":1.35,"t":4}],"clips":[{"rx":-6.88619566,"ry":0.0,"rw":0.5,"rh":1.35,"t":0}],"s":"0 STAND 4","x1":-6.63619566,"x2":-6.63619566,"x3":-6.63619566,"hit":0,"fl":0,"st":0,"c":null}],"p1":[],"p2":[],"i1":0,"i2":0},
{"f":2737,"p":[{"hits":[],"hurts":[{"rx":-7.47,"ry":1.45,"rw":0.45,"rh":0.35,"t":3},{"rx":-7.82,"ry":0.6,"rw":0.8,"rh":0.95,"t":3},{"rx":-7.82,"ry":0.0,"rw":0.8,"rh":0.6,"t":3}],"grabs":[{"rx":-7.72,"ry":0.0,"rw":0.6,"rh":1.4,"t":4}],"clips":[{"rx":-7.72,"ry":0.0,"rw":0.6,"rh":1.4,"t":0}],"s":"0 STAND 33","x1":-7.5,"x2":-7.5,"x3":-7.5,"hit":0,"fl":0,"st":0,"c":null},{"hits":[],"hurts":[{"rx":-6.936196,"ry":1.3,"rw":0.42,"rh":0.4,"t":3},{"rx":-6.98619556,"ry":0.55,"rw":0.7,"rh":0.98,"t":3},{"rx":-6.98619556,"ry":0.0,"rw":0.7,"rh":0.55,"t":3}],"grabs":[{"rx":-6.88619566,"ry":0.0,"rw":0.5,"rh":1.35,"t":4}],"clips":[{"rx":-6.88619566,"ry":0.0,"rw":0.5,"rh":1.35,"t":0}],"s":"0 STAND 5","x1":-6.63619566,"x2":-6.63619566,"x3":-6.63619566,"hit":0,"fl":0,"st":0,"c":null}],"p1":[],"p2":[],"i1":0,"i2":0},
{"f":2738,"p":[{"hits":[],"hurts":[{"rx":-7.47,"ry":1.45,"rw":0.45,"rh":0.35,"t":3},{"rx":-7.82,"ry":0.6,"rw":0.8,"rh":0.95,"t":3},{"rx":-7.82,"ry":0.0,"rw":0.8,"rh":0.6,"t":3}],"grabs":[{"rx":-7.72,"ry":0.0,"rw":0.6,"rh":1.4,"t":4}],"clips":[{"rx":-7.72,"ry":0.0,"rw":0.6,"rh":1.4,"t":0}],"s":"0 STAND 34","x1":-7.5,"x2":-7.5,"x3":-7.5,"hit":0,"fl":0,"st":0,"c":null},{"hits":[],"hurts":[{"rx":-6.936196,"ry":1.3,"rw":0.42,"rh":0.4,"t":3},{"rx":-6.98619556,"ry":0.55,"rw":0.7,"rh":0.98,"t":3},{"rx":-6.98619556,"ry":0.0,"rw":0.7,"rh":0.55,"t":3}],"grabs":[{"rx":-6.88619566,"ry":0.0,"rw":0.5,"rh":1.35,"t":4}],"clips":[{"rx":-6.88619566,"ry":0.0,"rw":0.5,"rh":1.35,"t":0}],"s":"0 STAND 6","x1":-6.63619566,"x2":-6.63619566,"x3":-6.63619566,"hit":0,"fl":0,"st":0,"c":null}],"p1":[],"p2":[],"i1":0,"i2":0}]