[
{"f":1781,"p":[{"hits":[],"hurts":[{"rx":-7.47,"ry":1.45,"rw":0.45,"rh":0.35,"t":3},{"rx":-7.82,"ry":0.6,"rw":0.8,"rh":0.95,"t":3},{"rx":-7.82,"ry":0.0,"rw":0.8,"rh":0.6,"t":3}],"grabs":[{"rx":-7.72,"ry":0.0,"rw":0.6,"rh":1.4,"t":4}],"clips":[{"rx":-7.72,"ry":0.0,"rw":0.6,"rh":1.4,"t":0}],"s":"0 STAND 446","x1":-7.5,"x2":-7.5,"x3":-7.5,"hit":0,"fl":0,"st":0,"c":null},{"hits":[],"hurts":[{"rx":-6.84999943,"ry":1.3,"rw":0.7,"rh":0.4,"t":3},{"rx":-6.84999943,"ry":0.0,"rw":0.7,"rh":0.55,"t":3},{"rx":-6.84999943,"ry":0.55,"rw":0.7,"rh":0.75,"t":3}],"grabs":[{"rx":-6.74999952,"ry":0.0,"rw":0.5,"rh":1.35,"t":4}],"clips":[{"rx":-6.74999952,"ry":0.0,"rw":0.5,"rh":1.35,"t":0}],"s":"602 5HP 1","x1":-6.39999962,"x2":-6.39999962,"x3":-6.399999,"hit":0,"fl":0,"st":32,"c":null}],"p1":[],"p2":[],"i1":2560,"i2":0},
{"f":1782,"p":[{"hits":[],"hurts":[{"rx":-8.2,"ry":1.55,"rw":1.3,"rh":0.35,"t":3},{"rx":-8.2,"ry":0.6,"rw":1.3,"rh":0.95,"t":3},{"rx":-8.2,"ry":0.0,"rw":1.3,"rh":0.6,"t":3}],"grabs":[{"rx":-7.95,"ry":0.0,"rw":0.9,"rh":1.4,"t":4}],"clips":[{"rx":-7.95,"ry":0.0,"rw":0.900000036,"rh":1.4,"t":0}],"s":"758 VT_LARIAT_CHARGE 1","x1":-7.5,"x2":-7.5,"x3":-7.5,"hit":0,"fl":0,"st":32,"c":null},{"hits":[],"hurts":[{"rx":-6.84999943,"ry":1.3,"rw":0.7,"rh":0.4,"t":3},{"rx":-6.84999943,"ry":0.0,"rw":0.7,"rh":0.55,"t":3},{"rx":-6.84999943,"ry":0.55,"rw":0.7,"rh":0.75,"t":3}],"grabs":[{"rx":-6.74999952,"ry":0.0,"rw":0.5,"rh":1.35,"t":4}],"clips":[{"rx":-6.74999952,"ry":0.0,"rw":0.5,"rh":1.35,"t":0}],"s":"602 5HP 2","x1":-6.39999962,"x2":-6.39999962,"x3":-6.399999,"hit":0,"fl":29,"st":32,"c":null}],"p1":[],"p2":[],"i1":0,"i2":0},
{"f":1783,"p":[{"hits":[],"hurts":[{"rx":-8.2,"ry":1.55,"rw":1.3,"rh":0.35,"t":3},{"rx":-8.2,"ry":0.6,"rw":1.3,"rh":0.95,"t":3},{"rx":-8.2,"ry":0.0,"rw":1.3,"rh":0.6,"t":3},{"rx":-8.2,"ry":1.55,"rw":1.3,"rh":0.35,"t":3},{"rx":-8.2,"ry":0.4,"rw":1.3,"rh":1.15,"t":3},{"rx":-8.2,"ry":0.0,"rw":1.3,"rh":0.4,"t":3}],"grabs":[{"rx":-7.95,"ry":0.0,"rw":0.9,"rh":1.4,"t":4}],"clips":[{"rx":-7.95,"ry":0.0,"rw":0.900000036,"rh":1.4,"t":0}],"s":"758 VT_LARIAT_CHARGE 2","x1":-7.5,"x2":-7.5,"x3":-7.5,"hit":0,"fl":115,"st":32,"c":null},{"hits":[],"hurts":[{"rx":-6.84999943,"ry":1.3,"rw":0.7,"rh":0.4,"t":3},{"rx":-6.84999943,"ry":0.0,"rw":0.7,"rh":0.55,"t":3},{"rx":-6.84999943,"ry":0.55,"rw":0.7,"rh":0.75,"t":3}],"grabs":[{"rx":-6.74999952,"ry":0.0,"rw":0.5,"rh":1.35,"t":4}],"clips":[{"rx":-6.74999952,"ry":0.0,"rw":0.5,"rh":1.35,"t":0}],"s":"602 5HP 3","x1":-6.39999962,"x2":-6.39999962,"x3":-6.399999,"hit":0,"fl":28,"st":32,"c":null}],"p1":[],"p2":[],"i1":0,"i2":0},
{"f":1784,"p":[{"hits":[],"hurts":[{"rx":-8.2,"ry":1.55,"rw":1.3,"rh":0.35,"t":3},{"rx":-8.2,"ry":0.6,"rw":1.3,"rh":0.95,"t":3},{"rx":-8.2,"ry":0.0,"rw":1.3,"rh":0.6,"t":3},{"rx":-8.2,"ry":1.55,"rw":1.3,"rh":0.35,"t":3},{"rx":-8.2,"ry":0.4,"rw":1.3,"rh":1.15,"t":3},{"rx":-8.2,"ry":0.0,"rw":1.3,"rh":0.4,"t":3}],"grabs":[{"rx":-7.95,"ry":0.0,"rw":0.9,"rh":1.4,"t":4}],"clips":[{"rx":-7.95,"ry":0.0,"rw":0.900000036,"rh":1.4,"t":0}],"s":"758 VT_LARIAT_CHARGE 3","x1":-7.5,"x2":-7.5,"x3":-7.5,"hit":0,"fl":114,"st":32,"c":null},{"hits":[],"hurts":[{"rx":-6.95,"ry":1.3,"rw":0.7,"rh":0.4,"t":3},{"rx":-6.95,"ry":0.0,"rw":0.7,"rh":0.55,"t":3},{"rx":-6.95,"ry":0.55,"rw":0.7,"rh":0.75,"t":3}],"grabs":[{"rx":-6.84999943,"ry":0.0,"rw":0.5,"rh":1.35,"t":4}],"clips":[{"rx":-6.74999952,"ry":0.0,"rw":0.5,"rh":1.35,"t":0}],"s":"602 5HP 4","x1":-6.39999962,"x2":-6.39999962,"x3":-6.399999,"hit":0,"fl":27,"st":32,"c":null}],"p1":[],"p2":[],"i1":0,"i2":0},
{"f":1785,"p":[{"hits":[],"hurts":[{"rx":-8.2,"ry":1.55,"rw":1.3,"rh":0.35,"t":3},{"rx":-8.2,"ry":0.6,"rw":1.3,"rh":0.95,"t":3},{"rx":-8.2,"ry":0.0,"rw":1.3,"rh":0.6,"t":3},{"rx":-8.2,"ry":1.55,"rw":1.3,"rh":0.35,"t":3},{"rx":-8.2,"ry":0.4,"rw":1.3,"rh":1.15,"t":3},{"rx":-8.2,"ry":0.0,"rw":1.3,"rh":0.4,"t":3}],"grabs":[{"rx":-7.95,"ry":0.0,"rw":0.9,"rh":1.4,"t":4}],"clips":[{"rx":-7.95,"ry":0.0,"rw":0.900000036,"rh":1.4,"t":0}],"s":"758 VT_LARIAT_CHARGE 4","x1":-7.5,"x2":-7.5,"x3":-7.5,"hit":0,"fl":113,"st":32,"c":null},{"hits":[],"hurts":[{"rx":-6.95,"ry":1.3,"rw":0.7,"rh":0.4,"t":3},{"rx":-6.95,"ry":0.0,"rw":0.7,"rh":0.55,"t":3},{"rx":-6.95,"ry":0.55,"rw":0.7,"rh":0.75,"t":3}],"grabs":[{"rx":-6.84999943,"ry":0.0,"rw":0.5,"rh":1.35,"t":4}],"clips":[{"rx":-6.74999952,"ry":0.0,"rw":0.5,"rh":1.35,"t":0}],"s":"602 5HP 5","x1":-6.39999962,"x2":-6.39999962,"x3":-6.399999,"hit":0,"fl":26,"st":32,"c":null}],"p1":[],"p2":[],"i1":0,"i2":0},
{"f":1786,"p":[{"hits":[],"hurts":[{"rx":-8.2,"ry":1.55,"rw":1.3,"rh":0.35,"t":3},{"rx":-8.2,"ry":0.6,"rw":1.3,"rh":0.95,"t":3},{"rx":-8.2,"ry":0.0,"rw":1.3,"rh":0.6,"t":3},{"rx":-8.2,"ry":1.55,"rw":1.3,"rh":0.35,"t":3},{"rx":-8.2,"ry":0.4,"rw":1.3,"rh":1.15,"t":3},{"rx":-8.2,"ry":0.0,"rw":1.3,"rh":0.4,"t":3}],"grabs":[{"rx":-7.95,"ry":0.0,"rw":0.9,"rh":1.4,"t":4}],"clips":[{"rx":-7.95,"ry":0.0,"rw":0.900000036,"rh":1.4,"t":0}],"s":"758 VT_LARIAT_CHARGE 5","x1":-7.5,"x2":-7.5,"x3":-7.5,"hit":0,"fl":112,"st":32,"c":null},{"hits":[],"hurts":[{"rx":-6.95,"ry":1.3,"rw":0.7,"rh":0.4,"t":3},{"rx":-6.95,"ry":0.0,"rw":0.7,"rh":0.55,"t":3},{"rx":-6.95,"ry":0.55,"rw":0.7,"rh":0.75,"t":3}],"grabs":[{"rx":-6.84999943,"ry":0.0,"rw":0.5,"rh":1.35,"t":4}],"clips":[{"rx":-6.74999952,"ry":0.0,"rw":0.5,"rh":1.35,"t":0}],"s":"602 5HP 6","x1":-6.39999962,"x2":-6.39999962,"x3":-6.399999,"hit":0,"fl":25,"st":32,"c":null}],"p1":[],"p2":[],"i1":0,"i2":0},
{"f":1787,"p":[{"hits":[],"hurts":[{"rx":-8.2,"ry":1.55,"rw":1.3,"rh":0.35,"t":3},{"rx":-8.2,"ry":0.6,"rw":1.3,"rh":0.95,"t":3},{"rx":-8.2,"ry":0.0,"rw":1.3,"rh":0.6,"t":3},{"rx":-8.2,"ry":1.55,"rw":1.3,"rh":0.35,"t":3},{"rx":-8.2,"ry":0.4,"rw":1.3,"rh":1.15,"t":3},{"rx":-8.2,"ry":0.0,"rw":1.3,"rh":0.4,"t":3}],"grabs":[{"rx":-7.95,"ry":0.0,"rw":0.9,"rh":1.4,"t":4}],"clips":[{"rx":-7.95,"ry":0.0,"rw":0.900000036,"rh":1.4,"t":0}],"s":"758 VT_LARIAT_CHARGE 6","x1":-7.5,"x2":-7.5,"x3":-7.5,"hit":0,"fl":111,"st":32,"c":null},{"hits":[],"hurts":[{"rx":-6.95,"ry":1.3,"rw":0.7,"rh":0.4,"t":3},{"rx":-6.95,"ry":0.0,"rw":0.7,"rh":0.55,"t":3},{"rx":-6.95,"ry":0.55,"rw":0.7,"rh":0.75,"t":3}],"grabs":[{"rx":-6.84999943,"ry":0.0,"rw":0.5,"rh":1.35,"t":4}],"clips":[{"rx":-6.74999952,"ry":0.0,"rw":0.5,"rh":1.35,"t":0}],"s":"602 5HP 7","x1":-6.39999962,"x2":-6.39999962,"x3":-6.399999,"hit":0,"fl":24,"st":32,"c":null}],"p1":[],"p2":[],"i1":0,"i2":0},
{"f":1788,"p":[{"hits":[],"hurts":[{"rx":-8.2,"ry":1.55,"rw":1.3,"rh":0.35,"t":3},{"rx":-8.2,"ry":0.6,"rw":1.3,"rh":0.95,"t":3},{"rx":-8.2,"ry":0.0,"rw":1.3,"rh":0.6,"t":3},{"rx":-8.2,"ry":1.55,"rw":1.3,"rh":0.35,"t":3},{"rx":-8.2,"ry":0.4,"rw":1.3,"rh":1.15,"t":3},{"rx":-8.2,"ry":0.0,"rw":1.3,"rh":0.4,"t":3}],"grabs":[{"rx":-7.95,"ry":0.0,"rw":0.9,"rh":1.4,"t":4}],"clips":[{"rx":-7.95,"ry":0.0,"rw":0.900000036,"rh":1.4,"t":0}],"s":"758 VT_LARIAT_CHARGE 7","x1":-7.5,"x2":-7.5,"x3":-7.5,"hit":0,"fl":110,"st":32,"c":null},{"hits":[],"hurts":[{"rx":-7.04999971,"ry":1.3,"rw":0.7,"rh":0.4,"t":3},{"rx":-7.04999971,"ry":0.0,"rw":0.7,"rh":0.55,"t":3},{"rx":-7.04999971,"ry":0.55,"rw":0.7,"rh":0.75,"t":3}],"grabs":[{"rx":-6.95,"ry":0.0,"rw":0.5,"rh":1.35,"t":4}],"clips":[{"rx":-6.95,"ry":0.0,"rw":0.5,"rh":1.35,"t":0}],"s":"602 5HP 8","x1":-6.39999962,"x2":-6.39999962,"x3":-6.399999,"hit":0,"fl":23,"st":32,"c":null}],"p1":[],"p2":[],"i1":0,"i2":0},
{"f":1789,"p":[{"hits":[],"hurts":[{"rx":-8.2,"ry":1.55,"rw":1.3,"rh":0.35,"t":3},{"rx":-8.2,"ry":0.6,"rw":1.3,"rh":0.95,"t":3},{"rx":-8.2,"ry":0.0,"rw":1.3,"rh":0.6,"t":3},{"rx":-8.2,"ry":1.55,"rw":1.3,"rh":0.35,"t":3},{"rx":-8.2,"ry":0.4,"rw":1.3,"rh":1.15,"t":3},{"rx":-8.2,"ry":0.0,"rw":1.3,"rh":0.4,"t":3}],"grabs":[{"rx":-7.95,"ry":0.0,"rw":0.9,"rh":1.4,"t":4}],"clips":[{"rx":-7.95,"ry":0.0,"rw":0.900000036,"rh":1.4,"t":0}],"s":"758 VT_LARIAT_CHARGE 8","x1":-7.5,"x2":-7.5,"x3":-7.5,"hit":0,"fl":109,"st":32,"c":null},{"hits":[{"rx":-7.64999962,"ry":1.2,"rw":0.65,"rh":0.4,"t":0,"l":0,"c":1,"e":3,"s":50,"i":8}],"hurts":[{"rx":-7.04999971,"ry":1.3,"rw":0.7,"rh":0.4,"t":3},{"rx":-7.04999971,"ry":0.0,"rw":0.7,"rh":0.55,"t":3},{"rx":-7.04999971,"ry":0.55,"rw":0.7,"rh":0.75,"t":3},{"rx":-7.49999952,"ry":1.1,"rw":0.45,"rh":0.6,"t":3},{"rx":-7.29999971,"ry":0.0,"rw":0.25,"rh":1.1,"t":3}],"grabs":[{"rx":-6.95,"ry":0.0,"rw":0.5,"rh":1.35,"t":4}],"clips":[{"rx":-6.95,"ry":0.0,"rw":0.5,"rh":1.35,"t":0}],"s":"602 5HP 9","x1":-6.39999962,"x2":-6.39999962,"x3":-6.399999,"hit":0,"fl":22,"st":0,"c":null}],"p1":[],"p2":[],"i1":0,"i2":0},
{"f":1790,"p":[{"hits":[],"hurts":[],"grabs":[],"clips":[{"rx":-7.65,"ry":0.0,"rw":0.6,"rh":1.4,"t":0}],"s":"744 VT_broking_HIGH_1 1","x1":-7.5,"x2":-7.5,"x3":-7.5,"hit":0,"fl":108,"st":0,"c":null},{"hits":[],"hurts":[{"rx":-7.04999971,"ry":1.3,"rw":0.7,"rh":0.4,"t":3},{"rx":-7.04999971,"ry":0.0,"rw":0.7,"rh":0.55,"t":3},{"rx":-7.04999971,"ry":0.55,"rw":0.7,"rh":0.75,"t":3},{"rx":-7.49999952,"ry":1.1,"rw":0.45,"rh":0.6,"t":3},{"rx":-7.29999971,"ry":0.0,"rw":0.25,"rh":1.1,"t":3}],"grabs":[{"rx":-6.95,"ry":0.0,"rw":0.5,"rh":1.35,"t":4}],"clips":[{"rx":-6.95,"ry":0.0,"rw":0.5,"rh":1.35,"t":0}],"s":"602 5HP 9","x1":-6.39999962,"x2":-6.39999962,"x3":-6.374999,"hit":0,"fl":39,"st":0,"c":null}],"p1":[],"p2":[],"i1":0,"i2":0},
{"f":1791,"p":[{"hits":[],"hurts":[{"rx":-7.8,"ry":0.6,"rw":0.9,"rh":0.95,"t":1},{"rx":-7.8,"ry":0.0,"rw":0.9,"rh":0.6,"t":1}],"grabs":[{"rx":-7.65,"ry":0.0,"rw":0.6,"rh":1.4,"t":4}],"clips":[{"rx":-7.65,"ry":0.0,"rw":0.6,"rh":1.4,"t":0}],"s":"744 VT_broking_HIGH_1 2","x1":-7.5,"x2":-7.5,"x3":-7.5,"hit":0,"fl":22,"st":0,"c":null},{"hits":[],"hurts":[{"rx":-7.04999971,"ry":1.3,"rw":0.7,"rh":0.4,"t":3},{"rx":-7.04999971,"ry":0.0,"rw":0.7,"rh":0.55,"t":3},{"rx":-7.04999971,"ry":0.55,"rw":0.7,"rh":0.75,"t":3},{"rx":-7.49999952,"ry":1.1,"rw":0.45,"rh":0.6,"t":3},{"rx":-7.29999971,"ry":0.0,"rw":0.25,"rh":1.1,"t":3}],"grabs":[{"rx":-6.95,"ry":0.0,"rw":0.5,"rh":1.35,"t":4}],"clips":[{"rx":-6.95,"ry":0.0,"rw":0.5,"rh":1.35,"t":0}],"s":"602 5HP 9","x1":-6.39999962,"x2":-6.39999962,"x3":-6.42478561,"hit":0,"fl":38,"st":0,"c":null}],"p1":[],"p2":[],"i1":0,"i2":0},
{"f":1792,"p":[{"hits":[],"hurts":[{"rx":-7.8,"ry":0.6,"rw":0.9,"rh":0.95,"t":1},{"rx":-7.8,"ry":0.0,"rw":0.9,"rh":0.6,"t":1}],"grabs":[{"rx":-7.65,"ry":0.0,"rw":0.6,"rh":1.4,"t":4}],"clips":[{"rx":-7.65,"ry":0.0,"rw":0.6,"rh":1.4,"t":0}],"s":"744 VT_broking_HIGH_1 3","x1":-7.5,"x2":-7.5,"x3":-7.5,"hit":0,"fl":21,"st":0,"c":null},{"hits":[],"hurts":[{"rx":-7.04999971,"ry":1.3,"rw":0.7,"rh":0.4,"t":3},{"rx":-7.04999971,"ry":0.0,"rw":0.7,"rh":0.55,"t":3},{"rx":-7.04999971,"ry":0.55,"rw":0.7,"rh":0.75,"t":3},{"rx":-7.49999952,"ry":1.1,"rw":0.45,"rh":0.6,"t":3},{"rx":-7.29999971,"ry":0.0,"rw":0.25,"rh":1.1,"t":3}],"grabs":[{"rx":-6.95,"ry":0.0,"rw":0.5,"rh":1.35,"t":4}],"clips":[{"rx":-6.95,"ry":0.0,"rw":0.5,"rh":1.35,"t":0}],"s":"602 5HP 9","x1":-6.39999962,"x2":-6.39999962,"x3":-6.375851,"hit":0,"fl":37,"st":0,"c":null}],"p1":[],"p2":[],"i1":0,"i2":0},
{"f":1793,"p":[{"hits":[],"hurts":[{"rx":-7.8,"ry":0.6,"rw":0.9,"rh":0.95,"t":1},{"rx":-7.8,"ry":0.0,"rw":0.9,"rh":0.6,"t":1}],"grabs":[{"rx":-7.65,"ry":0.0,"rw":0.6,"rh":1.4,"t":4}],"clips":[{"rx":-7.65,"ry":0.0,"rw":0.6,"rh":1.4,"t":0}],"s":"744 VT_broking_HIGH_1 4","x1":-7.5,"x2":-7.5,"x3":-7.5,"hit":0,"fl":20,"st":0,"c":null},{"hits":[],"hurts":[{"rx":-7.04999971,"ry":1.3,"rw":0.7,"rh":0.4,"t":3},{"rx":-7.04999971,"ry":0.0,"rw":0.7,"rh":0.55,"t":3},{"rx":-7.04999971,"ry":0.55,"rw":0.7,"rh":0.75,"t":3},{"rx":-7.49999952,"ry":1.1,"rw":0.45,"rh":0.6,"t":3},{"rx":-7.29999971,"ry":0.0,"rw":0.25,"rh":1.1,"t":3}],"grabs":[{"rx":-6.95,"ry":0.0,"rw":0.5,"rh":1.35,"t":4}],"clips":[{"rx":-6.95,"ry":0.0,"rw":0.5,"rh":1.35,"t":0}],"s":"602 5HP 9","x1":-6.39999962,"x2":-6.39999962,"x3":-6.42309666,"hit":0,"fl":36,"st":0,"c":null}],"p1":[],"p2":[],"i1":0,"i2":0},
{"f":1794,"p":[{"hits":[],"hurts":[{"rx":-7.8,"ry":0.6,"rw":0.9,"rh":0.95,"t":1},{"rx":-7.8,"ry":0.0,"rw":0.9,"rh":0.6,"t":1}],"grabs":[{"rx":-7.65,"ry":0.0,"rw":0.6,"rh":1.4,"t":4}],"clips":[{"rx":-7.65,"ry":0.0,"rw":0.6,"rh":1.4,"t":0}],"s":"744 VT_broking_HIGH_1 5","x1":-7.5,"x2":-7.5,"x3":-7.5,"hit":0,"fl":19,"st":0,"c":null},{"hits":[],"hurts":[{"rx":-7.04999971,"ry":1.3,"rw":0.7,"rh":0.4,"t":3},{"rx":-7.04999971,"ry":0.0,"rw":0.7,"rh":0.55,"t":3},{"rx":-7.04999971,"ry":0.55,"rw":0.7,"rh":0.75,"t":3},{"rx":-7.49999952,"ry":1.1,"rw":0.45,"rh":0.6,"t":3},{"rx":-7.29999971,"ry":0.0,"rw":0.25,"rh":1.1,"t":3}],"grabs":[{"rx":-6.95,"ry":0.0,"rw":0.5,"rh":1.35,"t":4}],"clips":[{"rx":-6.95,"ry":0.0,"rw":0.5,"rh":1.35,"t":0}],"s":"602 5HP 9","x1":-6.39999962,"x2":-6.39999962,"x3":-6.378349,"hit":0,"fl":35,"st":0,"c":null}],"p1":[],"p2":[],"i1":0,"i2":0},
{"f":1795,"p":[{"hits":[],"hurts":[{"rx":-7.8,"ry":0.6,"rw":0.9,"rh":0.95,"t":1},{"rx":-7.8,"ry":0.0,"rw":0.9,"rh":0.6,"t":1}],"grabs":[{"rx":-7.65,"ry":0.0,"rw":0.6,"rh":1.4,"t":4}],"clips":[{"rx":-7.65,"ry":0.0,"rw":0.6,"rh":1.4,"t":0}],"s":"744 VT_broking_HIGH_1 6","x1":-7.5,"x2":-7.5,"x3":-7.5,"hit":0,"fl":18,"st":0,"c":null},{"hits":[],"hurts":[{"rx":-7.04999971,"ry":1.3,"rw":0.7,"rh":0.4,"t":3},{"rx":-7.04999971,"ry":0.0,"rw":0.7,"rh":0.55,"t":3},{"rx":-7.04999971,"ry":0.55,"rw":0.7,"rh":0.75,"t":3},{"rx":-7.49999952,"ry":1.1,"rw":0.45,"rh":0.6,"t":3},{"rx":-7.29999971,"ry":0.0,"rw":0.25,"rh":1.1,"t":3}],"grabs":[{"rx":-6.95,"ry":0.0,"rw":0.5,"rh":1.35,"t":4}],"clips":[{"rx":-6.95,"ry":0.0,"rw":0.5,"rh":1.35,"t":0}],"s":"602 5HP 9","x1":-6.39999962,"x2":-6.39999962,"x3":-6.419833,"hit":0,"fl":34,"st":0,"c":null}],"p1":[],"p2":[],"i1":0,"i2":0},
{"f":1796,"p":[{"hits":[],"hurts":[{"rx":-7.8,"ry":0.6,"rw":0.9,"rh":0.95,"t":1},{"rx":-7.8,"ry":0.0,"rw":0.9,"rh":0.6,"t":1}],"grabs":[{"rx":-7.65,"ry":0.0,"rw":0.6,"rh":1.4,"t":4}],"clips":[{"rx":-7.65,"ry":0.0,"rw":0.6,"rh":1.4,"t":0}],"s":"744 VT_broking_HIGH_1 7","x1":-7.5,"x2":-7.5,"x3":-7.5,"hit":0,"fl":17,"st":0,"c":null},{"hits":[],"hurts":[{"rx":-7.04999971,"ry":1.3,"rw":0.7,"rh":0.4,"t":3},{"rx":-7.04999971,"ry":0.0,"rw":0.7,"rh":0.55,"t":3},{"rx":-7.04999971,"ry":0.55,"rw":0.7,"rh":0.75,"t":3},{"rx":-7.49999952,"ry":1.1,"rw":0.45,"rh":0.6,"t":3},{"rx":-7.29999971,"ry":0.0,"rw":0.25,"rh":1.1,"t":3}],"grabs":[{"rx":-6.95,"ry":0.0,"rw":0.5,"rh":1.35,"t":4}],"clips":[{"rx":-6.95,"ry":0.0,"rw":0.5,"rh":1.35,"t":0}],"s":"602 5HP 9","x1":-6.39999962,"x2":-6.39999962,"x3":-6.382322,"hit":0,"fl":33,"st":0,"c":null}],"p1":[],"p2":[],"i1":0,"i2":0},
{"f":1797,"p":[{"hits":[],"hurts":[{"rx":-7.8,"ry":0.6,"rw":0.9,"rh":0.95,"t":1},{"rx":-7.8,"ry":0.0,"rw":0.9,"rh":0.6,"t":1}],"grabs":[{"rx":-7.65,"ry":0.0,"rw":0.6,"rh":1.4,"t":4}],"clips":[{"rx":-7.65,"ry":0.0,"rw":0.6,"rh":1.4,"t":0}],"s":"744 VT_broking_HIGH_1 8","x1":-7.5,"x2":-7.5,"x3":-7.5,"hit":0,"fl":16,"st":0,"c":null},{"hits":[],"hurts":[{"rx":-7.04999971,"ry":1.3,"rw":0.7,"rh":0.4,"t":3},{"rx":-7.04999971,"ry":0.0,"rw":0.7,"rh":0.55,"t":3},{"rx":-7.04999971,"ry":0.55,"rw":0.7,"rh":0.75,"t":3},{"rx":-7.49999952,"ry":1.1,"rw":0.45,"rh":0.6,"t":3},{"rx":-7.29999971,"ry":0.0,"rw":0.25,"rh":1.1,"t":3}],"grabs":[{"rx":-6.95,"ry":0.0,"rw":0.5,"rh":1.35,"t":4}],"clips":[{"rx":-6.95,"ry":0.0,"rw":0.5,"rh":1.35,"t":0}],"s":"602 5HP 9","x1":-6.39999962,"x2":-6.39999962,"x3":-6.415219,"hit":0,"fl":32,"st":0,"c":null}],"p1":[],"p2":[],"i1":0,"i2":0},
{"f":1798,"p":[{"hits":[],"hurts":[{"rx":-7.8,"ry":0.6,"rw":0.9,"rh":0.95,"t":1},{"rx":-7.8,"ry":0.0,"rw":0.9,"rh":0.6,"t":1}],"grabs":[{"rx":-7.65,"ry":0.0,"rw":0.6,"rh":1.4,"t":4}],"clips":[{"rx":-7.65,"ry":0.0,"rw":0.6,"rh":1.4,"t":0}],"s":"744 VT_broking_HIGH_1 9","x1":-7.5,"x2":-7.5,"x3":-7.5,"hit":0,"fl":15,"st":0,"c":null},{"hits":[],"hurts":[{"rx":-7.04999971,"ry":1.3,"rw":0.7,"rh":0.4,"t":3},{"rx":-7.04999971,"ry":0.0,"rw":0.7,"rh":0.55,"t":3},{"rx":-7.04999971,"ry":0.55,"rw":0.7,"rh":0.75,"t":3},{"rx":-7.49999952,"ry":1.1,"rw":0.45,"rh":0.6,"t":3},{"rx":-7.29999971,"ry":0.0,"rw":0.25,"rh":1.1,"t":3}],"grabs":[{"rx":-6.95,"ry":0.0,"rw":0.5,"rh":1.35,"t":4}],"clips":[{"rx":-6.95,"ry":0.0,"rw":0.5,"rh":1.35,"t":0}],"s":"602 5HP 9","x1":-6.39999962,"x2":-6.39999962,"x3":-6.38749933,"hit":0,"fl":31,"st":0,"c":null}],"p1":[],"p2":[],"i1":0,"i2":0},
{"f":1799,"p":[{"hits":[],"hurts":[{"rx":-7.8,"ry":0.6,"rw":0.9,"rh":0.95,"t":1},{"rx":-7.8,"ry":0.0,"rw":0.9,"rh":0.6,"t":1}],"grabs":[{"rx":-7.65,"ry":0.0,"rw":0.6,"rh":1.4,"t":4}],"clips":[{"rx":-7.65,"ry":0.0,"rw":0.6,"rh":1.4,"t":0}],"s":"744 VT_broking_HIGH_1 10","x1":-7.5,"x2":-7.5,"x3":-7.5,"hit":0,"fl":14,"st":0,"c":null},{"hits":[],"hurts":[{"rx":-7.04999971,"ry":1.3,"rw":0.7,"rh":0.4,"t":3},{"rx":-7.04999971,"ry":0.0,"rw":0.7,"rh":0.55,"t":3},{"rx":-7.04999971,"ry":0.55,"rw":0.7,"rh":0.75,"t":3},{"rx":-7.49999952,"ry":1.1,"rw":0.45,"rh":0.6,"t":3},{"rx":-7.29999971,"ry":0.0,"rw":0.25,"rh":1.1,"t":3}],"grabs":[{"rx":-6.95,"ry":0.0,"rw":0.5,"rh":1.35,"t":4}],"clips":[{"rx":-6.95,"ry":0.0,"rw":0.5,"rh":1.35,"t":0}],"s":"602 5HP 9","x1":-6.39999962,"x2":-6.39999962,"x3":-6.4095664,"hit":0,"fl":30,"st":0,"c":null}],"p1":[],"p2":[],"i1":0,"i2":0},
{"f":1800,"p":[{"hits":[],"hurts":[{"rx":-7.8,"ry":0.6,"rw":0.9,"rh":0.95,"t":1},{"rx":-7.8,"ry":0.0,"rw":0.9,"rh":0.6,"t":1}],"grabs":[{"rx":-7.65,"ry":0.0,"rw":0.6,"rh":1.4,"t":4}],"clips":[{"rx":-7.65,"ry":0.0,"rw":0.6,"rh":1.4,"t":0}],"s":"744 VT_broking_HIGH_1 11","x1":-7.5,"x2":-7.5,"x3":-7.5,"hit":0,"fl":13,"st":0,"c":null},{"hits":[],"hurts":[{"rx":-7.04999971,"ry":1.3,"rw":0.7,"rh":0.4,"t":3},{"rx":-7.04999971,"ry":0.0,"rw":0.7,"rh":0.55,"t":3},{"rx":-7.04999971,"ry":0.55,"rw":0.7,"rh":0.75,"t":3},{"rx":-7.49999952,"ry":1.1,"rw":0.45,"rh":0.6,"t":3},{"rx":-7.29999971,"ry":0.0,"rw":0.25,"rh":1.1,"t":3}],"grabs":[{"rx":-6.95,"ry":0.0,"rw":0.5,"rh":1.35,"t":4}],"clips":[{"rx":-6.95,"ry":0.0,"rw":0.5,"rh":1.35,"t":0}],"s":"602 5HP 9","x1":-6.39999962,"x2":-6.39999962,"x3":-6.393529,"hit":0,"fl":29,"st":0,"c":null}],"p1":[],"p2":[],"i1":0,"i2":0},
{"f":1801,"p":[{"hits":[],"hurts":[{"rx":-7.8,"ry":0.6,"rw":0.9,"rh":0.95,"t":1},{"rx":-7.8,"ry":0.0,"rw":0.9,"rh":0.6,"t":1}],"grabs":[{"rx":-7.65,"ry":0.0,"rw":0.6,"rh":1.4,"t":4}],"clips":[{"rx":-7.65,"ry":0.0,"rw":0.6,"rh":1.4,"t":0}],"s":"744 VT_broking_HIGH_1 12","x1":-7.5,"x2":-7.5,"x3":-7.5,"hit":0,"fl":12,"st":0,"c":null},{"hits":[],"hurts":[{"rx":-7.04999971,"ry":1.3,"rw":0.7,"rh":0.4,"t":3},{"rx":-7.04999971,"ry":0.0,"rw":0.7,"rh":0.55,"t":3},{"rx":-7.04999971,"ry":0.55,"rw":0.7,"rh":0.75,"t":3},{"rx":-7.49999952,"ry":1.1,"rw":0.45,"rh":0.6,"t":3},{"rx":-7.29999971,"ry":0.0,"rw":0.25,"rh":1.1,"t":3}],"grabs":[{"rx":-6.95,"ry":0.0,"rw":0.5,"rh":1.35,"t":4}],"clips":[{"rx":-6.95,"ry":0.0,"rw":0.5,"rh":1.35,"t":0}],"s":"602 5HP 9","x1":-6.39999962,"x2":-6.39999962,"x3":-6.40326262,"hit":0,"fl":28,"st":0,"c":null}],"p1":[],"p2":[],"i1":0,"i2":0},
{"f":1802,"p":[{"hits":[],"hurts":[{"rx":-7.8,"ry":0.6,"rw":0.9,"rh":0.95,"t":1},{"rx":-7.8,"ry":0.0,"rw":0.9,"rh":0.6,"t":1}],"grabs":[{"rx":-7.65,"ry":0.0,"rw":0.6,"rh":1.4,"t":4}],"clips":[{"rx":-7.65,"ry":0.0,"rw":0.6,"rh":1.4,"t":0}],"s":"744 VT_broking_HIGH_1 13","x1":-7.5,"x2":-7.5,"x3":-7.5,"hit":0,"fl":11,"st":0,"c":null},{"hits":[],"hurts":[{"rx":-7.04999971,"ry":1.3,"rw":0.7,"rh":0.4,"t":3},{"rx":-7.04999971,"ry":0.0,"rw":0.7,"rh":0.55,"t":3},{"rx":-7.04999971,"ry":0.55,"rw":0.7,"rh":0.75,"t":3},{"rx":-7.49999952,"ry":1.1,"rw":0.45,"rh":0.6,"t":3},{"rx":-7.29999971,"ry":0.0,"rw":0.25,"rh":1.1,"t":3}],"grabs":[{"rx":-6.95,"ry":0.0,"rw":0.5,"rh":1.35,"t":4}],"clips":[{"rx":-6.95,"ry":0.0,"rw":0.5,"rh":1.35,"t":0}],"s":"602 5HP 9","x1":-6.39999962,"x2":-6.39999962,"x3":-6.399999,"hit":0,"fl":27,"st":0,"c":null}],"p1":[],"p2":[],"i1":0,"i2":0},
{"f":1803,"p":[{"hits":[],"hurts":[{"rx":-7.8,"ry":0.6,"rw":0.9,"rh":0.95,"t":1},{"rx":-7.8,"ry":0.0,"rw":0.9,"rh":0.6,"t":1}],"grabs":[{"rx":-7.65,"ry":0.0,"rw":0.6,"rh":1.4,"t":4}],"clips":[{"rx":-7.65,"ry":0.0,"rw":0.6,"rh":1.4,"t":0}],"s":"744 VT_broking_HIGH_1 14","x1":-7.5,"x2":-7.5,"x3":-7.5,"hit":0,"fl":10,"st":0,"c":null},{"hits":[],"hurts":[{"rx":-7.04999971,"ry":1.3,"rw":0.7,"rh":0.4,"t":3},{"rx":-7.04999971,"ry":0.0,"rw":0.7,"rh":0.55,"t":3},{"rx":-7.04999971,"ry":0.55,"rw":0.7,"rh":0.75,"t":3},{"rx":-7.49999952,"ry":1.1,"rw":0.45,"rh":0.6,"t":3},{"rx":-7.29999971,"ry":0.0,"rw":0.25,"rh":1.1,"t":3}],"grabs":[{"rx":-6.95,"ry":0.0,"rw":0.5,"rh":1.35,"t":4}],"clips":[{"rx":-6.95,"ry":0.0,"rw":0.5,"rh":1.35,"t":0}],"s":"602 5HP 9","x1":-6.39999962,"x2":-6.39999962,"x3":-6.399999,"hit":0,"fl":26,"st":0,"c":null}],"p1":[],"p2":[],"i1":0,"i2":0},
{"f":1804,"p":[{"hits":[],"hurts":[{"rx":-7.8,"ry":0.6,"rw":0.9,"rh":0.95,"t":1},{"rx":-7.8,"ry":0.0,"rw":0.9,"rh":0.6,"t":1}],"grabs":[{"rx":-7.65,"ry":0.0,"rw":0.6,"rh":1.4,"t":4}],"clips":[{"rx":-7.65,"ry":0.0,"rw":0.6,"rh":1.4,"t":0}],"s":"744 VT_broking_HIGH_1 15","x1":-7.5,"x2":-7.5,"x3":-7.5,"hit":0,"fl":9,"st":0,"c":null},{"hits":[],"hurts":[{"rx":-7.04999971,"ry":1.3,"rw":0.7,"rh":0.4,"t":3},{"rx":-7.04999971,"ry":0.0,"rw":0.7,"rh":0.55,"t":3},{"rx":-7.04999971,"ry":0.55,"rw":0.7,"rh":0.75,"t":3},{"rx":-7.49999952,"ry":1.1,"rw":0.45,"rh":0.6,"t":3},{"rx":-7.29999971,"ry":0.0,"rw":0.25,"rh":1.1,"t":3}],"grabs":[{"rx":-6.95,"ry":0.0,"rw":0.5,"rh":1.35,"t":4}],"clips":[{"rx":-6.95,"ry":0.0,"rw":0.5,"rh":1.35,"t":0}],"s":"602 5HP 9","x1":-6.39999962,"x2":-6.39999962,"x3":-6.399999,"hit":0,"fl":25,"st":0,"c":null}],"p1":[],"p2":[],"i1":0,"i2":0},
{"f":1805,"p":[{"hits":[],"hurts":[{"rx":-7.8,"ry":0.6,"rw":0.9,"rh":0.95,"t":1},{"rx":-7.8,"ry":0.0,"rw":0.9,"rh":0.6,"t":1}],"grabs":[{"rx":-7.65,"ry":0.0,"rw":0.6,"rh":1.4,"t":4}],"clips":[{"rx":-7.65,"ry":0.0,"rw":0.6,"rh":1.4,"t":0}],"s":"744 VT_broking_HIGH_1 16","x1":-7.5,"x2":-7.5,"x3":-7.5,"hit":0,"fl":8,"st":0,"c":null},{"hits":[],"hurts":[{"rx":-7.04999971,"ry":1.3,"rw":0.7,"rh":0.4,"t":3},{"rx":-7.04999971,"ry":0.0,"rw":0.7,"rh":0.55,"t":3},{"rx":-7.04999971,"ry":0.55,"rw":0.7,"rh":0.75,"t":3},{"rx":-7.49999952,"ry":1.1,"rw":0.45,"rh":0.6,"t":3},{"rx":-7.29999971,"ry":0.0,"rw":0.25,"rh":1.1,"t":3}],"grabs":[{"rx":-6.95,"ry":0.0,"rw":0.5,"rh":1.35,"t":4}],"clips":[{"rx":-6.95,"ry":0.0,"rw":0.5,"rh":1.35,"t":0}],"s":"602 5HP 9","x1":-6.39999962,"x2":-6.39999962,"x3":-6.399999,"hit":0,"fl":24,"st":0,"c":null}],"p1":[],"p2":[],"i1":0,"i2":0},
{"f":1806,"p":[{"hits":[],"hurts":[{"rx":-7.8,"ry":1.45,"rw":0.9,"rh":0.4,"t":3},{"rx":-7.8,"ry":0.7,"rw":0.9,"rh":0.75,"t":3},{"rx":-7.8,"ry":0.0,"rw":0.9,"rh":0.7,"t":3}],"grabs":[{"rx":-7.65,"ry":0.0,"rw":0.6,"rh":1.4,"t":4}],"clips":[{"rx":-7.65,"ry":0.0,"rw":0.6,"rh":1.4,"t":0}],"s":"744 VT_broking_HIGH_1 17","x1":-7.5,"x2":-7.5,"x3":-7.5,"hit":0,"fl":7,"st":0,"c":null},{"hits":[],"hurts":[{"rx":-7.04999971,"ry":1.3,"rw":0.7,"rh":0.4,"t":3},{"rx":-7.04999971,"ry":0.0,"rw":0.7,"rh":0.55,"t":3},{"rx":-7.04999971,"ry":0.55,"rw":0.7,"rh":0.75,"t":3},{"rx":-7.49999952,"ry":1.1,"rw":0.45,"rh":0.6,"t":3},{"rx":-7.29999971,"ry":0.0,"rw":0.25,"rh":1.1,"t":3}],"grabs":[{"rx":-6.95,"ry":0.0,"rw":0.5,"rh":1.35,"t":4}],"clips":[{"rx":-6.95,"ry":0.0,"rw":0.5,"rh":1.35,"t":0}],"s":"602 5HP 9","x1":-6.39999962,"x2":-6.39999962,"x3":-6.399999,"hit":0,"fl":23,"st":0,"c":null}],"p1":[],"p2":[],"i1":0,"i2":0},
{"f":1807,"p":[{"hits":[],"hurts":[{"rx":-7.8,"ry":1.45,"rw":0.9,"rh":0.4,"t":3},{"rx":-7.8,"ry":0.7,"rw":0.9,"rh":0.75,"t":3},{"rx":-7.8,"ry":0.0,"rw":0.9,"rh":0.7,"t":3}],"grabs":[{"rx":-7.65,"ry":0.0,"rw":0.6,"rh":1.4,"t":4}],"clips":[{"rx":-7.65,"ry":0.0,"rw":0.6,"rh":1.4,"t":0}],"s":"744 VT_broking_HIGH_1 18","x1":-7.5,"x2":-7.5,"x3":-7.5,"hit":0,"fl":6,"st":0,"c":null},{"hits":[],"hurts":[{"rx":-7.04999971,"ry":1.3,"rw":0.7,"rh":0.4,"t":3},{"rx":-7.04999971,"ry":0.0,"rw":0.7,"rh":0.55,"t":3},{"rx":-7.04999971,"ry":0.55,"rw":0.7,"rh":0.75,"t":3},{"rx":-7.49999952,"ry":1.1,"rw":0.45,"rh":0.6,"t":3},{"rx":-7.29999971,"ry":0.0,"rw":0.25,"rh":1.1,"t":3}],"grabs":[{"rx":-6.95,"ry":0.0,"rw":0.5,"rh":1.35,"t":4}],"clips":[{"rx":-6.95,"ry":0.0,"rw":0.5,"rh":1.35,"t":0}],"s":"602 5HP 9","x1":-6.39999962,"x2":-6.39999962,"x3":-6.399999,"hit":0,"fl":22,"st":0,"c":null}],"p1":[],"p2":[],"i1":0,"i2":0},
{"f":1808,"p":[{"hits":[],"hurts":[{"rx":-7.8,"ry":1.45,"rw":0.9,"rh":0.4,"t":3},{"rx":-7.8,"ry":0.7,"rw":0.9,"rh":0.75,"t":3},{"rx":-7.8,"ry":0.0,"rw":0.9,"rh":0.7,"t":3}],"grabs":[{"rx":-7.65,"ry":0.0,"rw":0.6,"rh":1.4,"t":4}],"clips":[{"rx":-7.65,"ry":0.0,"rw":0.6,"rh":1.4,"t":0}],"s":"744 VT_broking_HIGH_1 19","x1":-7.5,"x2":-7.5,"x3":-7.5,"hit":0,"fl":5,"st":0,"c":null},{"hits":[],"hurts":[{"rx":-7.04999971,"ry":1.3,"rw":0.7,"rh":0.4,"t":3},{"rx":-7.04999971,"ry":0.0,"rw":0.7,"rh":0.55,"t":3},{"rx":-7.04999971,"ry":0.55,"rw":0.7,"rh":0.75,"t":3},{"rx":-7.49999952,"ry":1.1,"rw":0.45,"rh":0.6,"t":3},{"rx":-7.29999971,"ry":0.0,"rw":0.25,"rh":1.1,"t":3}],"grabs":[{"rx":-6.95,"ry":0.0,"rw":0.5,"rh":1.35,"t":4}],"clips":[{"rx":-6.95,"ry":0.0,"rw":0.5,"rh":1.35,"t":0}],"s":"602 5HP 10","x1":-6.39999962,"x2":-6.39999962,"x3":-6.399999,"hit":0,"fl":21,"st":0,"c":null}],"p1":[],"p2":[],"i1":0,"i2":0},
{"f":1809,"p":[{"hits":[],"hurts":[{"rx":-7.8,"ry":1.45,"rw":0.9,"rh":0.4,"t":3},{"rx":-7.8,"ry":0.7,"rw":0.9,"rh":0.75,"t":3},{"rx":-7.8,"ry":0.0,"rw":0.9,"rh":0.7,"t":3}],"grabs":[{"rx":-7.65,"ry":0.0,"rw":0.6,"rh":1.4,"t":4}],"clips":[{"rx":-7.65,"ry":0.0,"rw":0.6,"rh":1.4,"t":0}],"s":"744 VT_broking_HIGH_1 20","x1":-7.5,"x2":-7.5,"x3":-7.5,"hit":0,"fl":4,"st":0,"c":null},{"hits":[],"hurts":[{"rx":-7.04999971,"ry":1.3,"rw":0.7,"rh":0.4,"t":3},{"rx":-7.04999971,"ry":0.0,"rw":0.7,"rh":0.55,"t":3},{"rx":-7.04999971,"ry":0.55,"rw":0.7,"rh":0.75,"t":3},{"rx":-7.49999952,"ry":1.1,"rw":0.45,"rh":0.6,"t":3},{"rx":-7.29999971,"ry":0.0,"rw":0.25,"rh":1.1,"t":3}],"grabs":[{"rx":-6.95,"ry":0.0,"rw":0.5,"rh":1.35,"t":4}],"clips":[{"rx":-6.95,"ry":0.0,"rw":0.5,"rh":1.35,"t":0}],"s":"602 5HP 11","x1":-6.39999962,"x2":-6.39999962,"x3":-6.399999,"hit":0,"fl":20,"st":0,"c":null}],"p1":[],"p2":[],"i1":0,"i2":0},
{"f":1810,"p":[{"hits":[],"hurts":[{"rx":-7.8,"ry":1.45,"rw":0.9,"rh":0.4,"t":3},{"rx":-7.8,"ry":0.7,"rw":0.9,"rh":0.75,"t":3},{"rx":-7.8,"ry":0.0,"rw":0.9,"rh":0.7,"t":3}],"grabs":[{"rx":-7.65,"ry":0.0,"rw":0.6,"rh":1.4,"t":4}],"clips":[{"rx":-7.65,"ry":0.0,"rw":0.6,"rh":1.4,"t":0}],"s":"744 VT_broking_HIGH_1 21","x1":-7.5,"x2":-7.5,"x3":-7.5,"hit":0,"fl":3,"st":0,"c":null},{"hits":[],"hurts":[{"rx":-7.04999971,"ry":1.3,"rw":0.7,"rh":0.4,"t":3},{"rx":-7.04999971,"ry":0.0,"rw":0.7,"rh":0.55,"t":3},{"rx":-7.04999971,"ry":0.55,"rw":0.7,"rh":0.75,"t":3},{"rx":-7.49999952,"ry":1.1,"rw":0.45,"rh":0.6,"t":3},{"rx":-7.29999971,"ry":0.0,"rw":0.25,"rh":1.1,"t":3}],"grabs":[{"rx":-6.95,"ry":0.0,"rw":0.5,"rh":1.35,"t":4}],"clips":[{"rx":-6.95,"ry":0.0,"rw":0.5,"rh":1.35,"t":0}],"s":"602 5HP 12","x1":-6.39999962,"x2":-6.39999962,"x3":-6.399999,"hit":0,"fl":19,"st":0,"c":null}],"p1":[],"p2":[],"i1":0,"i2":0},
{"f":1811,"p":[{"hits":[],"hurts":[{"rx":-7.8,"ry":1.45,"rw":0.9,"rh":0.4,"t":3},{"rx":-7.8,"ry":0.7,"rw":0.9,"rh":0.75,"t":3},{"rx":-7.8,"ry":0.0,"rw":0.9,"rh":0.7,"t":3}],"grabs":[{"rx":-7.65,"ry":0.0,"rw":0.6,"rh":1.4,"t":4}],"clips":[{"rx":-7.65,"ry":0.0,"rw":0.6,"rh":1.4,"t":0}],"s":"744 VT_broking_HIGH_1 22","x1":-7.5,"x2":-7.5,"x3":-7.5,"hit":0,"fl":2,"st":0,"c":null},{"hits":[],"hurts":[{"rx":-7.04999971,"ry":1.3,"rw":0.7,"rh":0.4,"t":3},{"rx":-7.04999971,"ry":0.0,"rw":0.7,"rh":0.55,"t":3},{"rx":-7.04999971,"ry":0.55,"rw":0.7,"rh":0.75,"t":3},{"rx":-7.49999952,"ry":1.1,"rw":0.45,"rh":0.6,"t":3},{"rx":-7.29999971,"ry":0.0,"rw":0.25,"rh":1.1,"t":3}],"grabs":[{"rx":-6.95,"ry":0.0,"rw":0.5,"rh":1.35,"t":4}],"clips":[{"rx":-6.95,"ry":0.0,"rw":0.5,"rh":1.35,"t":0}],"s":"602 5HP 13","x1":-6.39999962,"x2":-6.39999962,"x3":-6.399999,"hit":0,"fl":18,"st":0,"c":null}],"p1":[],"p2":[],"i1":0,"i2":0},
{"f":1812,"p":[{"hits":[],"hurts":[{"rx":-7.8,"ry":1.45,"rw":0.9,"rh":0.4,"t":3},{"rx":-7.8,"ry":0.7,"rw":0.9,"rh":0.75,"t":3},{"rx":-7.8,"ry":0.0,"rw":0.9,"rh":0.7,"t":3}],"grabs":[{"rx":-7.65,"ry":0.0,"rw":0.6,"rh":1.4,"t":4}],"clips":[{"rx":-7.65,"ry":0.0,"rw":0.6,"rh":1.4,"t":0}],"s":"744 VT_broking_HIGH_1 23 IASA","x1":-7.5,"x2":-7.5,"x3":-7.5,"hit":0,"fl":1,"st":0,"c":null},{"hits":[],"hurts":[{"rx":-7.04999971,"ry":1.3,"rw":0.7,"rh":0.4,"t":3},{"rx":-7.04999971,"ry":0.0,"rw":0.7,"rh":0.55,"t":3},{"rx":-7.04999971,"ry":0.55,"rw":0.7,"rh":0.75,"t":3},{"rx":-7.29999971,"ry":0.0,"rw":0.25,"rh":1.1,"t":3}],"grabs":[{"rx":-6.95,"ry":0.0,"rw":0.5,"rh":1.35,"t":4}],"clips":[{"rx":-6.95,"ry":0.0,"rw":0.5,"rh":1.35,"t":0}],"s":"602 5HP 14","x1":-6.39999962,"x2":-6.39999962,"x3":-6.399999,"hit":0,"fl":17,"st":0,"c":null}],"p1":[],"p2":[],"i1":0,"i2":0},
{"f":1813,"p":[{"hits":[],"hurts":[{"rx":-7.8,"ry":1.45,"rw":0.9,"rh":0.4,"t":3},{"rx":-7.8,"ry":0.7,"rw":0.9,"rh":0.75,"t":3},{"rx":-7.8,"ry":0.0,"rw":0.9,"rh":0.7,"t":3}],"grabs":[{"rx":-7.65,"ry":0.0,"rw":0.6,"rh":1.4,"t":4}],"clips":[{"rx":-7.65,"ry":0.0,"rw":0.6,"rh":1.4,"t":0}],"s":"744 VT_broking_HIGH_1 24 +","x1":-7.5,"x2":-7.5,"x3":-7.5,"hit":0,"fl":0,"st":0,"c":null},{"hits":[],"hurts":[{"rx":-7.04999971,"ry":1.3,"rw":0.7,"rh":0.4,"t":3},{"rx":-7.04999971,"ry":0.0,"rw":0.7,"rh":0.55,"t":3},{"rx":-7.04999971,"ry":0.55,"rw":0.7,"rh":0.75,"t":3},{"rx":-7.29999971,"ry":0.0,"rw":0.25,"rh":1.1,"t":3}],"grabs":[{"rx":-6.95,"ry":0.0,"rw":0.5,"rh":1.35,"t":4}],"clips":[{"rx":-6.95,"ry":0.0,"rw":0.5,"rh":1.35,"t":0}],"s":"602 5HP 15","x1":-6.39999962,"x2":-6.39999962,"x3":-6.399999,"hit":0,"fl":16,"st":0,"c":null}],"p1":[],"p2":[],"i1":0,"i2":0},
{"f":1814,"p":[{"hits":[],"hurts":[{"rx":-7.8,"ry":1.45,"rw":0.9,"rh":0.4,"t":3},{"rx":-7.8,"ry":0.7,"rw":0.9,"rh":0.75,"t":3},{"rx":-7.8,"ry":0.0,"rw":0.9,"rh":0.7,"t":3}],"grabs":[{"rx":-7.65,"ry":0.0,"rw":0.6,"rh":1.4,"t":4}],"clips":[{"rx":-7.65,"ry":0.0,"rw":0.6,"rh":1.4,"t":0}],"s":"744 VT_broking_HIGH_1 25 +","x1":-7.5,"x2":-7.5,"x3":-7.5,"hit":0,"fl":0,"st":0,"c":null},{"hits":[],"hurts":[{"rx":-7.04999971,"ry":1.3,"rw":0.7,"rh":0.4,"t":3},{"rx":-7.04999971,"ry":0.0,"rw":0.7,"rh":0.55,"t":3},{"rx":-7.04999971,"ry":0.55,"rw":0.7,"rh":0.75,"t":3}],"grabs":[{"rx":-6.95,"ry":0.0,"rw":0.5,"rh":1.35,"t":4}],"clips":[{"rx":-6.95,"ry":0.0,"rw":0.5,"rh":1.35,"t":0}],"s":"602 5HP 16","x1":-6.39999962,"x2":-6.39999962,"x3":-6.399999,"hit":0,"fl":15,"st":0,"c":null}],"p1":[],"p2":[],"i1":0,"i2":0},
{"f":1815,"p":[{"hits":[],"hurts":[{"rx":-7.8,"ry":1.45,"rw":0.9,"rh":0.4,"t":3},{"rx":-7.8,"ry":0.7,"rw":0.9,"rh":0.75,"t":3},{"rx":-7.8,"ry":0.0,"rw":0.9,"rh":0.7,"t":3}],"grabs":[{"rx":-7.65,"ry":0.0,"rw":0.6,"rh":1.4,"t":4}],"clips":[{"rx":-7.65,"ry":0.0,"rw":0.6,"rh":1.4,"t":0}],"s":"744 VT_broking_HIGH_1 26 +","x1":-7.5,"x2":-7.5,"x3":-7.5,"hit":0,"fl":0,"st":0,"c":null},{"hits":[],"hurts":[{"rx":-7.04999971,"ry":1.3,"rw":0.7,"rh":0.4,"t":3},{"rx":-7.04999971,"ry":0.0,"rw":0.7,"rh":0.55,"t":3},{"rx":-7.04999971,"ry":0.55,"rw":0.7,"rh":0.75,"t":3}],"grabs":[{"rx":-6.95,"ry":0.0,"rw":0.5,"rh":1.35,"t":4}],"clips":[{"rx":-6.95,"ry":0.0,"rw":0.5,"rh":1.35,"t":0}],"s":"602 5HP 17","x1":-6.39999962,"x2":-6.39999962,"x3":-6.399999,"hit":0,"fl":14,"st":0,"c":null}],"p1":[],"p2":[],"i1":0,"i2":0},
{"f":1816,"p":[{"hits":[],"hurts":[{"rx":-7.8,"ry":1.45,"rw":0.9,"rh":0.4,"t":3},{"rx":-7.8,"ry":0.7,"rw":0.9,"rh":0.75,"t":3},{"rx":-7.8,"ry":0.0,"rw":0.9,"rh":0.7,"t":3}],"grabs":[{"rx":-7.65,"ry":0.0,"rw":0.6,"rh":1.4,"t":4}],"clips":[{"rx":-7.65,"ry":0.0,"rw":0.6,"rh":1.4,"t":0}],"s":"744 VT_broking_HIGH_1 27 +","x1":-7.5,"x2":-7.5,"x3":-7.5,"hit":0,"fl":0,"st":0,"c":null},{"hits":[],"hurts":[{"rx":-7.04999971,"ry":1.3,"rw":0.7,"rh":0.4,"t":3},{"rx":-7.04999971,"ry":0.0,"rw":0.7,"rh":0.55,"t":3},{"rx":-7.04999971,"ry":0.55,"rw":0.7,"rh":0.75,"t":3}],"grabs":[{"rx":-6.95,"ry":0.0,"rw":0.5,"rh":1.35,"t":4}],"clips":[{"rx":-6.95,"ry":0.0,"rw":0.5,"rh":1.35,"t":0}],"s":"602 5HP 18","x1":-6.39999962,"x2":-6.39999962,"x3":-6.399999,"hit":0,"fl":13,"st":0,"c":null}],"p1":[],"p2":[],"i1":0,"i2":0},
{"f":1817,"p":[{"hits":[],"hurts":[{"rx":-7.8,"ry":1.45,"rw":0.9,"rh":0.4,"t":3},{"rx":-7.8,"ry":0.7,"rw":0.9,"rh":0.75,"t":3},{"rx":-7.8,"ry":0.0,"rw":0.9,"rh":0.7,"t":3}],"grabs":[{"rx":-7.65,"ry":0.0,"rw":0.6,"rh":1.4,"t":4}],"clips":[{"rx":-7.65,"ry":0.0,"rw":0.6,"rh":1.4,"t":0}],"s":"744 VT_broking_HIGH_1 28 +","x1":-7.5,"x2":-7.5,"x3":-7.5,"hit":0,"fl":0,"st":0,"c":null},{"hits":[],"hurts":[{"rx":-7.04999971,"ry":1.3,"rw":0.7,"rh":0.4,"t":3},{"rx":-7.04999971,"ry":0.0,"rw":0.7,"rh":0.55,"t":3},{"rx":-7.04999971,"ry":0.55,"rw":0.7,"rh":0.75,"t":3}],"grabs":[{"rx":-6.95,"ry":0.0,"rw":0.5,"rh":1.35,"t":4}],"clips":[{"rx":-6.95,"ry":0.0,"rw":0.5,"rh":1.35,"t":0}],"s":"602 5HP 19","x1":-6.39999962,"x2":-6.39999962,"x3":-6.399999,"hit":0,"fl":12,"st":0,"c":null}],"p1":[],"p2":[],"i1":0,"i2":0},
{"f":1818,"p":[{"hits":[],"hurts":[{"rx":-7.8,"ry":1.45,"rw":0.9,"rh":0.4,"t":3},{"rx":-7.8,"ry":0.7,"rw":0.9,"rh":0.75,"t":3},{"rx":-7.8,"ry":0.0,"rw":0.9,"rh":0.7,"t":3}],"grabs":[{"rx":-7.65,"ry":0.0,"rw":0.6,"rh":1.4,"t":4}],"clips":[{"rx":-7.65,"ry":0.0,"rw":0.6,"rh":1.4,"t":0}],"s":"744 VT_broking_HIGH_1 29 +","x1":-7.5,"x2":-7.5,"x3":-7.5,"hit":0,"fl":0,"st":0,"c":null},{"hits":[],"hurts":[{"rx":-7.04999971,"ry":1.3,"rw":0.7,"rh":0.4,"t":3},{"rx":-7.04999971,"ry":0.0,"rw":0.7,"rh":0.55,"t":3},{"rx":-7.04999971,"ry":0.55,"rw":0.7,"rh":0.75,"t":3}],"grabs":[{"rx":-6.95,"ry":0.0,"rw":0.5,"rh":1.35,"t":4}],"clips":[{"rx":-6.95,"ry":0.0,"rw":0.5,"rh":1.35,"t":0}],"s":"602 5HP 20","x1":-6.39999962,"x2":-6.39999962,"x3":-6.399999,"hit":0,"fl":11,"st":0,"c":null}],"p1":[],"p2":[],"i1":0,"i2":0},
{"f":1819,"p":[{"hits":[],"hurts":[{"rx":-7.8,"ry":1.45,"rw":0.9,"rh":0.4,"t":3},{"rx":-7.8,"ry":0.7,"rw":0.9,"rh":0.75,"t":3},{"rx":-7.8,"ry":0.0,"rw":0.9,"rh":0.7,"t":3}],"grabs":[{"rx":-7.65,"ry":0.0,"rw":0.6,"rh":1.4,"t":4}],"clips":[{"rx":-7.65,"ry":0.0,"rw":0.6,"rh":1.4,"t":0}],"s":"744 VT_broking_HIGH_1 30 +","x1":-7.5,"x2":-7.5,"x3":-7.5,"hit":0,"fl":0,"st":0,"c":null},{"hits":[],"hurts":[{"rx":-7.04999971,"ry":1.3,"rw":0.7,"rh":0.4,"t":3},{"rx":-7.04999971,"ry":0.0,"rw":0.7,"rh":0.55,"t":3},{"rx":-7.04999971,"ry":0.55,"rw":0.7,"rh":0.75,"t":3}],"grabs":[{"rx":-6.95,"ry":0.0,"rw":0.5,"rh":1.35,"t":4}],"clips":[{"rx":-6.95,"ry":0.0,"rw":0.5,"rh":1.35,"t":0}],"s":"602 5HP 21","x1":-6.39999962,"x2":-6.39999962,"x3":-6.399999,"hit":0,"fl":10,"st":0,"c":null}],"p1":[],"p2":[],"i1":0,"i2":0},
{"f":1820,"p":[{"hits":[],"hurts":[{"rx":-7.8,"ry":1.45,"rw":0.9,"rh":0.4,"t":3},{"rx":-7.8,"ry":0.7,"rw":0.9,"rh":0.75,"t":3},{"rx":-7.8,"ry":0.0,"rw":0.9,"rh":0.7,"t":3}],"grabs":[{"rx":-7.65,"ry":0.0,"rw":0.6,"rh":1.4,"t":4}],"clips":[{"rx":-7.65,"ry":0.0,"rw":0.6,"rh":1.4,"t":0}],"s":"744 VT_broking_HIGH_1 31 +","x1":-7.5,"x2":-7.5,"x3":-7.5,"hit":0,"fl":0,"st":0,"c":null},{"hits":[],"hurts":[{"rx":-7.04999971,"ry":1.3,"rw":0.7,"rh":0.4,"t":3},{"rx":-7.04999971,"ry":0.0,"rw":0.7,"rh":0.55,"t":3},{"rx":-7.04999971,"ry":0.55,"rw":0.7,"rh":0.75,"t":3}],"grabs":[{"rx":-6.95,"ry":0.0,"rw":0.5,"rh":1.35,"t":4}],"clips":[{"rx":-6.95,"ry":0.0,"rw":0.5,"rh":1.35,"t":0}],"s":"602 5HP 22","x1":-6.39999962,"x2":-6.39999962,"x3":-6.399999,"hit":0,"fl":9,"st":0,"c":null}],"p1":[],"p2":[],"i1":0,"i2":0},
{"f":1821,"p":[{"hits":[],"hurts":[{"rx":-7.8,"ry":1.45,"rw":0.9,"rh":0.4,"t":3},{"rx":-7.8,"ry":0.7,"rw":0.9,"rh":0.75,"t":3},{"rx":-7.8,"ry":0.0,"rw":0.9,"rh":0.7,"t":3}],"grabs":[{"rx":-7.65,"ry":0.0,"rw":0.6,"rh":1.4,"t":4}],"clips":[{"rx":-7.65,"ry":0.0,"rw":0.6,"rh":1.4,"t":0}],"s":"744 VT_broking_HIGH_1 32 +","x1":-7.5,"x2":-7.5,"x3":-7.5,"hit":0,"fl":0,"st":0,"c":null},{"hits":[],"hurts":[{"rx":-7.04999971,"ry":1.3,"rw":0.7,"rh":0.4,"t":3},{"rx":-7.04999971,"ry":0.0,"rw":0.7,"rh":0.55,"t":3},{"rx":-7.04999971,"ry":0.55,"rw":0.7,"rh":0.75,"t":3}],"grabs":[{"rx":-6.95,"ry":0.0,"rw":0.5,"rh":1.35,"t":4}],"clips":[{"rx":-6.95,"ry":0.0,"rw":0.5,"rh":1.35,"t":0}],"s":"602 5HP 23","x1":-6.39999962,"x2":-6.39999962,"x3":-6.399999,"hit":0,"fl":8,"st":0,"c":null}],"p1":[],"p2":[],"i1":0,"i2":0},
{"f":1822,"p":[{"hits":[],"hurts":[{"rx":-7.8,"ry":1.45,"rw":0.9,"rh":0.4,"t":3},{"rx":-7.8,"ry":0.7,"rw":0.9,"rh":0.75,"t":3},{"rx":-7.8,"ry":0.0,"rw":0.9,"rh":0.7,"t":3}],"grabs":[{"rx":-7.65,"ry":0.0,"rw":0.6,"rh":1.4,"t":4}],"clips":[{"rx":-7.65,"ry":0.0,"rw":0.6,"rh":1.4,"t":0}],"s":"744 VT_broking_HIGH_1 33 +","x1":-7.5,"x2":-7.5,"x3":-7.5,"hit":0,"fl":0,"st":0,"c":null},{"hits":[],"hurts":[{"rx":-7.04999971,"ry":1.3,"rw":0.7,"rh":0.4,"t":3},{"rx":-7.04999971,"ry":0.0,"rw":0.7,"rh":0.55,"t":3},{"rx":-7.04999971,"ry":0.55,"rw":0.7,"rh":0.75,"t":3}],"grabs":[{"rx":-6.95,"ry":0.0,"rw":0.5,"rh":1.35,"t":4}],"clips":[{"rx":-6.95,"ry":0.0,"rw":0.5,"rh":1.35,"t":0}],"s":"602 5HP 24","x1":-6.39999962,"x2":-6.39999962,"x3":-6.399999,"hit":0,"fl":7,"st":0,"c":null}],"p1":[],"p2":[],"i1":0,"i2":0},
{"f":1823,"p":[{"hits":[],"hurts":[{"rx":-7.8,"ry":1.45,"rw":0.9,"rh":0.4,"t":3},{"rx":-7.8,"ry":0.7,"rw":0.9,"rh":0.75,"t":3},{"rx":-7.8,"ry":0.0,"rw":0.9,"rh":0.7,"t":3}],"grabs":[{"rx":-7.65,"ry":0.0,"rw":0.6,"rh":1.4,"t":4}],"clips":[{"rx":-7.65,"ry":0.0,"rw":0.6,"rh":1.4,"t":0}],"s":"744 VT_broking_HIGH_1 34 +","x1":-7.5,"x2":-7.5,"x3":-7.5,"hit":0,"fl":0,"st":0,"c":null},{"hits":[],"hurts":[{"rx":-7.04999971,"ry":1.3,"rw":0.7,"rh":0.4,"t":3},{"rx":-7.04999971,"ry":0.0,"rw":0.7,"rh":0.55,"t":3},{"rx":-7.04999971,"ry":0.55,"rw":0.7,"rh":0.75,"t":3}],"grabs":[{"rx":-6.95,"ry":0.0,"rw":0.5,"rh":1.35,"t":4}],"clips":[{"rx":-6.95,"ry":0.0,"rw":0.5,"rh":1.35,"t":0}],"s":"602 5HP 25","x1":-6.39999962,"x2":-6.39999962,"x3":-6.399999,"hit":0,"fl":6,"st":0,"c":null}],"p1":[],"p2":[],"i1":0,"i2":0},
{"f":1824,"p":[{"hits":[],"hurts":[{"rx":-7.8,"ry":1.45,"rw":0.9,"rh":0.4,"t":3},{"rx":-7.8,"ry":0.7,"rw":0.9,"rh":0.75,"t":3},{"rx":-7.8,"ry":0.0,"rw":0.9,"rh":0.7,"t":3}],"grabs":[{"rx":-7.65,"ry":0.0,"rw":0.6,"rh":1.4,"t":4}],"clips":[{"rx":-7.65,"ry":0.0,"rw":0.6,"rh":1.4,"t":0}],"s":"744 VT_broking_HIGH_1 35 +","x1":-7.5,"x2":-7.5,"x3":-7.5,"hit":0,"fl":0,"st":0,"c":null},{"hits":[],"hurts":[{"rx":-7.04999971,"ry":1.3,"rw":0.7,"rh":0.4,"t":3},{"rx":-7.04999971,"ry":0.0,"rw":0.7,"rh":0.55,"t":3},{"rx":-7.04999971,"ry":0.55,"rw":0.7,"rh":0.75,"t":3}],"grabs":[{"rx":-6.95,"ry":0.0,"rw":0.5,"rh":1.35,"t":4}],"clips":[{"rx":-6.95,"ry":0.0,"rw":0.5,"rh":1.35,"t":0}],"s":"602 5HP 26","x1":-6.39999962,"x2":-6.39999962,"x3":-6.399999,"hit":0,"fl":5,"st":0,"c":null}],"p1":[],"p2":[],"i1":0,"i2":0},
{"f":1825,"p":[{"hits":[],"hurts":[{"rx":-7.8,"ry":1.45,"rw":0.9,"rh":0.4,"t":3},{"rx":-7.8,"ry":0.7,"rw":0.9,"rh":0.75,"t":3},{"rx":-7.8,"ry":0.0,"rw":0.9,"rh":0.7,"t":3}],"grabs":[{"rx":-7.65,"ry":0.0,"rw":0.6,"rh":1.4,"t":4}],"clips":[{"rx":-7.65,"ry":0.0,"rw":0.6,"rh":1.4,"t":0}],"s":"744 VT_broking_HIGH_1 36 +","x1":-7.5,"x2":-7.5,"x3":-7.5,"hit":0,"fl":0,"st":0,"c":null},{"hits":[],"hurts":[{"rx":-7.04999971,"ry":1.3,"rw":0.7,"rh":0.4,"t":3},{"rx":-7.04999971,"ry":0.0,"rw":0.7,"rh":0.55,"t":3},{"rx":-7.04999971,"ry":0.55,"rw":0.7,"rh":0.75,"t":3}],"grabs":[{"rx":-6.95,"ry":0.0,"rw":0.5,"rh":1.35,"t":4}],"clips":[{"rx":-6.95,"ry":0.0,"rw":0.5,"rh":1.35,"t":0}],"s":"602 5HP 27","x1":-6.39999962,"x2":-6.39999962,"x3":-6.399999,"hit":0,"fl":4,"st":0,"c":null}],"p1":[],"p2":[],"i1":0,"i2":0},
{"f":1826,"p":[{"hits":[],"hurts":[{"rx":-7.8,"ry":1.45,"rw":0.9,"rh":0.4,"t":3},{"rx":-7.8,"ry":0.7,"rw":0.9,"rh":0.75,"t":3},{"rx":-7.8,"ry":0.0,"rw":0.9,"rh":0.7,"t":3}],"grabs":[{"rx":-7.65,"ry":0.0,"rw":0.6,"rh":1.4,"t":4}],"clips":[{"rx":-7.65,"ry":0.0,"rw":0.6,"rh":1.4,"t":0}],"s":"744 VT_broking_HIGH_1 37 +","x1":-7.5,"x2":-7.5,"x3":-7.5,"hit":0,"fl":0,"st":0,"c":null},{"hits":[],"hurts":[{"rx":-7.04999971,"ry":1.3,"rw":0.7,"rh":0.4,"t":3},{"rx":-7.04999971,"ry":0.0,"rw":0.7,"rh":0.55,"t":3},{"rx":-7.04999971,"ry":0.55,"rw":0.7,"rh":0.75,"t":3}],"grabs":[{"rx":-6.95,"ry":0.0,"rw":0.5,"rh":1.35,"t":4}],"clips":[{"rx":-6.95,"ry":0.0,"rw":0.5,"rh":1.35,"t":0}],"s":"602 5HP 28","x1":-6.39999962,"x2":-6.39999962,"x3":-6.399999,"hit":0,"fl":3,"st":0,"c":null}],"p1":[],"p2":[],"i1":0,"i2":0},
{"f":1827,"p":[{"hits":[],"hurts":[{"rx":-7.8,"ry":1.45,"rw":0.9,"rh":0.4,"t":3},{"rx":-7.8,"ry":0.7,"rw":0.9,"rh":0.75,"t":3},{"rx":-7.8,"ry":0.0,"rw":0.9,"rh":0.7,"t":3}],"grabs":[{"rx":-7.65,"ry":0.0,"rw":0.6,"rh":1.4,"t":4}],"clips":[{"rx":-7.65,"ry":0.0,"rw":0.6,"rh":1.4,"t":0}],"s":"744 VT_broking_HIGH_1 38 +","x1":-7.5,"x2":-7.5,"x3":-7.5,"hit":0,"fl":0,"st":0,"c":null},{"hits":[],"hurts":[{"rx":-7.04999971,"ry":1.3,"rw":0.7,"rh":0.4,"t":3},{"rx":-7.04999971,"ry":0.0,"rw":0.7,"rh":0.55,"t":3},{"rx":-7.04999971,"ry":0.55,"rw":0.7,"rh":0.75,"t":3}],"grabs":[{"rx":-6.95,"ry":0.0,"rw":0.5,"rh":1.35,"t":4}],"clips":[{"rx":-6.95,"ry":0.0,"rw":0.5,"rh":1.35,"t":0}],"s":"602 5HP 29","x1":-6.39999962,"x2":-6.39999962,"x3":-6.399999,"hit":0,"fl":2,"st":0,"c":null}],"p1":[],"p2":[],"i1":0,"i2":0},
{"f":1828,"p":[{"hits":[],"hurts":[{"rx":-7.8,"ry":1.45,"rw":0.9,"rh":0.4,"t":3},{"rx":-7.8,"ry":0.7,"rw":0.9,"rh":0.75,"t":3},{"rx":-7.8,"ry":0.0,"rw":0.9,"rh":0.7,"t":3}],"grabs":[{"rx":-7.65,"ry":0.0,"rw":0.6,"rh":1.4,"t":4}],"clips":[{"rx":-7.65,"ry":0.0,"rw":0.6,"rh":1.4,"t":0}],"s":"744 VT_broking_HIGH_1 39 +","x1":-7.5,"x2":-7.5,"x3":-7.5,"hit":0,"fl":0,"st":0,"c":null},{"hits":[],"hurts":[{"rx":-7.04999971,"ry":1.3,"rw":0.7,"rh":0.4,"t":3},{"rx":-7.04999971,"ry":0.0,"rw":0.7,"rh":0.55,"t":3},{"rx":-7.04999971,"ry":0.55,"rw":0.7,"rh":0.75,"t":3}],"grabs":[{"rx":-6.95,"ry":0.0,"rw":0.5,"rh":1.35,"t":4}],"clips":[{"rx":-6.95,"ry":0.0,"rw":0.5,"rh":1.35,"t":0}],"s":"602 5HP 30 IASA","x1":-6.39999962,"x2":-6.39999962,"x3":-6.399999,"hit":0,"fl":1,"st":0,"c":null}],"p1":[],"p2":[],"i1":0,"i2":0},
{"f":1829,"p":[{"hits":[],"hurts":[{"rx":-7.8,"ry":1.45,"rw":0.9,"rh":0.4,"t":3},{"rx":-7.8,"ry":0.7,"rw":0.9,"rh":0.75,"t":3},{"rx":-7.8,"ry":0.0,"rw":0.9,"rh":0.7,"t":3}],"grabs":[{"rx":-7.65,"ry":0.0,"rw":0.6,"rh":1.4,"t":4}],"clips":[{"rx":-7.65,"ry":0.0,"rw":0.6,"rh":1.4,"t":0}],"s":"744 VT_broking_HIGH_1 40 +","x1":-7.5,"x2":-7.5,"x3":-7.5,"hit":0,"fl":0,"st":0,"c":null},{"hits":[],"hurts":[{"rx":-6.74999952,"ry":1.3,"rw":0.7,"rh":0.4,"t":3},{"rx":-6.74999952,"ry":0.0,"rw":0.7,"rh":0.55,"t":3},{"rx":-6.74999952,"ry":0.55,"rw":0.7,"rh":0.75,"t":3}],"grabs":[{"rx":-6.64999962,"ry":0.0,"rw":0.5,"rh":1.35,"t":4}],"clips":[{"rx":-6.64999962,"ry":0.0,"rw":0.5,"rh":1.35,"t":0}],"s":"602 5HP 31 +","x1":-6.39999962,"x2":-6.39999962,"x3":-6.399999,"hit":0,"fl":0,"st":0,"c":null}],"p1":[],"p2":[],"i1":0,"i2":0},
{"f":1830,"p":[{"hits":[],"hurts":[{"rx":-7.8,"ry":1.45,"rw":0.9,"rh":0.4,"t":3},{"rx":-7.8,"ry":0.7,"rw":0.9,"rh":0.75,"t":3},{"rx":-7.8,"ry":0.0,"rw":0.9,"rh":0.7,"t":3}],"grabs":[{"rx":-7.65,"ry":0.0,"rw":0.6,"rh":1.4,"t":4}],"clips":[{"rx":-7.65,"ry":0.0,"rw":0.6,"rh":1.4,"t":0}],"s":"744 VT_broking_HIGH_1 41 +","x1":-7.5,"x2":-7.5,"x3":-7.5,"hit":0,"fl":0,"st":0,"c":null},{"hits":[],"hurts":[{"rx":-6.74999952,"ry":1.3,"rw":0.7,"rh":0.4,"t":3},{"rx":-6.74999952,"ry":0.0,"rw":0.7,"rh":0.55,"t":3},{"rx":-6.74999952,"ry":0.55,"rw":0.7,"rh":0.75,"t":3}],"grabs":[{"rx":-6.64999962,"ry":0.0,"rw":0.5,"rh":1.35,"t":4}],"clips":[{"rx":-6.64999962,"ry":0.0,"rw":0.5,"rh":1.35,"t":0}],"s":"602 5HP 32 +","x1":-6.39999962,"x2":-6.39999962,"x3":-6.399999,"hit":0,"fl":0,"st":0,"c":null}],"p1":[],"p2":[],"i1":0,"i2":0},
{"f":1831,"p":[{"hits":[],"hurts":[{"rx":-7.8,"ry":1.45,"rw":0.9,"rh":0.4,"t":3},{"rx":-7.8,"ry":0.7,"rw":0.9,"rh":0.75,"t":3},{"rx":-7.8,"ry":0.0,"rw":0.9,"rh":0.7,"t":3}],"grabs":[{"rx":-7.65,"ry":0.0,"rw":0.6,"rh":1.4,"t":4}],"clips":[{"rx":-7.65,"ry":0.0,"rw":0.6,"rh":1.4,"t":0}],"s":"744 VT_broking_HIGH_1 42 +","x1":-7.5,"x2":-7.5,"x3":-7.5,"hit":0,"fl":0,"st":0,"c":null},{"hits":[],"hurts":[{"rx":-6.74999952,"ry":1.3,"rw":0.7,"rh":0.4,"t":3},{"rx":-6.74999952,"ry":0.0,"rw":0.7,"rh":0.55,"t":3},{"rx":-6.74999952,"ry":0.55,"rw":0.7,"rh":0.75,"t":3}],"grabs":[{"rx":-6.64999962,"ry":0.0,"rw":0.5,"rh":1.35,"t":4}],"clips":[{"rx":-6.64999962,"ry":0.0,"rw":0.5,"rh":1.35,"t":0}],"s":"602 5HP 33 +","x1":-6.39999962,"x2":-6.39999962,"x3":-6.399999,"hit":0,"fl":0,"st":0,"c":null}],"p1":[],"p2":[],"i1":0,"i2":0},
{"f":1832,"p":[{"hits":[],"hurts":[{"rx":-7.8,"ry":1.45,"rw":0.9,"rh":0.4,"t":3},{"rx":-7.8,"ry":0.7,"rw":0.9,"rh":0.75,"t":3},{"rx":-7.8,"ry":0.0,"rw":0.9,"rh":0.7,"t":3}],"grabs":[{"rx":-7.65,"ry":0.0,"rw":0.6,"rh":1.4,"t":4}],"clips":[{"rx":-7.65,"ry":0.0,"rw":0.6,"rh":1.4,"t":0}],"s":"744 VT_broking_HIGH_1 43 +","x1":-7.5,"x2":-7.5,"x3":-7.5,"hit":0,"fl":0,"st":0,"c":null},{"hits":[],"hurts":[{"rx":-6.74999952,"ry":1.3,"rw":0.7,"rh":0.4,"t":3},{"rx":-6.74999952,"ry":0.0,"rw":0.7,"rh":0.55,"t":3},{"rx":-6.74999952,"ry":0.55,"rw":0.7,"rh":0.75,"t":3}],"grabs":[{"rx":-6.64999962,"ry":0.0,"rw":0.5,"rh":1.35,"t":4}],"clips":[{"rx":-6.64999962,"ry":0.0,"rw":0.5,"rh":1.35,"t":0}],"s":"602 5HP 34 +","x1":-6.39999962,"x2":-6.39999962,"x3":-6.399999,"hit":0,"fl":0,"st":0,"c":null}],"p1":[],"p2":[],"i1":0,"i2":0},
{"f":1833,"p":[{"hits":[],"hurts":[{"rx":-7.8,"ry":1.45,"rw":0.9,"rh":0.4,"t":3},{"rx":-7.8,"ry":0.7,"rw":0.9,"rh":0.75,"t":3},{"rx":-7.8,"ry":0.0,"rw":0.9,"rh":0.7,"t":3}],"grabs":[{"rx":-7.65,"ry":0.0,"rw":0.6,"rh":1.4,"t":4}],"clips":[{"rx":-7.65,"ry":0.0,"rw":0.6,"rh":1.4,"t":0}],"s":"744 VT_broking_HIGH_1 44 +","x1":-7.5,"x2":-7.5,"x3":-7.5,"hit":0,"fl":0,"st":0,"c":null},{"hits":[],"hurts":[{"rx":-6.74999952,"ry":1.3,"rw":0.7,"rh":0.4,"t":3},{"rx":-6.74999952,"ry":0.0,"rw":0.7,"rh":0.55,"t":3},{"rx":-6.74999952,"ry":0.55,"rw":0.7,"rh":0.75,"t":3}],"grabs":[{"rx":-6.64999962,"ry":0.0,"rw":0.5,"rh":1.35,"t":4}],"clips":[{"rx":-6.64999962,"ry":0.0,"rw":0.5,"rh":1.35,"t":0}],"s":"602 5HP 35 +","x1":-6.39999962,"x2":-6.39999962,"x3":-6.399999,"hit":0,"fl":0,"st":0,"c":null}],"p1":[],"p2":[],"i1":0,"i2":0},
{"f":1834,"p":[{"hits":[],"hurts":[{"rx":-7.8,"ry":1.45,"rw":0.9,"rh":0.4,"t":3},{"rx":-7.8,"ry":0.7,"rw":0.9,"rh":0.75,"t":3},{"rx":-7.8,"ry":0.0,"rw":0.9,"rh":0.7,"t":3}],"grabs":[{"rx":-7.65,"ry":0.0,"rw":0.6,"rh":1.4,"t":4}],"clips":[{"rx":-7.65,"ry":0.0,"rw":0.6,"rh":1.4,"t":0}],"s":"744 VT_broking_HIGH_1 45 +","x1":-7.5,"x2":-7.5,"x3":-7.5,"hit":0,"fl":0,"st":0,"c":null},{"hits":[],"hurts":[{"rx":-6.74999952,"ry":1.3,"rw":0.7,"rh":0.4,"t":3},{"rx":-6.74999952,"ry":0.0,"rw":0.7,"rh":0.55,"t":3},{"rx":-6.74999952,"ry":0.55,"rw":0.7,"rh":0.75,"t":3}],"grabs":[{"rx":-6.64999962,"ry":0.0,"rw":0.5,"rh":1.35,"t":4}],"clips":[{"rx":-6.64999962,"ry":0.0,"rw":0.5,"rh":1.35,"t":0}],"s":"602 5HP 36 +","x1":-6.39999962,"x2":-6.39999962,"x3":-6.399999,"hit":0,"fl":0,"st":0,"c":null}],"p1":[],"p2":[],"i1":0,"i2":0},
{"f":1835,"p":[{"hits":[],"hurts":[{"rx":-7.8,"ry":1.45,"rw":0.9,"rh":0.4,"t":3},{"rx":-7.8,"ry":0.7,"rw":0.9,"rh":0.75,"t":3},{"rx":-7.8,"ry":0.0,"rw":0.9,"rh":0.7,"t":3}],"grabs":[{"rx":-7.65,"ry":0.0,"rw":0.6,"rh":1.4,"t":4}],"clips":[{"rx":-7.65,"ry":0.0,"rw":0.6,"rh":1.4,"t":0}],"s":"744 VT_broking_HIGH_1 46 +","x1":-7.5,"x2":-7.5,"x3":-7.5,"hit":0,"fl":0,"st":0,"c":null},{"hits":[],"hurts":[{"rx":-6.74999952,"ry":1.3,"rw":0.7,"rh":0.4,"t":3},{"rx":-6.74999952,"ry":0.0,"rw":0.7,"rh":0.55,"t":3},{"rx":-6.74999952,"ry":0.55,"rw":0.7,"rh":0.75,"t":3}],"grabs":[{"rx":-6.64999962,"ry":0.0,"rw":0.5,"rh":1.35,"t":4}],"clips":[{"rx":-6.64999962,"ry":0.0,"rw":0.5,"rh":1.35,"t":0}],"s":"602 5HP 37 +","x1":-6.39999962,"x2":-6.39999962,"x3":-6.399999,"hit":0,"fl":0,"st":0,"c":null}],"p1":[],"p2":[],"i1":0,"i2":0},
{"f":1836,"p":[{"hits":[],"hurts":[{"rx":-7.8,"ry":1.45,"rw":0.9,"rh":0.4,"t":3},{"rx":-7.8,"ry":0.7,"rw":0.9,"rh":0.75,"t":3},{"rx":-7.8,"ry":0.0,"rw":0.9,"rh":0.7,"t":3}],"grabs":[{"rx":-7.65,"ry":0.0,"rw":0.6,"rh":1.4,"t":4}],"clips":[{"rx":-7.65,"ry":0.0,"rw":0.6,"rh":1.4,"t":0}],"s":"744 VT_broking_HIGH_1 47 +","x1":-7.5,"x2":-7.5,"x3":-7.5,"hit":0,"fl":0,"st":0,"c":null},{"hits":[],"hurts":[{"rx":-6.74999952,"ry":1.3,"rw":0.7,"rh":0.4,"t":3},{"rx":-6.74999952,"ry":0.0,"rw":0.7,"rh":0.55,"t":3},{"rx":-6.74999952,"ry":0.55,"rw":0.7,"rh":0.75,"t":3}],"grabs":[{"rx":-6.64999962,"ry":0.0,"rw":0.5,"rh":1.35,"t":4}],"clips":[{"rx":-6.64999962,"ry":0.0,"rw":0.5,"rh":1.35,"t":0}],"s":"602 5HP 38 +","x1":-6.39999962,"x2":-6.39999962,"x3":-6.399999,"hit":0,"fl":0,"st":0,"c":null}],"p1":[],"p2":[],"i1":0,"i2":0},
{"f":1837,"p":[{"hits":[],"hurts":[{"rx":-7.8,"ry":1.45,"rw":0.9,"rh":0.4,"t":3},{"rx":-7.8,"ry":0.7,"rw":0.9,"rh":0.75,"t":3},{"rx":-7.8,"ry":0.0,"rw":0.9,"rh":0.7,"t":3}],"grabs":[{"rx":-7.65,"ry":0.0,"rw":0.6,"rh":1.4,"t":4}],"clips":[{"rx":-7.65,"ry":0.0,"rw":0.6,"rh":1.4,"t":0}],"s":"744 VT_broking_HIGH_1 48 +","x1":-7.5,"x2":-7.5,"x3":-7.5,"hit":0,"fl":0,"st":0,"c":null},{"hits":[],"hurts":[{"rx":-6.74999952,"ry":1.3,"rw":0.7,"rh":0.4,"t":3},{"rx":-6.74999952,"ry":0.0,"rw":0.7,"rh":0.55,"t":3},{"rx":-6.74999952,"ry":0.55,"rw":0.7,"rh":0.75,"t":3}],"grabs":[{"rx":-6.64999962,"ry":0.0,"rw":0.5,"rh":1.35,"t":4}],"clips":[{"rx":-6.64999962,"ry":0.0,"rw":0.5,"rh":1.35,"t":0}],"s":"602 5HP 39 +","x1":-6.39999962,"x2":-6.39999962,"x3":-6.399999,"hit":0,"fl":0,"st":0,"c":null}],"p1":[],"p2":[],"i1":0,"i2":0},
{"f":1838,"p":[{"hits":[],"hurts":[{"rx":-7.8,"ry":1.45,"rw":0.9,"rh":0.4,"t":3},{"rx":-7.8,"ry":0.7,"rw":0.9,"rh":0.75,"t":3},{"rx":-7.8,"ry":0.0,"rw":0.9,"rh":0.7,"t":3}],"grabs":[{"rx":-7.65,"ry":0.0,"rw":0.6,"rh":1.4,"t":4}],"clips":[{"rx":-7.65,"ry":0.0,"rw":0.6,"rh":1.4,"t":0}],"s":"744 VT_broking_HIGH_1 49 +","x1":-7.5,"x2":-7.5,"x3":-7.5,"hit":0,"fl":0,"st":0,"c":null},{"hits":[],"hurts":[{"rx":-6.74999952,"ry":1.3,"rw":0.7,"rh":0.4,"t":3},{"rx":-6.74999952,"ry":0.0,"rw":0.7,"rh":0.55,"t":3},{"rx":-6.74999952,"ry":0.55,"rw":0.7,"rh":0.75,"t":3}],"grabs":[{"rx":-6.64999962,"ry":0.0,"rw":0.5,"rh":1.35,"t":4}],"clips":[{"rx":-6.64999962,"ry":0.0,"rw":0.5,"rh":1.35,"t":0}],"s":"602 5HP 40 +","x1":-6.39999962,"x2":-6.39999962,"x3":-6.399999,"hit":0,"fl":0,"st":0,"c":null}],"p1":[],"p2":[],"i1":0,"i2":0},
{"f":1839,"p":[{"hits":[],"hurts":[{"rx":-7.8,"ry":1.45,"rw":0.9,"rh":0.4,"t":3},{"rx":-7.8,"ry":0.7,"rw":0.9,"rh":0.75,"t":3},{"rx":-7.8,"ry":0.0,"rw":0.9,"rh":0.7,"t":3}],"grabs":[{"rx":-7.65,"ry":0.0,"rw":0.6,"rh":1.4,"t":4}],"clips":[{"rx":-7.65,"ry":0.0,"rw":0.6,"rh":1.4,"t":0}],"s":"744 VT_broking_HIGH_1 50 +","x1":-7.5,"x2":-7.5,"x3":-7.5,"hit":0,"fl":0,"st":0,"c":null},{"hits":[],"hurts":[{"rx":-6.74999952,"ry":1.3,"rw":0.7,"rh":0.4,"t":3},{"rx":-6.74999952,"ry":0.0,"rw":0.7,"rh":0.55,"t":3},{"rx":-6.74999952,"ry":0.55,"rw":0.7,"rh":0.75,"t":3}],"grabs":[{"rx":-6.64999962,"ry":0.0,"rw":0.5,"rh":1.35,"t":4}],"clips":[{"rx":-6.64999962,"ry":0.0,"rw":0.5,"rh":1.35,"t":0}],"s":"602 5HP 41 +","x1":-6.39999962,"x2":-6.39999962,"x3":-6.399999,"hit":0,"fl":0,"st":0,"c":null}],"p1":[],"p2":[],"i1":0,"i2":0},
{"f":1840,"p":[{"hits":[],"hurts":[{"rx":-7.8,"ry":1.45,"rw":0.9,"rh":0.4,"t":3},{"rx":-7.8,"ry":0.7,"rw":0.9,"rh":0.75,"t":3},{"rx":-7.8,"ry":0.0,"rw":0.9,"rh":0.7,"t":3}],"grabs":[{"rx":-7.65,"ry":0.0,"rw":0.6,"rh":1.4,"t":4}],"clips":[{"rx":-7.65,"ry":0.0,"rw":0.6,"rh":1.4,"t":0}],"s":"744 VT_broking_HIGH_1 51 +","x1":-7.5,"x2":-7.5,"x3":-7.5,"hit":0,"fl":0,"st":0,"c":null},{"hits":[],"hurts":[{"rx":-6.7,"ry":1.3,"rw":0.42,"rh":0.4,"t":3},{"rx":-6.74999952,"ry":0.55,"rw":0.7,"rh":0.98,"t":3},{"rx":-6.74999952,"ry":0.0,"rw":0.7,"rh":0.55,"t":3}],"grabs":[{"rx":-6.64999962,"ry":0.0,"rw":0.5,"rh":1.35,"t":4}],"clips":[{"rx":-6.64999962,"ry":0.0,"rw":0.5,"rh":1.35,"t":0}],"s":"0 STAND 1","x1":-6.39999962,"x2":-6.39999962,"x3":-6.399999,"hit":0,"fl":0,"st":0,"c":null}],"p1":[],"p2":[],"i1":0,"i2":0},
{"f":1841,"p":[{"hits":[],"hurts":[{"rx":-7.8,"ry":1.45,"rw":0.9,"rh":0.4,"t":3},{"rx":-7.8,"ry":0.7,"rw":0.9,"rh":0.75,"t":3},{"rx":-7.8,"ry":0.0,"rw":0.9,"rh":0.7,"t":3}],"grabs":[{"rx":-7.65,"ry":0.0,"rw":0.6,"rh":1.4,"t":4}],"clips":[{"rx":-7.65,"ry":0.0,"rw":0.6,"rh":1.4,"t":0}],"s":"744 VT_broking_HIGH_1 52 +","x1":-7.5,"x2":-7.5,"x3":-7.5,"hit":0,"fl":0,"st":0,"c":null},{"hits":[],"hurts":[{"rx":-6.7,"ry":1.3,"rw":0.42,"rh":0.4,"t":3},{"rx":-6.74999952,"ry":0.55,"rw":0.7,"rh":0.98,"t":3},{"rx":-6.74999952,"ry":0.0,"rw":0.7,"rh":0.55,"t":3}],"grabs":[{"rx":-6.64999962,"ry":0.0,"rw":0.5,"rh":1.35,"t":4}],"clips":[{"rx":-6.64999962,"ry":0.0,"rw":0.5,"rh":1.35,"t":0}],"s":"0 STAND 2","x1":-6.39999962,"x2":-6.39999962,"x3":-6.399999,"hit":0,"fl":0,"st":0,"c":null}],"p1":[],"p2":[],"i1":0,"i2":0},
{"f":1842,"p":[{"hits":[],"hurts":[{"rx":-7.8,"ry":1.45,"rw":0.9,"rh":0.4,"t":3},{"rx":-7.8,"ry":0.7,"rw":0.9,"rh":0.75,"t":3},{"rx":-7.8,"ry":0.0,"rw":0.9,"rh":0.7,"t":3}],"grabs":[{"rx":-7.65,"ry":0.0,"rw":0.6,"rh":1.4,"t":4}],"clips":[{"rx":-7.65,"ry":0.0,"rw":0.6,"rh":1.4,"t":0}],"s":"744 VT_broking_HIGH_1 53 +","x1":-7.5,"x2":-7.5,"x3":-7.5,"hit":0,"fl":0,"st":0,"c":null},{"hits":[],"hurts":[{"rx":-6.7,"ry":1.3,"rw":0.42,"rh":0.4,"t":3},{"rx":-6.74999952,"ry":0.55,"rw":0.7,"rh":0.98,"t":3},{"rx":-6.74999952,"ry":0.0,"rw":0.7,"rh":0.55,"t":3}],"grabs":[{"rx":-6.64999962,"ry":0.0,"rw":0.5,"rh":1.35,"t":4}],"clips":[{"rx":-6.64999962,"ry":0.0,"rw":0.5,"rh":1.35,"t":0}],"s":"0 STAND 3","x1":-6.39999962,"x2":-6.39999962,"x3":-6.399999,"hit":0,"fl":0,"st":0,"c":null}],"p1":[],"p2":[],"i1":0,"i2":0},
{"f":1843,"p":[{"hits":[],"hurts":[{"rx":-7.8,"ry":1.45,"rw":0.9,"rh":0.4,"t":3},{"rx":-7.8,"ry":0.7,"rw":0.9,"rh":0.75,"t":3},{"rx":-7.8,"ry":0.0,"rw":0.9,"rh":0.7,"t":3}],"grabs":[{"rx":-7.65,"ry":0.0,"rw":0.6,"rh":1.4,"t":4}],"clips":[{"rx":-7.65,"ry":0.0,"rw":0.6,"rh":1.4,"t":0}],"s":"744 VT_broking_HIGH_1 54 +","x1":-7.5,"x2":-7.5,"x3":-7.5,"hit":0,"fl":0,"st":0,"c":null},{"hits":[],"hurts":[{"rx":-6.7,"ry":1.3,"rw":0.42,"rh":0.4,"t":3},{"rx":-6.74999952,"ry":0.55,"rw":0.7,"rh":0.98,"t":3},{"rx":-6.74999952,"ry":0.0,"rw":0.7,"rh":0.55,"t":3}],"grabs":[{"rx":-6.64999962,"ry":0.0,"rw":0.5,"rh":1.35,"t":4}],"clips":[{"rx":-6.64999962,"ry":0.0,"rw":0.5,"rh":1.35,"t":0}],"s":"0 STAND 4","x1":-6.39999962,"x2":-6.39999962,"x3":-6.399999,"hit":0,"fl":0,"st":0,"c":null}],"p1":[],"p2":[],"i1":0,"i2":0},
{"f":1844,"p":[{"hits":[],"hurts":[{"rx":-7.8,"ry":1.45,"rw":0.9,"rh":0.4,"t":3},{"rx":-7.8,"ry":0.7,"rw":0.9,"rh":0.75,"t":3},{"rx":-7.8,"ry":0.0,"rw":0.9,"rh":0.7,"t":3}],"grabs":[{"rx":-7.65,"ry":0.0,"rw":0.6,"rh":1.4,"t":4}],"clips":[{"rx":-7.65,"ry":0.0,"rw":0.6,"rh":1.4,"t":0}],"s":"744 VT_broking_HIGH_1 55 +","x1":-7.5,"x2":-7.5,"x3":-7.5,"hit":0,"fl":0,"st":0,"c":null},{"hits":[],"hurts":[{"rx":-6.7,"ry":1.3,"rw":0.42,"rh":0.4,"t":3},{"rx":-6.74999952,"ry":0.55,"rw":0.7,"rh":0.98,"t":3},{"rx":-6.74999952,"ry":0.0,"rw":0.7,"rh":0.55,"t":3}],"grabs":[{"rx":-6.64999962,"ry":0.0,"rw":0.5,"rh":1.35,"t":4}],"clips":[{"rx":-6.64999962,"ry":0.0,"rw":0.5,"rh":1.35,"t":0}],"s":"0 STAND 5","x1":-6.39999962,"x2":-6.39999962,"x3":-6.399999,"hit":0,"fl":0,"st":0,"c":null}],"p1":[],"p2":[],"i1":0,"i2":0},
{"f":1845,"p":[{"hits":[],"hurts":[{"rx":-7.8,"ry":1.45,"rw":0.9,"rh":0.4,"t":3},{"rx":-7.8,"ry":0.7,"rw":0.9,"rh":0.75,"t":3},{"rx":-7.8,"ry":0.0,"rw":0.9,"rh":0.7,"t":3}],"grabs":[{"rx":-7.65,"ry":0.0,"rw":0.6,"rh":1.4,"t":4}],"clips":[{"rx":-7.65,"ry":0.0,"rw":0.6,"rh":1.4,"t":0}],"s":"744 VT_broking_HIGH_1 56 +","x1":-7.5,"x2":-7.5,"x3":-7.5,"hit":0,"fl":0,"st":0,"c":null},{"hits":[],"hurts":[{"rx":-6.7,"ry":1.3,"rw":0.42,"rh":0.4,"t":3},{"rx":-6.74999952,"ry":0.55,"rw":0.7,"rh":0.98,"t":3},{"rx":-6.74999952,"ry":0.0,"rw":0.7,"rh":0.55,"t":3}],"grabs":[{"rx":-6.64999962,"ry":0.0,"rw":0.5,"rh":1.35,"t":4}],"clips":[{"rx":-6.64999962,"ry":0.0,"rw":0.5,"rh":1.35,"t":0}],"s":"0 STAND 6","x1":-6.39999962,"x2":-6.39999962,"x3":-6.399999,"hit":0,"fl":0,"st":0,"c":null}],"p1":[],"p2":[],"i1":0,"i2":0},
{"f":1846,"p":[{"hits":[],"hurts":[{"rx":-7.8,"ry":1.45,"rw":0.9,"rh":0.4,"t":3},{"rx":-7.8,"ry":0.7,"rw":0.9,"rh":0.75,"t":3},{"rx":-7.8,"ry":0.0,"rw":0.9,"rh":0.7,"t":3}],"grabs":[{"rx":-7.65,"ry":0.0,"rw":0.6,"rh":1.4,"t":4}],"clips":[{"rx":-7.65,"ry":0.0,"rw":0.6,"rh":1.4,"t":0}],"s":"744 VT_broking_HIGH_1 57 +","x1":-7.5,"x2":-7.5,"x3":-7.5,"hit":0,"fl":0,"st":0,"c":null},{"hits":[],"hurts":[{"rx":-6.7,"ry":1.3,"rw":0.42,"rh":0.4,"t":3},{"rx":-6.74999952,"ry":0.55,"rw":0.7,"rh":0.98,"t":3},{"rx":-6.74999952,"ry":0.0,"rw":0.7,"rh":0.55,"t":3}],"grabs":[{"rx":-6.64999962,"ry":0.0,"rw":0.5,"rh":1.35,"t":4}],"clips":[{"rx":-6.64999962,"ry":0.0,"rw":0.5,"rh":1.35,"t":0}],"s":"0 STAND 7","x1":-6.39999962,"x2":-6.39999962,"x3":-6.399999,"hit":0,"fl":0,"st":0,"c":null}],"p1":[],"p2":[],"i1":0,"i2":0},
{"f":1847,"p":[{"hits":[],"hurts":[{"rx":-7.8,"ry":1.45,"rw":0.9,"rh":0.4,"t":3},{"rx":-7.8,"ry":0.7,"rw":0.9,"rh":0.75,"t":3},{"rx":-7.8,"ry":0.0,"rw":0.9,"rh":0.7,"t":3}],"grabs":[{"rx":-7.65,"ry":0.0,"rw":0.6,"rh":1.4,"t":4}],"clips":[{"rx":-7.65,"ry":0.0,"rw":0.6,"rh":1.4,"t":0}],"s":"744 VT_broking_HIGH_1 58 +","x1":-7.5,"x2":-7.5,"x3":-7.5,"hit":0,"fl":0,"st":0,"c":null},{"hits":[],"hurts":[{"rx":-6.7,"ry":1.3,"rw":0.42,"rh":0.4,"t":3},{"rx":-6.74999952,"ry":0.55,"rw":0.7,"rh":0.98,"t":3},{"rx":-6.74999952,"ry":0.0,"rw":0.7,"rh":0.55,"t":3}],"grabs":[{"rx":-6.64999962,"ry":0.0,"rw":0.5,"rh":1.35,"t":4}],"clips":[{"rx":-6.64999962,"ry":0.0,"rw":0.5,"rh":1.35,"t":0}],"s":"0 STAND 8","x1":-6.39999962,"x2":-6.39999962,"x3":-6.399999,"hit":0,"fl":0,"st":0,"c":null}],"p1":[],"p2":[],"i1":0,"i2":0},
{"f":1848,"p":[{"hits":[],"hurts":[{"rx":-7.8,"ry":1.45,"rw":0.9,"rh":0.4,"t":3},{"rx":-7.8,"ry":0.7,"rw":0.9,"rh":0.75,"t":3},{"rx":-7.8,"ry":0.0,"rw":0.9,"rh":0.7,"t":3}],"grabs":[{"rx":-7.65,"ry":0.0,"rw":0.6,"rh":1.4,"t":4}],"clips":[{"rx":-7.65,"ry":0.0,"rw":0.6,"rh":1.4,"t":0}],"s":"744 VT_broking_HIGH_1 59 +","x1":-7.5,"x2":-7.5,"x3":-7.5,"hit":0,"fl":0,"st":0,"c":null},{"hits":[],"hurts":[{"rx":-6.7,"ry":1.3,"rw":0.42,"rh":0.4,"t":3},{"rx":-6.74999952,"ry":0.55,"rw":0.7,"rh":0.98,"t":3},{"rx":-6.74999952,"ry":0.0,"rw":0.7,"rh":0.55,"t":3}],"grabs":[{"rx":-6.64999962,"ry":0.0,"rw":0.5,"rh":1.35,"t":4}],"clips":[{"rx":-6.64999962,"ry":0.0,"rw":0.5,"rh":1.35,"t":0}],"s":"0 STAND 9","x1":-6.39999962,"x2":-6.39999962,"x3":-6.399999,"hit":0,"fl":0,"st":0,"c":null}],"p1":[],"p2":[],"i1":0,"i2":0},
{"f":1849,"p":[{"hits":[],"hurts":[{"rx":-7.8,"ry":1.45,"rw":0.9,"rh":0.4,"t":3},{"rx":-7.8,"ry":0.7,"rw":0.9,"rh":0.75,"t":3},{"rx":-7.8,"ry":0.0,"rw":0.9,"rh":0.7,"t":3}],"grabs":[{"rx":-7.65,"ry":0.0,"rw":0.6,"rh":1.4,"t":4}],"clips":[{"rx":-7.65,"ry":0.0,"rw":0.6,"rh":1.4,"t":0}],"s":"744 VT_broking_HIGH_1 60 +","x1":-7.5,"x2":-7.5,"x3":-7.5,"hit":0,"fl":0,"st":0,"c":null},{"hits":[],"hurts":[{"rx":-6.7,"ry":1.3,"rw":0.42,"rh":0.4,"t":3},{"rx":-6.74999952,"ry":0.55,"rw":0.7,"rh":0.98,"t":3},{"rx":-6.74999952,"ry":0.0,"rw":0.7,"rh":0.55,"t":3}],"grabs":[{"rx":-6.64999962,"ry":0.0,"rw":0.5,"rh":1.35,"t":4}],"clips":[{"rx":-6.64999962,"ry":0.0,"rw":0.5,"rh":1.35,"t":0}],"s":"0 STAND 10","x1":-6.39999962,"x2":-6.39999962,"x3":-6.399999,"hit":0,"fl":0,"st":0,"c":null}],"p1":[],"p2":[],"i1":0,"i2":0},
{"f":1850,"p":[{"hits":[],"hurts":[{"rx":-7.47,"ry":1.45,"rw":0.45,"rh":0.35,"t":3},{"rx":-7.82,"ry":0.6,"rw":0.8,"rh":0.95,"t":3},{"rx":-7.82,"ry":0.0,"rw":0.8,"rh":0.6,"t":3}],"grabs":[{"rx":-7.72,"ry":0.0,"rw":0.6,"rh":1.4,"t":4}],"clips":[{"rx":-7.72,"ry":0.0,"rw":0.6,"rh":1.4,"t":0}],"s":"0 STAND 1","x1":-7.5,"x2":-7.5,"x3":-7.5,"hit":0,"fl":0,"st":0,"c":null},{"hits":[],"hurts":[{"rx":-6.7,"ry":1.3,"rw":0.42,"rh":0.4,"t":3},{"rx":-6.74999952,"ry":0.55,"rw":0.7,"rh":0.98,"t":3},{"rx":-6.74999952,"ry":0.0,"rw":0.7,"rh":0.55,"t":3}],"grabs":[{"rx":-6.64999962,"ry":0.0,"rw":0.5,"rh":1.35,"t":4}],"clips":[{"rx":-6.64999962,"ry":0.0,"rw":0.5,"rh":1.35,"t":0}],"s":"0 STAND 11","x1":-6.39999962,"x2":-6.39999962,"x3":-6.399999,"hit":0,"fl":0,"st":0,"c":null}],"p1":[],"p2":[],"i1":0,"i2":0},
{"f":1851,"p":[{"hits":[],"hurts":[{"rx":-7.47,"ry":1.45,"rw":0.45,"rh":0.35,"t":3},{"rx":-7.82,"ry":0.6,"rw":0.8,"rh":0.95,"t":3},{"rx":-7.82,"ry":0.0,"rw":0.8,"rh":0.6,"t":3}],"grabs":[{"rx":-7.72,"ry":0.0,"rw":0.6,"rh":1.4,"t":4}],"clips":[{"rx":-7.72,"ry":0.0,"rw":0.6,"rh":1.4,"t":0}],"s":"0 STAND 2","x1":-7.5,"x2":-7.5,"x3":-7.5,"hit":0,"fl":0,"st":0,"c":null},{"hits":[],"hurts":[{"rx":-6.7,"ry":1.3,"rw":0.42,"rh":0.4,"t":3},{"rx":-6.74999952,"ry":0.55,"rw":0.7,"rh":0.98,"t":3},{"rx":-6.74999952,"ry":0.0,"rw":0.7,"rh":0.55,"t":3}],"grabs":[{"rx":-6.64999962,"ry":0.0,"rw":0.5,"rh":1.35,"t":4}],"clips":[{"rx":-6.64999962,"ry":0.0,"rw":0.5,"rh":1.35,"t":0}],"s":"0 STAND 12","x1":-6.39999962,"x2":-6.39999962,"x3":-6.399999,"hit":0,"fl":0,"st":0,"c":null}],"p1":[],"p2":[],"i1":0,"i2":0},
{"f":1852,"p":[{"hits":[],"hurts":[{"rx":-7.47,"ry":1.45,"rw":0.45,"rh":0.35,"t":3},{"rx":-7.82,"ry":0.6,"rw":0.8,"rh":0.95,"t":3},{"rx":-7.82,"ry":0.0,"rw":0.8,"rh":0.6,"t":3}],"grabs":[{"rx":-7.72,"ry":0.0,"rw":0.6,"rh":1.4,"t":4}],"clips":[{"rx":-7.72,"ry":0.0,"rw":0.6,"rh":1.4,"t":0}],"s":"0 STAND 3","x1":-7.5,"x2":-7.5,"x3":-7.5,"hit":0,"fl":0,"st":0,"c":null},{"hits":[],"hurts":[{"rx":-6.7,"ry":1.3,"rw":0.42,"rh":0.4,"t":3},{"rx":-6.74999952,"ry":0.55,"rw":0.7,"rh":0.98,"t":3},{"rx":-6.74999952,"ry":0.0,"rw":0.7,"rh":0.55,"t":3}],"grabs":[{"rx":-6.64999962,"ry":0.0,"rw":0.5,"rh":1.35,"t":4}],"clips":[{"rx":-6.64999962,"ry":0.0,"rw":0.5,"rh":1.35,"t":0}],"s":"0 STAND 13","x1":-6.39999962,"x2":-6.39999962,"x3":-6.399999,"hit":0,"fl":0,"st":0,"c":null}],"p1":[],"p2":[],"i1":0,"i2":0},
{"f":1853,"p":[{"hits":[],"hurts":[{"rx":-7.47,"ry":1.45,"rw":0.45,"rh":0.35,"t":3},{"rx":-7.82,"ry":0.6,"rw":0.8,"rh":0.95,"t":3},{"rx":-7.82,"ry":0.0,"rw":0.8,"rh":0.6,"t":3}],"grabs":[{"rx":-7.72,"ry":0.0,"rw":0.6,"rh":1.4,"t":4}],"clips":[{"rx":-7.72,"ry":0.0,"rw":0.6,"rh":1.4,"t":0}],"s":"0 STAND 4","x1":-7.5,"x2":-7.5,"x3":-7.5,"hit":0,"fl":0,"st":0,"c":null},{"hits":[],"hurts":[{"rx":-6.7,"ry":1.3,"rw":0.42,"rh":0.4,"t":3},{"rx":-6.74999952,"ry":0.55,"rw":0.7,"rh":0.98,"t":3},{"rx":-6.74999952,"ry":0.0,"rw":0.7,"rh":0.55,"t":3}],"grabs":[{"rx":-6.64999962,"ry":0.0,"rw":0.5,"rh":1.35,"t":4}],"clips":[{"rx":-6.64999962,"ry":0.0,"rw":0.5,"rh":1.35,"t":0}],"s":"0 STAND 14","x1":-6.39999962,"x2":-6.39999962,"x3":-6.399999,"hit":0,"fl":0,"st":0,"c":null}],"p1":[],"p2":[],"i1":0,"i2":0},
{"f":1854,"p":[{"hits":[],"hurts":[{"rx":-7.47,"ry":1.45,"rw":0.45,"rh":0.35,"t":3},{"rx":-7.82,"ry":0.6,"rw":0.8,"rh":0.95,"t":3},{"rx":-7.82,"ry":0.0,"rw":0.8,"rh":0.6,"t":3}],"grabs":[{"rx":-7.72,"ry":0.0,"rw":0.6,"rh":1.4,"t":4}],"clips":[{"rx":-7.72,"ry":0.0,"rw":0.6,"rh":1.4,"t":0}],"s":"0 STAND 5","x1":-7.5,"x2":-7.5,"x3":-7.5,"hit":0,"fl":0,"st":0,"c":null},{"hits":[],"hurts":[{"rx":-6.7,"ry":1.3,"rw":0.42,"rh":0.4,"t":3},{"rx":-6.74999952,"ry":0.55,"rw":0.7,"rh":0.98,"t":3},{"rx":-6.74999952,"ry":0.0,"rw":0.7,"rh":0.55,"t":3}],"grabs":[{"rx":-6.64999962,"ry":0.0,"rw":0.5,"rh":1.35,"t":4}],"clips":[{"rx":-6.64999962,"ry":0.0,"rw":0.5,"rh":1.35,"t":0}],"s":"0 STAND 15","x1":-6.39999962,"x2":-6.39999962,"x3":-6.399999,"hit":0,"fl":0,"st":0,"c":null}],"p1":[],"p2":[],"i1":0,"i2":0},
{"f":1855,"p":[{"hits":[],"hurts":[{"rx":-7.47,"ry":1.45,"rw":0.45,"rh":0.35,"t":3},{"rx":-7.82,"ry":0.6,"rw":0.8,"rh":0.95,"t":3},{"rx":-7.82,"ry":0.0,"rw":0.8,"rh":0.6,"t":3}],"grabs":[{"rx":-7.72,"ry":0.0,"rw":0.6,"rh":1.4,"t":4}],"clips":[{"rx":-7.72,"ry":0.0,"rw":0.6,"rh":1.4,"t":0}],"s":"0 STAND 6","x1":-7.5,"x2":-7.5,"x3":-7.5,"hit":0,"fl":0,"st":0,"c":null},{"hits":[],"hurts":[{"rx":-6.7,"ry":1.3,"rw":0.42,"rh":0.4,"t":3},{"rx":-6.74999952,"ry":0.55,"rw":0.7,"rh":0.98,"t":3},{"rx":-6.74999952,"ry":0.0,"rw":0.7,"rh":0.55,"t":3}],"grabs":[{"rx":-6.64999962,"ry":0.0,"rw":0.5,"rh":1.35,"t":4}],"clips":[{"rx":-6.64999962,"ry":0.0,"rw":0.5,"rh":1.35,"t":0}],"s":"0 STAND 16","x1":-6.39999962,"x2":-6.39999962,"x3":-6.399999,"hit":0,"fl":0,"st":0,"c":null}],"p1":[],"p2":[],"i1":0,"i2":0}]